Workbook

Sheet abbeygate_price_list
A1: Product ID | B1: Product Name | C1: Ancillary | D1: SKU | E1: Old SKU | F1: Sales Code? | G1: Size | H1: Colour | I1: Page Type | J1: Paper Type | K1: Corner Size | L1: Additional Corner Price | M1: Sales Price (Including VAT) | N1: Tiered Price Customisation (Qty:Price;) (Excluding VAT) | O1: Qty 1 | P1: Qty 10 | Q1: Qty 25 | R1: Qty 50 | S1: Qty 100 | T1: Qty 250 | U1: Qty 500 | V1: Qty 750 | W1: Qty 1000 | X1: Tiered Price Including UV Printing (Qty:Price;) (Excluding VAT) | Y1: Qty 1 | Z1: Qty 10 | AA1: Qty 25 | AB1: Qty 50 | AC1: Qty 100 | AD1: Qty 250 | AE1: Qty 500 | AF1: Qty 750 | AG1: Qty 1000 | AH1: 2982: B2B Users Regular Price | AI1: 2982: B2B Users Sale Price | AJ1: 2982: B2B Users Tiered Price | AK1: Notes | AL1: Short description | AM1: Description | AN1: Weight (lbs) | AO1: Length (in) | AP1: Width (in) | AQ1: Height (in) | AR1: Categories | AS1: Tags
A2: 337 | B2: Chelsea Leather A5 Notebook, Feint Ruled, Black | C2: Notebook | D2: CL-BK-U-31 | E2: CL-BK-U-31 | F2: CLU31 | G2: A5 | H2: Black | J2: White | K2: 22mm x 22mm | L2: 0.48 | M2: 16.99 | N2: 1:16.23;10:14.81;25:9.76;50:8.10;100:6.77;250:5.62;500:4.82;750:4.71;1000:4.32; | O2: =IFERROR(VALUE(_xlfn.TEXTBEFORE(_xlfn.TEXTAFTER(";"&$N2,";"&SUBSTITUTE(O$1,"Qty ","")&":"),";")),"") -> 16.23 | P2: =IFERROR(VALUE(_xlfn.TEXTBEFORE(_xlfn.TEXTAFTER(";"&$N2,";"&SUBSTITUTE(P$1,"Qty ","")&":"),";")),"") -> 14.81 | Q2: =IFERROR(VALUE(_xlfn.TEXTBEFORE(_xlfn.TEXTAFTER(";"&$N2,";"&SUBSTITUTE(Q$1,"Qty ","")&":"),";")),"") -> 9.76 | R2: =IFERROR(VALUE(_xlfn.TEXTBEFORE(_xlfn.TEXTAFTER(";"&$N2,";"&SUBSTITUTE(R$1,"Qty ","")&":"),";")),"") -> 8.1 | S2: =IFERROR(VALUE(_xlfn.TEXTBEFORE(_xlfn.TEXTAFTER(";"&$N2,";"&SUBSTITUTE(S$1,"Qty ","")&":"),";")),"") -> 6.77 | T2: =IFERROR(VALUE(_xlfn.TEXTBEFORE(_xlfn.TEXTAFTER(";"&$N2,";"&SUBSTITUTE(T$1,"Qty ","")&":"),";")),"") -> 5.62 | U2: =IFERROR(VALUE(_xlfn.TEXTBEFORE(_xlfn.TEXTAFTER(";"&$N2,";"&SUBSTITUTE(U$1,"Qty ","")&":"),";")),"") -> 4.82 | V2: =IFERROR(VALUE(_xlfn.TEXTBEFORE(_xlfn.TEXTAFTER(";"&$N2,";"&SUBSTITUTE(V$1,"Qty ","")&":"),";")),"") -> 4.71 | W2: =IFERROR(VALUE(_xlfn.TEXTBEFORE(_xlfn.TEXTAFTER(";"&$N2,";"&SUBSTITUTE(W$1,"Qty ","")&":"),";")),"") -> 4.32 | X2: {=IF(Y2="","",_xlfn.TEXTJOIN(";",TRUE,SUBSTITUTE($Y$1:$AG$1,"Qty ","")&":"&TEXT(Y2:AG2,"0.00"))&";")} -> 1:21.45;10:19.21;25:13.33;50:11.07;100:9.50;250:8.00;500:7.19;750:7.02;1000:6.57; | Y2: ='Blocking Prices'!$C$15+O2 -> 21.45 | Z2: ='Blocking Prices'!$D$15+P2 -> 19.21 | AA2: ='Blocking Prices'!$E$15+Q2 -> 13.33 | AB2: ='Blocking Prices'!$F$15+R2 -> 11.07 | AC2: ='Blocking Prices'!$G$15+S2 -> 9.5 | AD2: ='Blocking Prices'!$H$15+T2 -> 8 | AE2: ='Blocking Prices'!$I$15+U2 -> 7.19 | AF2: ='Blocking Prices'!$J$15+V2 -> 7.02 | AG2: ='Blocking Prices'!$K$15+W2 -> 6.57 | AL2: <p class="p1">Chelsea Leather range, luxury soft grained real leather?day per page layout.<span class="Apple-converted-space">?</span>Smyth sewn sections for strength and durability printed on white or cream FSC paper.<span class="Apple-converted-space">?</span>Self-colour cotton perimeter stitched flexible cover, ribbon marker, general information pages, forward planners, UK and international holidays, contacts directory, notes page and full colour map section</p>_x000D_\n&nbsp; | AM2: Chelsea Leather range, luxury soft grained real leather day per page layout. Smyth sewn sections for strength and durability printed on white or cream FSC paper. Self-colour cotton perimeter stitched flexible cover, ribbon marker, general information pages, forward planners, UK and international holidays, contacts directory, notes page and full colour map section | AN2: =IFERROR(_xlfn.LET(_xlpm.v,INDEX('product-export-27-8-2026'!$A:$AJ,MATCH($A2,'product-export-27-8-2026'!$A:$A,0),MATCH(AN$1,'product-export-27-8-2026'!$1:$1,0)),IF(_xlpm.v="","",_xlpm.v)),"") | AO2: =IFERROR(_xlfn.LET(_xlpm.v,INDEX('product-export-27-8-2026'!$A:$AJ,MATCH($A2,'product-export-27-8-2026'!$A:$A,0),MATCH(AO$1,'product-export-27-8-2026'!$1:$1,0)),IF(_xlpm.v="","",_xlpm.v)),"") | AP2: =IFERROR(_xlfn.LET(_xlpm.v,INDEX('product-export-27-8-2026'!$A:$AJ,MATCH($A2,'product-export-27-8-2026'!$A:$A,0),MATCH(AP$1,'product-export-27-8-2026'!$1:$1,0)),IF(_xlpm.v="","",_xlpm.v)),"") | AQ2: =IFERROR(_xlfn.LET(_xlpm.v,INDEX('product-export-27-8-2026'!$A:$AJ,MATCH($A2,'product-export-27-8-2026'!$A:$A,0),MATCH(AQ$1,'product-export-27-8-2026'!$1:$1,0)),IF(_xlpm.v="","",_xlpm.v)),"") | AR2: =IFERROR(_xlfn.LET(_xlpm.v,INDEX('product-export-27-8-2026'!$A:$AJ,MATCH($A2,'product-export-27-8-2026'!$A:$A,0),MATCH(AR$1,'product-export-27-8-2026'!$1:$1,0)),IF(_xlpm.v="","",_xlpm.v)),"") -> Notebooks > A5 Notebooks, Chelsea Collection, Foil blocked, Notebooks, Notebooks > Real Leather Notebooks | AS2: =IFERROR(_xlfn.LET(_xlpm.v,INDEX('product-export-27-8-2026'!$A:$AJ,MATCH($A2,'product-export-27-8-2026'!$A:$A,0),MATCH(AS$1,'product-export-27-8-2026'!$1:$1,0)),IF(_xlpm.v="","",_xlpm.v)),"") -> Chelsea-Leather-A5-Notebook-Feint-Ruled
A3: 600 | B3: Dorchester Horizon Pocket, Week to View, Black-Black | C3: Diary | D3: HZ-BK/BK-U-095 | E3: HZ-BK/BK-U-095 | F3: HZ96U | G3: Pocket | H3: Black-Black | I3: Week to View | J3: White | K3: 18mm x 18mm | L3: 0.42 | M3: 9.99 | N3: 1:9.74;10:9.33;25:5.30;50:3.77;100:3.28;250:3.07;500:2.95;750:2.77;1000:2.63; | O3: =IFERROR(VALUE(_xlfn.TEXTBEFORE(_xlfn.TEXTAFTER(";"&$N3,";"&SUBSTITUTE(O$1,"Qty ","")&":"),";")),"") -> 9.74 | P3: =IFERROR(VALUE(_xlfn.TEXTBEFORE(_xlfn.TEXTAFTER(";"&$N3,";"&SUBSTITUTE(P$1,"Qty ","")&":"),";")),"") -> 9.33 | Q3: =IFERROR(VALUE(_xlfn.TEXTBEFORE(_xlfn.TEXTAFTER(";"&$N3,";"&SUBSTITUTE(Q$1,"Qty ","")&":"),";")),"") -> 5.3 | R3: =IFERROR(VALUE(_xlfn.TEXTBEFORE(_xlfn.TEXTAFTER(";"&$N3,";"&SUBSTITUTE(R$1,"Qty ","")&":"),";")),"") -> 3.77 | S3: =IFERROR(VALUE(_xlfn.TEXTBEFORE(_xlfn.TEXTAFTER(";"&$N3,";"&SUBSTITUTE(S$1,"Qty ","")&":"),";")),"") -> 3.28 | T3: =IFERROR(VALUE(_xlfn.TEXTBEFORE(_xlfn.TEXTAFTER(";"&$N3,";"&SUBSTITUTE(T$1,"Qty ","")&":"),";")),"") -> 3.07 | U3: =IFERROR(VALUE(_xlfn.TEXTBEFORE(_xlfn.TEXTAFTER(";"&$N3,";"&SUBSTITUTE(U$1,"Qty ","")&":"),";")),"") -> 2.95 | V3: =IFERROR(VALUE(_xlfn.TEXTBEFORE(_xlfn.TEXTAFTER(";"&$N3,";"&SUBSTITUTE(V$1,"Qty ","")&":"),";")),"") -> 2.77 | W3: =IFERROR(VALUE(_xlfn.TEXTBEFORE(_xlfn.TEXTAFTER(";"&$N3,";"&SUBSTITUTE(W$1,"Qty ","")&":"),";")),"") -> 2.63 | X3: {=IF(Y3="","",_xlfn.TEXTJOIN(";",TRUE,SUBSTITUTE($Y$1:$AG$1,"Qty ","")&":"&TEXT(Y3:AG3,"0.00"))&";")} -> 1:13.16;10:11.96;25:7.13;50:5.27;100:4.66;250:4.33;500:4.15;750:3.94;1000:3.77; | Y3: ='Blocking Prices'!$C$14+O3 -> 13.16 | Z3: ='Blocking Prices'!$D$14+P3 -> 11.96 | AA3: ='Blocking Prices'!$E$14+Q3 -> 7.13 | AB3: ='Blocking Prices'!$F$14+R3 -> 5.27 | AC3: ='Blocking Prices'!$G$14+S3 -> 4.66 | AD3: ='Blocking Prices'!$H$14+T3 -> 4.33 | AE3: ='Blocking Prices'!$I$14+U3 -> 4.15 | AF3: ='Blocking Prices'!$J$14+V3 -> 3.94 | AG3: ='Blocking Prices'!$K$14+W3 -> 3.77 | AL3: <span data-sheets-root="1">Stay on top of your week with the Dorchester Horizon Pocket Diary - Week to View. Featuring a soft Vegan Leather Horizon design, white paper, and a ribbon marker, this compact diary combines style and practicality for easy weekly planning.</span>_x000D_\n<div class="trade-info">_x000D_\n<div class="trade-info__item">_x000D_\n<div class="product-popup-modal__text rte">_x000D_\n_x000D_\n&nbsp;_x000D_\n_x000D_\n</div>_x000D_\n</div>_x000D_\n</div> | AN3: =IFERROR(_xlfn.LET(_xlpm.v,INDEX('product-export-27-8-2026'!$A:$AJ,MATCH($A3,'product-export-27-8-2026'!$A:$A,0),MATCH(AN$1,'product-export-27-8-2026'!$1:$1,0)),IF(_xlpm.v="","",_xlpm.v)),"") | AO3: =IFERROR(_xlfn.LET(_xlpm.v,INDEX('product-export-27-8-2026'!$A:$AJ,MATCH($A3,'product-export-27-8-2026'!$A:$A,0),MATCH(AO$1,'product-export-27-8-2026'!$1:$1,0)),IF(_xlpm.v="","",_xlpm.v)),"") | AP3: =IFERROR(_xlfn.LET(_xlpm.v,INDEX('product-export-27-8-2026'!$A:$AJ,MATCH($A3,'product-export-27-8-2026'!$A:$A,0),MATCH(AP$1,'product-export-27-8-2026'!$1:$1,0)),IF(_xlpm.v="","",_xlpm.v)),"") | AQ3: =IFERROR(_xlfn.LET(_xlpm.v,INDEX('product-export-27-8-2026'!$A:$AJ,MATCH($A3,'product-export-27-8-2026'!$A:$A,0),MATCH(AQ$1,'product-export-27-8-2026'!$1:$1,0)),IF(_xlpm.v="","",_xlpm.v)),"") | AR3: =IFERROR(_xlfn.LET(_xlpm.v,INDEX('product-export-27-8-2026'!$A:$AJ,MATCH($A3,'product-export-27-8-2026'!$A:$A,0),MATCH(AR$1,'product-export-27-8-2026'!$1:$1,0)),IF(_xlpm.v="","",_xlpm.v)),"") -> Diaries, Dorchester Collection, Diaries > Pocket Diaries | AS3: =IFERROR(_xlfn.LET(_xlpm.v,INDEX('product-export-27-8-2026'!$A:$AJ,MATCH($A3,'product-export-27-8-2026'!$A:$A,0),MATCH(AS$1,'product-export-27-8-2026'!$1:$1,0)),IF(_xlpm.v="","",_xlpm.v)),"") -> Dorchester-Horizon-Pocket-Week-to-View
A4: 604 | B4: Dorchester Horizon Pocket, Week to View, Black-Grey | C4: Diary | D4: HZ-BK/GY-U-095 | E4: HZ-BK/GY-U-095 | F4: HZ96U | G4: Pocket | H4: Black-Grey | I4: Week to View | J4: White | K4: 18mm x 18mm | L4: 0.42 | M4: 9.99 | N4: 1:9.74;10:9.33;25:5.30;50:3.77;100:3.28;250:3.07;500:2.95;750:2.77;1000:2.63; | O4: =IFERROR(VALUE(_xlfn.TEXTBEFORE(_xlfn.TEXTAFTER(";"&$N4,";"&SUBSTITUTE(O$1,"Qty ","")&":"),";")),"") -> 9.74 | P4: =IFERROR(VALUE(_xlfn.TEXTBEFORE(_xlfn.TEXTAFTER(";"&$N4,";"&SUBSTITUTE(P$1,"Qty ","")&":"),";")),"") -> 9.33 | Q4: =IFERROR(VALUE(_xlfn.TEXTBEFORE(_xlfn.TEXTAFTER(";"&$N4,";"&SUBSTITUTE(Q$1,"Qty ","")&":"),";")),"") -> 5.3 | R4: =IFERROR(VALUE(_xlfn.TEXTBEFORE(_xlfn.TEXTAFTER(";"&$N4,";"&SUBSTITUTE(R$1,"Qty ","")&":"),";")),"") -> 3.77 | S4: =IFERROR(VALUE(_xlfn.TEXTBEFORE(_xlfn.TEXTAFTER(";"&$N4,";"&SUBSTITUTE(S$1,"Qty ","")&":"),";")),"") -> 3.28 | T4: =IFERROR(VALUE(_xlfn.TEXTBEFORE(_xlfn.TEXTAFTER(";"&$N4,";"&SUBSTITUTE(T$1,"Qty ","")&":"),";")),"") -> 3.07 | U4: =IFERROR(VALUE(_xlfn.TEXTBEFORE(_xlfn.TEXTAFTER(";"&$N4,";"&SUBSTITUTE(U$1,"Qty ","")&":"),";")),"") -> 2.95 | V4: =IFERROR(VALUE(_xlfn.TEXTBEFORE(_xlfn.TEXTAFTER(";"&$N4,";"&SUBSTITUTE(V$1,"Qty ","")&":"),";")),"") -> 2.77 | W4: =IFERROR(VALUE(_xlfn.TEXTBEFORE(_xlfn.TEXTAFTER(";"&$N4,";"&SUBSTITUTE(W$1,"Qty ","")&":"),";")),"") -> 2.63 | X4: {=IF(Y4="","",_xlfn.TEXTJOIN(";",TRUE,SUBSTITUTE($Y$1:$AG$1,"Qty ","")&":"&TEXT(Y4:AG4,"0.00"))&";")} -> 1:13.16;10:11.96;25:7.13;50:5.27;100:4.66;250:4.33;500:4.15;750:3.94;1000:3.77; | Y4: ='Blocking Prices'!$C$14+O4 -> 13.16 | Z4: ='Blocking Prices'!$D$14+P4 -> 11.96 | AA4: ='Blocking Prices'!$E$14+Q4 -> 7.13 | AB4: ='Blocking Prices'!$F$14+R4 -> 5.27 | AC4: ='Blocking Prices'!$G$14+S4 -> 4.66 | AD4: ='Blocking Prices'!$H$14+T4 -> 4.33 | AE4: ='Blocking Prices'!$I$14+U4 -> 4.15 | AF4: ='Blocking Prices'!$J$14+V4 -> 3.94 | AG4: ='Blocking Prices'!$K$14+W4 -> 3.77 | AL4: <span data-sheets-root="1">Stay on top of your week with the Dorchester Horizon Pocket Diary - Week to View. Featuring a soft Vegan Leather Horizon design, white paper, and a ribbon marker, this compact diary combines style and practicality for easy weekly planning.</span>_x000D_\n<div class="trade-info">_x000D_\n<div class="trade-info__item">_x000D_\n<div class="product-popup-modal__text rte">_x000D_\n_x000D_\n&nbsp;_x000D_\n_x000D_\n</div>_x000D_\n</div>_x000D_\n</div> | AN4: =IFERROR(_xlfn.LET(_xlpm.v,INDEX('product-export-27-8-2026'!$A:$AJ,MATCH($A4,'product-export-27-8-2026'!$A:$A,0),MATCH(AN$1,'product-export-27-8-2026'!$1:$1,0)),IF(_xlpm.v="","",_xlpm.v)),"") | AO4: =IFERROR(_xlfn.LET(_xlpm.v,INDEX('product-export-27-8-2026'!$A:$AJ,MATCH($A4,'product-export-27-8-2026'!$A:$A,0),MATCH(AO$1,'product-export-27-8-2026'!$1:$1,0)),IF(_xlpm.v="","",_xlpm.v)),"") | AP4: =IFERROR(_xlfn.LET(_xlpm.v,INDEX('product-export-27-8-2026'!$A:$AJ,MATCH($A4,'product-export-27-8-2026'!$A:$A,0),MATCH(AP$1,'product-export-27-8-2026'!$1:$1,0)),IF(_xlpm.v="","",_xlpm.v)),"") | AQ4: =IFERROR(_xlfn.LET(_xlpm.v,INDEX('product-export-27-8-2026'!$A:$AJ,MATCH($A4,'product-export-27-8-2026'!$A:$A,0),MATCH(AQ$1,'product-export-27-8-2026'!$1:$1,0)),IF(_xlpm.v="","",_xlpm.v)),"") | AR4: =IFERROR(_xlfn.LET(_xlpm.v,INDEX('product-export-27-8-2026'!$A:$AJ,MATCH($A4,'product-export-27-8-2026'!$A:$A,0),MATCH(AR$1,'product-export-27-8-2026'!$1:$1,0)),IF(_xlpm.v="","",_xlpm.v)),"") -> Diaries, Dorchester Collection, Diaries > Pocket Diaries | AS4: =IFERROR(_xlfn.LET(_xlpm.v,INDEX('product-export-27-8-2026'!$A:$AJ,MATCH($A4,'product-export-27-8-2026'!$A:$A,0),MATCH(AS$1,'product-export-27-8-2026'!$1:$1,0)),IF(_xlpm.v="","",_xlpm.v)),"") -> Dorchester-Horizon-Pocket-Week-to-View
A5: 607 | B5: Dorchester Horizon Pocket, Week to View, Black-Red | C5: Diary | D5: HZ-BK/RD-U-095 | E5: HZ-BK/RD-U-095 | F5: HZ96U | G5: Pocket | H5: Black-Red | I5: Week to View | J5: White | K5: 18mm x 18mm | L5: 0.42 | M5: 9.99 | N5: 1:9.74;10:9.33;25:5.30;50:3.77;100:3.28;250:3.07;500:2.95;750:2.77;1000:2.63; | O5: =IFERROR(VALUE(_xlfn.TEXTBEFORE(_xlfn.TEXTAFTER(";"&$N5,";"&SUBSTITUTE(O$1,"Qty ","")&":"),";")),"") -> 9.74 | P5: =IFERROR(VALUE(_xlfn.TEXTBEFORE(_xlfn.TEXTAFTER(";"&$N5,";"&SUBSTITUTE(P$1,"Qty ","")&":"),";")),"") -> 9.33 | Q5: =IFERROR(VALUE(_xlfn.TEXTBEFORE(_xlfn.TEXTAFTER(";"&$N5,";"&SUBSTITUTE(Q$1,"Qty ","")&":"),";")),"") -> 5.3 | R5: =IFERROR(VALUE(_xlfn.TEXTBEFORE(_xlfn.TEXTAFTER(";"&$N5,";"&SUBSTITUTE(R$1,"Qty ","")&":"),";")),"") -> 3.77 | S5: =IFERROR(VALUE(_xlfn.TEXTBEFORE(_xlfn.TEXTAFTER(";"&$N5,";"&SUBSTITUTE(S$1,"Qty ","")&":"),";")),"") -> 3.28 | T5: =IFERROR(VALUE(_xlfn.TEXTBEFORE(_xlfn.TEXTAFTER(";"&$N5,";"&SUBSTITUTE(T$1,"Qty ","")&":"),";")),"") -> 3.07 | U5: =IFERROR(VALUE(_xlfn.TEXTBEFORE(_xlfn.TEXTAFTER(";"&$N5,";"&SUBSTITUTE(U$1,"Qty ","")&":"),";")),"") -> 2.95 | V5: =IFERROR(VALUE(_xlfn.TEXTBEFORE(_xlfn.TEXTAFTER(";"&$N5,";"&SUBSTITUTE(V$1,"Qty ","")&":"),";")),"") -> 2.77 | W5: =IFERROR(VALUE(_xlfn.TEXTBEFORE(_xlfn.TEXTAFTER(";"&$N5,";"&SUBSTITUTE(W$1,"Qty ","")&":"),";")),"") -> 2.63 | X5: {=IF(Y5="","",_xlfn.TEXTJOIN(";",TRUE,SUBSTITUTE($Y$1:$AG$1,"Qty ","")&":"&TEXT(Y5:AG5,"0.00"))&";")} -> 1:13.16;10:11.96;25:7.13;50:5.27;100:4.66;250:4.33;500:4.15;750:3.94;1000:3.77; | Y5: ='Blocking Prices'!$C$14+O5 -> 13.16 | Z5: ='Blocking Prices'!$D$14+P5 -> 11.96 | AA5: ='Blocking Prices'!$E$14+Q5 -> 7.13 | AB5: ='Blocking Prices'!$F$14+R5 -> 5.27 | AC5: ='Blocking Prices'!$G$14+S5 -> 4.66 | AD5: ='Blocking Prices'!$H$14+T5 -> 4.33 | AE5: ='Blocking Prices'!$I$14+U5 -> 4.15 | AF5: ='Blocking Prices'!$J$14+V5 -> 3.94 | AG5: ='Blocking Prices'!$K$14+W5 -> 3.77 | AL5: <span data-sheets-root="1">Stay on top of your week with the Dorchester Horizon Pocket Diary - Week to View. Featuring a soft Vegan Leather Horizon design, white paper, and a ribbon marker, this compact diary combines style and practicality for easy weekly planning.</span>_x000D_\n<div class="trade-info">_x000D_\n<div class="trade-info__item">_x000D_\n<div class="product-popup-modal__text rte">_x000D_\n_x000D_\n&nbsp;_x000D_\n_x000D_\n</div>_x000D_\n</div>_x000D_\n</div> | AN5: =IFERROR(_xlfn.LET(_xlpm.v,INDEX('product-export-27-8-2026'!$A:$AJ,MATCH($A5,'product-export-27-8-2026'!$A:$A,0),MATCH(AN$1,'product-export-27-8-2026'!$1:$1,0)),IF(_xlpm.v="","",_xlpm.v)),"") | AO5: =IFERROR(_xlfn.LET(_xlpm.v,INDEX('product-export-27-8-2026'!$A:$AJ,MATCH($A5,'product-export-27-8-2026'!$A:$A,0),MATCH(AO$1,'product-export-27-8-2026'!$1:$1,0)),IF(_xlpm.v="","",_xlpm.v)),"") | AP5: =IFERROR(_xlfn.LET(_xlpm.v,INDEX('product-export-27-8-2026'!$A:$AJ,MATCH($A5,'product-export-27-8-2026'!$A:$A,0),MATCH(AP$1,'product-export-27-8-2026'!$1:$1,0)),IF(_xlpm.v="","",_xlpm.v)),"") | AQ5: =IFERROR(_xlfn.LET(_xlpm.v,INDEX('product-export-27-8-2026'!$A:$AJ,MATCH($A5,'product-export-27-8-2026'!$A:$A,0),MATCH(AQ$1,'product-export-27-8-2026'!$1:$1,0)),IF(_xlpm.v="","",_xlpm.v)),"") | AR5: =IFERROR(_xlfn.LET(_xlpm.v,INDEX('product-export-27-8-2026'!$A:$AJ,MATCH($A5,'product-export-27-8-2026'!$A:$A,0),MATCH(AR$1,'product-export-27-8-2026'!$1:$1,0)),IF(_xlpm.v="","",_xlpm.v)),"") -> Diaries, Dorchester Collection, Diaries > Pocket Diaries | AS5: =IFERROR(_xlfn.LET(_xlpm.v,INDEX('product-export-27-8-2026'!$A:$AJ,MATCH($A5,'product-export-27-8-2026'!$A:$A,0),MATCH(AS$1,'product-export-27-8-2026'!$1:$1,0)),IF(_xlpm.v="","",_xlpm.v)),"") -> Dorchester-Horizon-Pocket-Week-to-View
A6: 609 | B6: Dorchester Horizon Pocket, Week to View, Black-Yellow | C6: Diary | D6: HZ-BK/YE-U-095 | E6: HZ-BK/YE-U-095 | F6: HZ96U | G6: Pocket | H6: Black-Yellow | I6: Week to View | J6: White | K6: 18mm x 18mm | L6: 0.42 | M6: 9.99 | N6: 1:9.74;10:9.33;25:5.30;50:3.77;100:3.28;250:3.07;500:2.95;750:2.77;1000:2.63; | O6: =IFERROR(VALUE(_xlfn.TEXTBEFORE(_xlfn.TEXTAFTER(";"&$N6,";"&SUBSTITUTE(O$1,"Qty ","")&":"),";")),"") -> 9.74 | P6: =IFERROR(VALUE(_xlfn.TEXTBEFORE(_xlfn.TEXTAFTER(";"&$N6,";"&SUBSTITUTE(P$1,"Qty ","")&":"),";")),"") -> 9.33 | Q6: =IFERROR(VALUE(_xlfn.TEXTBEFORE(_xlfn.TEXTAFTER(";"&$N6,";"&SUBSTITUTE(Q$1,"Qty ","")&":"),";")),"") -> 5.3 | R6: =IFERROR(VALUE(_xlfn.TEXTBEFORE(_xlfn.TEXTAFTER(";"&$N6,";"&SUBSTITUTE(R$1,"Qty ","")&":"),";")),"") -> 3.77 | S6: =IFERROR(VALUE(_xlfn.TEXTBEFORE(_xlfn.TEXTAFTER(";"&$N6,";"&SUBSTITUTE(S$1,"Qty ","")&":"),";")),"") -> 3.28 | T6: =IFERROR(VALUE(_xlfn.TEXTBEFORE(_xlfn.TEXTAFTER(";"&$N6,";"&SUBSTITUTE(T$1,"Qty ","")&":"),";")),"") -> 3.07 | U6: =IFERROR(VALUE(_xlfn.TEXTBEFORE(_xlfn.TEXTAFTER(";"&$N6,";"&SUBSTITUTE(U$1,"Qty ","")&":"),";")),"") -> 2.95 | V6: =IFERROR(VALUE(_xlfn.TEXTBEFORE(_xlfn.TEXTAFTER(";"&$N6,";"&SUBSTITUTE(V$1,"Qty ","")&":"),";")),"") -> 2.77 | W6: =IFERROR(VALUE(_xlfn.TEXTBEFORE(_xlfn.TEXTAFTER(";"&$N6,";"&SUBSTITUTE(W$1,"Qty ","")&":"),";")),"") -> 2.63 | X6: {=IF(Y6="","",_xlfn.TEXTJOIN(";",TRUE,SUBSTITUTE($Y$1:$AG$1,"Qty ","")&":"&TEXT(Y6:AG6,"0.00"))&";")} -> 1:13.16;10:11.96;25:7.13;50:5.27;100:4.66;250:4.33;500:4.15;750:3.94;1000:3.77; | Y6: ='Blocking Prices'!$C$14+O6 -> 13.16 | Z6: ='Blocking Prices'!$D$14+P6 -> 11.96 | AA6: ='Blocking Prices'!$E$14+Q6 -> 7.13 | AB6: ='Blocking Prices'!$F$14+R6 -> 5.27 | AC6: ='Blocking Prices'!$G$14+S6 -> 4.66 | AD6: ='Blocking Prices'!$H$14+T6 -> 4.33 | AE6: ='Blocking Prices'!$I$14+U6 -> 4.15 | AF6: ='Blocking Prices'!$J$14+V6 -> 3.94 | AG6: ='Blocking Prices'!$K$14+W6 -> 3.77 | AL6: <span data-sheets-root="1">Stay on top of your week with the Dorchester Horizon Pocket Diary - Week to View. Featuring a soft Vegan Leather Horizon design, white paper, and a ribbon marker, this compact diary combines style and practicality for easy weekly planning.</span>_x000D_\n<div class="trade-info">_x000D_\n<div class="trade-info__item">_x000D_\n<div class="product-popup-modal__text rte">_x000D_\n_x000D_\n&nbsp;_x000D_\n_x000D_\n</div>_x000D_\n</div>_x000D_\n</div> | AN6: =IFERROR(_xlfn.LET(_xlpm.v,INDEX('product-export-27-8-2026'!$A:$AJ,MATCH($A6,'product-export-27-8-2026'!$A:$A,0),MATCH(AN$1,'product-export-27-8-2026'!$1:$1,0)),IF(_xlpm.v="","",_xlpm.v)),"") | AO6: =IFERROR(_xlfn.LET(_xlpm.v,INDEX('product-export-27-8-2026'!$A:$AJ,MATCH($A6,'product-export-27-8-2026'!$A:$A,0),MATCH(AO$1,'product-export-27-8-2026'!$1:$1,0)),IF(_xlpm.v="","",_xlpm.v)),"") | AP6: =IFERROR(_xlfn.LET(_xlpm.v,INDEX('product-export-27-8-2026'!$A:$AJ,MATCH($A6,'product-export-27-8-2026'!$A:$A,0),MATCH(AP$1,'product-export-27-8-2026'!$1:$1,0)),IF(_xlpm.v="","",_xlpm.v)),"") | AQ6: =IFERROR(_xlfn.LET(_xlpm.v,INDEX('product-export-27-8-2026'!$A:$AJ,MATCH($A6,'product-export-27-8-2026'!$A:$A,0),MATCH(AQ$1,'product-export-27-8-2026'!$1:$1,0)),IF(_xlpm.v="","",_xlpm.v)),"") | AR6: =IFERROR(_xlfn.LET(_xlpm.v,INDEX('product-export-27-8-2026'!$A:$AJ,MATCH($A6,'product-export-27-8-2026'!$A:$A,0),MATCH(AR$1,'product-export-27-8-2026'!$1:$1,0)),IF(_xlpm.v="","",_xlpm.v)),"") -> Diaries, Dorchester Collection, Diaries > Pocket Diaries | AS6: =IFERROR(_xlfn.LET(_xlpm.v,INDEX('product-export-27-8-2026'!$A:$AJ,MATCH($A6,'product-export-27-8-2026'!$A:$A,0),MATCH(AS$1,'product-export-27-8-2026'!$1:$1,0)),IF(_xlpm.v="","",_xlpm.v)),"") -> Dorchester-Horizon-Pocket-Week-to-View
A7: 611 | B7: Dorchester Horizon Pocket, Week to View, Green- Green | C7: Diary | D7: HZ-GN/GN-U-095 | E7: HZ-GN/GN-U-095 | F7: HZ96U | G7: Pocket | H7: Green-Green | I7: Week to View | J7: White | K7: 18mm x 18mm | L7: 0.42 | M7: 9.99 | N7: 1:9.74;10:9.33;25:5.30;50:3.77;100:3.28;250:3.07;500:2.95;750:2.77;1000:2.63; | O7: =IFERROR(VALUE(_xlfn.TEXTBEFORE(_xlfn.TEXTAFTER(";"&$N7,";"&SUBSTITUTE(O$1,"Qty ","")&":"),";")),"") -> 9.74 | P7: =IFERROR(VALUE(_xlfn.TEXTBEFORE(_xlfn.TEXTAFTER(";"&$N7,";"&SUBSTITUTE(P$1,"Qty ","")&":"),";")),"") -> 9.33 | Q7: =IFERROR(VALUE(_xlfn.TEXTBEFORE(_xlfn.TEXTAFTER(";"&$N7,";"&SUBSTITUTE(Q$1,"Qty ","")&":"),";")),"") -> 5.3 | R7: =IFERROR(VALUE(_xlfn.TEXTBEFORE(_xlfn.TEXTAFTER(";"&$N7,";"&SUBSTITUTE(R$1,"Qty ","")&":"),";")),"") -> 3.77 | S7: =IFERROR(VALUE(_xlfn.TEXTBEFORE(_xlfn.TEXTAFTER(";"&$N7,";"&SUBSTITUTE(S$1,"Qty ","")&":"),";")),"") -> 3.28 | T7: =IFERROR(VALUE(_xlfn.TEXTBEFORE(_xlfn.TEXTAFTER(";"&$N7,";"&SUBSTITUTE(T$1,"Qty ","")&":"),";")),"") -> 3.07 | U7: =IFERROR(VALUE(_xlfn.TEXTBEFORE(_xlfn.TEXTAFTER(";"&$N7,";"&SUBSTITUTE(U$1,"Qty ","")&":"),";")),"") -> 2.95 | V7: =IFERROR(VALUE(_xlfn.TEXTBEFORE(_xlfn.TEXTAFTER(";"&$N7,";"&SUBSTITUTE(V$1,"Qty ","")&":"),";")),"") -> 2.77 | W7: =IFERROR(VALUE(_xlfn.TEXTBEFORE(_xlfn.TEXTAFTER(";"&$N7,";"&SUBSTITUTE(W$1,"Qty ","")&":"),";")),"") -> 2.63 | X7: {=IF(Y7="","",_xlfn.TEXTJOIN(";",TRUE,SUBSTITUTE($Y$1:$AG$1,"Qty ","")&":"&TEXT(Y7:AG7,"0.00"))&";")} -> 1:13.16;10:11.96;25:7.13;50:5.27;100:4.66;250:4.33;500:4.15;750:3.94;1000:3.77; | Y7: ='Blocking Prices'!$C$14+O7 -> 13.16 | Z7: ='Blocking Prices'!$D$14+P7 -> 11.96 | AA7: ='Blocking Prices'!$E$14+Q7 -> 7.13 | AB7: ='Blocking Prices'!$F$14+R7 -> 5.27 | AC7: ='Blocking Prices'!$G$14+S7 -> 4.66 | AD7: ='Blocking Prices'!$H$14+T7 -> 4.33 | AE7: ='Blocking Prices'!$I$14+U7 -> 4.15 | AF7: ='Blocking Prices'!$J$14+V7 -> 3.94 | AG7: ='Blocking Prices'!$K$14+W7 -> 3.77 | AL7: <span data-sheets-root="1">Stay on top of your week with the Dorchester Horizon Pocket Diary - Week to View. Featuring a soft Vegan Leather Horizon design, white paper, and a ribbon marker, this compact diary combines style and practicality for easy weekly planning.</span>_x000D_\n<div class="trade-info">_x000D_\n<div class="trade-info__item">_x000D_\n<div class="product-popup-modal__text rte">_x000D_\n_x000D_\n&nbsp;_x000D_\n_x000D_\n</div>_x000D_\n</div>_x000D_\n</div> | AN7: =IFERROR(_xlfn.LET(_xlpm.v,INDEX('product-export-27-8-2026'!$A:$AJ,MATCH($A7,'product-export-27-8-2026'!$A:$A,0),MATCH(AN$1,'product-export-27-8-2026'!$1:$1,0)),IF(_xlpm.v="","",_xlpm.v)),"") | AO7: =IFERROR(_xlfn.LET(_xlpm.v,INDEX('product-export-27-8-2026'!$A:$AJ,MATCH($A7,'product-export-27-8-2026'!$A:$A,0),MATCH(AO$1,'product-export-27-8-2026'!$1:$1,0)),IF(_xlpm.v="","",_xlpm.v)),"") | AP7: =IFERROR(_xlfn.LET(_xlpm.v,INDEX('product-export-27-8-2026'!$A:$AJ,MATCH($A7,'product-export-27-8-2026'!$A:$A,0),MATCH(AP$1,'product-export-27-8-2026'!$1:$1,0)),IF(_xlpm.v="","",_xlpm.v)),"") | AQ7: =IFERROR(_xlfn.LET(_xlpm.v,INDEX('product-export-27-8-2026'!$A:$AJ,MATCH($A7,'product-export-27-8-2026'!$A:$A,0),MATCH(AQ$1,'product-export-27-8-2026'!$1:$1,0)),IF(_xlpm.v="","",_xlpm.v)),"") | AR7: =IFERROR(_xlfn.LET(_xlpm.v,INDEX('product-export-27-8-2026'!$A:$AJ,MATCH($A7,'product-export-27-8-2026'!$A:$A,0),MATCH(AR$1,'product-export-27-8-2026'!$1:$1,0)),IF(_xlpm.v="","",_xlpm.v)),"") -> Diaries, Dorchester Collection, Diaries > Pocket Diaries | AS7: =IFERROR(_xlfn.LET(_xlpm.v,INDEX('product-export-27-8-2026'!$A:$AJ,MATCH($A7,'product-export-27-8-2026'!$A:$A,0),MATCH(AS$1,'product-export-27-8-2026'!$1:$1,0)),IF(_xlpm.v="","",_xlpm.v)),"") -> Dorchester-Horizon-Pocket-Week-to-View
A8: 613 | B8: Dorchester Horizon Pocket, Week to View, Royal Blue | C8: Diary | D8: HZ-BK/RB-U-095 | E8: HZ-BK/RB-U-095 | F8: HZ96U | G8: Pocket | H8: Royal Blue | I8: Week to View | J8: White | K8: 18mm x 18mm | L8: 0.42 | M8: 9.99 | N8: 1:9.74;10:9.33;25:5.30;50:3.77;100:3.28;250:3.07;500:2.95;750:2.77;1000:2.63; | O8: =IFERROR(VALUE(_xlfn.TEXTBEFORE(_xlfn.TEXTAFTER(";"&$N8,";"&SUBSTITUTE(O$1,"Qty ","")&":"),";")),"") -> 9.74 | P8: =IFERROR(VALUE(_xlfn.TEXTBEFORE(_xlfn.TEXTAFTER(";"&$N8,";"&SUBSTITUTE(P$1,"Qty ","")&":"),";")),"") -> 9.33 | Q8: =IFERROR(VALUE(_xlfn.TEXTBEFORE(_xlfn.TEXTAFTER(";"&$N8,";"&SUBSTITUTE(Q$1,"Qty ","")&":"),";")),"") -> 5.3 | R8: =IFERROR(VALUE(_xlfn.TEXTBEFORE(_xlfn.TEXTAFTER(";"&$N8,";"&SUBSTITUTE(R$1,"Qty ","")&":"),";")),"") -> 3.77 | S8: =IFERROR(VALUE(_xlfn.TEXTBEFORE(_xlfn.TEXTAFTER(";"&$N8,";"&SUBSTITUTE(S$1,"Qty ","")&":"),";")),"") -> 3.28 | T8: =IFERROR(VALUE(_xlfn.TEXTBEFORE(_xlfn.TEXTAFTER(";"&$N8,";"&SUBSTITUTE(T$1,"Qty ","")&":"),";")),"") -> 3.07 | U8: =IFERROR(VALUE(_xlfn.TEXTBEFORE(_xlfn.TEXTAFTER(";"&$N8,";"&SUBSTITUTE(U$1,"Qty ","")&":"),";")),"") -> 2.95 | V8: =IFERROR(VALUE(_xlfn.TEXTBEFORE(_xlfn.TEXTAFTER(";"&$N8,";"&SUBSTITUTE(V$1,"Qty ","")&":"),";")),"") -> 2.77 | W8: =IFERROR(VALUE(_xlfn.TEXTBEFORE(_xlfn.TEXTAFTER(";"&$N8,";"&SUBSTITUTE(W$1,"Qty ","")&":"),";")),"") -> 2.63 | X8: {=IF(Y8="","",_xlfn.TEXTJOIN(";",TRUE,SUBSTITUTE($Y$1:$AG$1,"Qty ","")&":"&TEXT(Y8:AG8,"0.00"))&";")} -> 1:13.16;10:11.96;25:7.13;50:5.27;100:4.66;250:4.33;500:4.15;750:3.94;1000:3.77; | Y8: ='Blocking Prices'!$C$14+O8 -> 13.16 | Z8: ='Blocking Prices'!$D$14+P8 -> 11.96 | AA8: ='Blocking Prices'!$E$14+Q8 -> 7.13 | AB8: ='Blocking Prices'!$F$14+R8 -> 5.27 | AC8: ='Blocking Prices'!$G$14+S8 -> 4.66 | AD8: ='Blocking Prices'!$H$14+T8 -> 4.33 | AE8: ='Blocking Prices'!$I$14+U8 -> 4.15 | AF8: ='Blocking Prices'!$J$14+V8 -> 3.94 | AG8: ='Blocking Prices'!$K$14+W8 -> 3.77 | AL8: <span data-sheets-root="1">Stay on top of your week with the Dorchester Horizon Pocket Diary - Week to View. Featuring a soft Vegan Leather Horizon design, white paper, and a ribbon marker, this compact diary combines style and practicality for easy weekly planning.</span>_x000D_\n<div class="trade-info">_x000D_\n<div class="trade-info__item">_x000D_\n<div class="product-popup-modal__text rte">_x000D_\n_x000D_\n&nbsp;_x000D_\n_x000D_\n</div>_x000D_\n</div>_x000D_\n</div> | AN8: =IFERROR(_xlfn.LET(_xlpm.v,INDEX('product-export-27-8-2026'!$A:$AJ,MATCH($A8,'product-export-27-8-2026'!$A:$A,0),MATCH(AN$1,'product-export-27-8-2026'!$1:$1,0)),IF(_xlpm.v="","",_xlpm.v)),"") | AO8: =IFERROR(_xlfn.LET(_xlpm.v,INDEX('product-export-27-8-2026'!$A:$AJ,MATCH($A8,'product-export-27-8-2026'!$A:$A,0),MATCH(AO$1,'product-export-27-8-2026'!$1:$1,0)),IF(_xlpm.v="","",_xlpm.v)),"") | AP8: =IFERROR(_xlfn.LET(_xlpm.v,INDEX('product-export-27-8-2026'!$A:$AJ,MATCH($A8,'product-export-27-8-2026'!$A:$A,0),MATCH(AP$1,'product-export-27-8-2026'!$1:$1,0)),IF(_xlpm.v="","",_xlpm.v)),"") | AQ8: =IFERROR(_xlfn.LET(_xlpm.v,INDEX('product-export-27-8-2026'!$A:$AJ,MATCH($A8,'product-export-27-8-2026'!$A:$A,0),MATCH(AQ$1,'product-export-27-8-2026'!$1:$1,0)),IF(_xlpm.v="","",_xlpm.v)),"") | AR8: =IFERROR(_xlfn.LET(_xlpm.v,INDEX('product-export-27-8-2026'!$A:$AJ,MATCH($A8,'product-export-27-8-2026'!$A:$A,0),MATCH(AR$1,'product-export-27-8-2026'!$1:$1,0)),IF(_xlpm.v="","",_xlpm.v)),"") -> Diaries, Dorchester Collection, Diaries > Pocket Diaries | AS8: =IFERROR(_xlfn.LET(_xlpm.v,INDEX('product-export-27-8-2026'!$A:$AJ,MATCH($A8,'product-export-27-8-2026'!$A:$A,0),MATCH(AS$1,'product-export-27-8-2026'!$1:$1,0)),IF(_xlpm.v="","",_xlpm.v)),"") -> Dorchester-Horizon-Pocket-Week-to-View
A9: 615 | B9: Dorchester Bicolor Pocket, Week to View, Black-Aqua | C9: Diary | D9: NB-BK/AQ-U-096 | E9: NB-BK/AQ-U-096 | F9: NB96U | G9: Pocket | H9: Black-Aqua | I9: Week to View | J9: Cream | K9: 18mm x 18mm | L9: 0.42 | M9: 9.99 | N9: 1:9.74;10:9.33;25:5.30;50:3.77;100:3.28;250:3.07;500:2.95;750:2.77;1000:2.63; | O9: =IFERROR(VALUE(_xlfn.TEXTBEFORE(_xlfn.TEXTAFTER(";"&$N9,";"&SUBSTITUTE(O$1,"Qty ","")&":"),";")),"") -> 9.74 | P9: =IFERROR(VALUE(_xlfn.TEXTBEFORE(_xlfn.TEXTAFTER(";"&$N9,";"&SUBSTITUTE(P$1,"Qty ","")&":"),";")),"") -> 9.33 | Q9: =IFERROR(VALUE(_xlfn.TEXTBEFORE(_xlfn.TEXTAFTER(";"&$N9,";"&SUBSTITUTE(Q$1,"Qty ","")&":"),";")),"") -> 5.3 | R9: =IFERROR(VALUE(_xlfn.TEXTBEFORE(_xlfn.TEXTAFTER(";"&$N9,";"&SUBSTITUTE(R$1,"Qty ","")&":"),";")),"") -> 3.77 | S9: =IFERROR(VALUE(_xlfn.TEXTBEFORE(_xlfn.TEXTAFTER(";"&$N9,";"&SUBSTITUTE(S$1,"Qty ","")&":"),";")),"") -> 3.28 | T9: =IFERROR(VALUE(_xlfn.TEXTBEFORE(_xlfn.TEXTAFTER(";"&$N9,";"&SUBSTITUTE(T$1,"Qty ","")&":"),";")),"") -> 3.07 | U9: =IFERROR(VALUE(_xlfn.TEXTBEFORE(_xlfn.TEXTAFTER(";"&$N9,";"&SUBSTITUTE(U$1,"Qty ","")&":"),";")),"") -> 2.95 | V9: =IFERROR(VALUE(_xlfn.TEXTBEFORE(_xlfn.TEXTAFTER(";"&$N9,";"&SUBSTITUTE(V$1,"Qty ","")&":"),";")),"") -> 2.77 | W9: =IFERROR(VALUE(_xlfn.TEXTBEFORE(_xlfn.TEXTAFTER(";"&$N9,";"&SUBSTITUTE(W$1,"Qty ","")&":"),";")),"") -> 2.63 | X9: {=IF(Y9="","",_xlfn.TEXTJOIN(";",TRUE,SUBSTITUTE($Y$1:$AG$1,"Qty ","")&":"&TEXT(Y9:AG9,"0.00"))&";")} -> 1:13.16;10:11.96;25:7.13;50:5.27;100:4.66;250:4.33;500:4.15;750:3.94;1000:3.77; | Y9: ='Blocking Prices'!$C$14+O9 -> 13.16 | Z9: ='Blocking Prices'!$D$14+P9 -> 11.96 | AA9: ='Blocking Prices'!$E$14+Q9 -> 7.13 | AB9: ='Blocking Prices'!$F$14+R9 -> 5.27 | AC9: ='Blocking Prices'!$G$14+S9 -> 4.66 | AD9: ='Blocking Prices'!$H$14+T9 -> 4.33 | AE9: ='Blocking Prices'!$I$14+U9 -> 4.15 | AF9: ='Blocking Prices'!$J$14+V9 -> 3.94 | AG9: ='Blocking Prices'!$K$14+W9 -> 3.77 | AL9: Stay organized in style with the Dorchester Bicolor Pocket Diary - Week to View. Featuring a unique bicolour design, cream paper, and a ribbon marker, it offers sophisticated weekly planning in a portable, compact size._x000D_\n<div class="trade-info">_x000D_\n<div class="trade-info__item">_x000D_\n<div class="product-popup-modal__text rte">_x000D_\n_x000D_\n&nbsp;_x000D_\n_x000D_\n</div>_x000D_\n</div>_x000D_\n</div> | AN9: =IFERROR(_xlfn.LET(_xlpm.v,INDEX('product-export-27-8-2026'!$A:$AJ,MATCH($A9,'product-export-27-8-2026'!$A:$A,0),MATCH(AN$1,'product-export-27-8-2026'!$1:$1,0)),IF(_xlpm.v="","",_xlpm.v)),"") | AO9: =IFERROR(_xlfn.LET(_xlpm.v,INDEX('product-export-27-8-2026'!$A:$AJ,MATCH($A9,'product-export-27-8-2026'!$A:$A,0),MATCH(AO$1,'product-export-27-8-2026'!$1:$1,0)),IF(_xlpm.v="","",_xlpm.v)),"") | AP9: =IFERROR(_xlfn.LET(_xlpm.v,INDEX('product-export-27-8-2026'!$A:$AJ,MATCH($A9,'product-export-27-8-2026'!$A:$A,0),MATCH(AP$1,'product-export-27-8-2026'!$1:$1,0)),IF(_xlpm.v="","",_xlpm.v)),"") | AQ9: =IFERROR(_xlfn.LET(_xlpm.v,INDEX('product-export-27-8-2026'!$A:$AJ,MATCH($A9,'product-export-27-8-2026'!$A:$A,0),MATCH(AQ$1,'product-export-27-8-2026'!$1:$1,0)),IF(_xlpm.v="","",_xlpm.v)),"") | AR9: =IFERROR(_xlfn.LET(_xlpm.v,INDEX('product-export-27-8-2026'!$A:$AJ,MATCH($A9,'product-export-27-8-2026'!$A:$A,0),MATCH(AR$1,'product-export-27-8-2026'!$1:$1,0)),IF(_xlpm.v="","",_xlpm.v)),"") -> Diaries, Dorchester Collection, Diaries > Pocket Diaries | AS9: =IFERROR(_xlfn.LET(_xlpm.v,INDEX('product-export-27-8-2026'!$A:$AJ,MATCH($A9,'product-export-27-8-2026'!$A:$A,0),MATCH(AS$1,'product-export-27-8-2026'!$1:$1,0)),IF(_xlpm.v="","",_xlpm.v)),"") -> Dorchester-Newhide-Bicolor-Pocket-Week-to-View
A10: 618 | B10: Dorchester Bicolor Pocket, Week to View, Black-Orange | C10: Diary | D10: NB-BK/OR-U-096 | E10: NB-BK/OR-U-096 | F10: NB96U | G10: Pocket | H10: Black-Orange | I10: Week to View | J10: Cream | K10: 18mm x 18mm | L10: 0.42 | M10: 9.99 | N10: 1:9.74;10:9.33;25:5.30;50:3.77;100:3.28;250:3.07;500:2.95;750:2.77;1000:2.63; | O10: =IFERROR(VALUE(_xlfn.TEXTBEFORE(_xlfn.TEXTAFTER(";"&$N10,";"&SUBSTITUTE(O$1,"Qty ","")&":"),";")),"") -> 9.74 | P10: =IFERROR(VALUE(_xlfn.TEXTBEFORE(_xlfn.TEXTAFTER(";"&$N10,";"&SUBSTITUTE(P$1,"Qty ","")&":"),";")),"") -> 9.33 | Q10: =IFERROR(VALUE(_xlfn.TEXTBEFORE(_xlfn.TEXTAFTER(";"&$N10,";"&SUBSTITUTE(Q$1,"Qty ","")&":"),";")),"") -> 5.3 | R10: =IFERROR(VALUE(_xlfn.TEXTBEFORE(_xlfn.TEXTAFTER(";"&$N10,";"&SUBSTITUTE(R$1,"Qty ","")&":"),";")),"") -> 3.77 | S10: =IFERROR(VALUE(_xlfn.TEXTBEFORE(_xlfn.TEXTAFTER(";"&$N10,";"&SUBSTITUTE(S$1,"Qty ","")&":"),";")),"") -> 3.28 | T10: =IFERROR(VALUE(_xlfn.TEXTBEFORE(_xlfn.TEXTAFTER(";"&$N10,";"&SUBSTITUTE(T$1,"Qty ","")&":"),";")),"") -> 3.07 | U10: =IFERROR(VALUE(_xlfn.TEXTBEFORE(_xlfn.TEXTAFTER(";"&$N10,";"&SUBSTITUTE(U$1,"Qty ","")&":"),";")),"") -> 2.95 | V10: =IFERROR(VALUE(_xlfn.TEXTBEFORE(_xlfn.TEXTAFTER(";"&$N10,";"&SUBSTITUTE(V$1,"Qty ","")&":"),";")),"") -> 2.77 | W10: =IFERROR(VALUE(_xlfn.TEXTBEFORE(_xlfn.TEXTAFTER(";"&$N10,";"&SUBSTITUTE(W$1,"Qty ","")&":"),";")),"") -> 2.63 | X10: {=IF(Y10="","",_xlfn.TEXTJOIN(";",TRUE,SUBSTITUTE($Y$1:$AG$1,"Qty ","")&":"&TEXT(Y10:AG10,"0.00"))&";")} -> 1:13.16;10:11.96;25:7.13;50:5.27;100:4.66;250:4.33;500:4.15;750:3.94;1000:3.77; | Y10: ='Blocking Prices'!$C$14+O10 -> 13.16 | Z10: ='Blocking Prices'!$D$14+P10 -> 11.96 | AA10: ='Blocking Prices'!$E$14+Q10 -> 7.13 | AB10: ='Blocking Prices'!$F$14+R10 -> 5.27 | AC10: ='Blocking Prices'!$G$14+S10 -> 4.66 | AD10: ='Blocking Prices'!$H$14+T10 -> 4.33 | AE10: ='Blocking Prices'!$I$14+U10 -> 4.15 | AF10: ='Blocking Prices'!$J$14+V10 -> 3.94 | AG10: ='Blocking Prices'!$K$14+W10 -> 3.77 | AL10: Stay organized in style with the Dorchester Bicolor Pocket Diary - Week to View. Featuring a unique bicolour design, cream paper, and a ribbon marker, it offers sophisticated weekly planning in a portable, compact size._x000D_\n<div class="trade-info">_x000D_\n<div class="trade-info__item">_x000D_\n<div class="product-popup-modal__text rte">_x000D_\n_x000D_\n&nbsp;_x000D_\n_x000D_\n</div>_x000D_\n</div>_x000D_\n</div> | AN10: =IFERROR(_xlfn.LET(_xlpm.v,INDEX('product-export-27-8-2026'!$A:$AJ,MATCH($A10,'product-export-27-8-2026'!$A:$A,0),MATCH(AN$1,'product-export-27-8-2026'!$1:$1,0)),IF(_xlpm.v="","",_xlpm.v)),"") | AO10: =IFERROR(_xlfn.LET(_xlpm.v,INDEX('product-export-27-8-2026'!$A:$AJ,MATCH($A10,'product-export-27-8-2026'!$A:$A,0),MATCH(AO$1,'product-export-27-8-2026'!$1:$1,0)),IF(_xlpm.v="","",_xlpm.v)),"") | AP10: =IFERROR(_xlfn.LET(_xlpm.v,INDEX('product-export-27-8-2026'!$A:$AJ,MATCH($A10,'product-export-27-8-2026'!$A:$A,0),MATCH(AP$1,'product-export-27-8-2026'!$1:$1,0)),IF(_xlpm.v="","",_xlpm.v)),"") | AQ10: =IFERROR(_xlfn.LET(_xlpm.v,INDEX('product-export-27-8-2026'!$A:$AJ,MATCH($A10,'product-export-27-8-2026'!$A:$A,0),MATCH(AQ$1,'product-export-27-8-2026'!$1:$1,0)),IF(_xlpm.v="","",_xlpm.v)),"") | AR10: =IFERROR(_xlfn.LET(_xlpm.v,INDEX('product-export-27-8-2026'!$A:$AJ,MATCH($A10,'product-export-27-8-2026'!$A:$A,0),MATCH(AR$1,'product-export-27-8-2026'!$1:$1,0)),IF(_xlpm.v="","",_xlpm.v)),"") -> Diaries, Dorchester Collection, Diaries > Pocket Diaries | AS10: =IFERROR(_xlfn.LET(_xlpm.v,INDEX('product-export-27-8-2026'!$A:$AJ,MATCH($A10,'product-export-27-8-2026'!$A:$A,0),MATCH(AS$1,'product-export-27-8-2026'!$1:$1,0)),IF(_xlpm.v="","",_xlpm.v)),"") -> Dorchester-Newhide-Bicolor-Pocket-Week-to-View
A11: 620 | B11: Dorchester Bicolor Pocket, Week to View, Black-Purple | C11: Diary | D11: NB-BK/PU-U-096 | E11: NB-BK/PU-U-096 | F11: NB96U | G11: Pocket | H11: Black-Purple | I11: Week to View | J11: Cream | K11: 18mm x 18mm | L11: 0.42 | M11: 9.99 | N11: 1:9.74;10:9.33;25:5.30;50:3.77;100:3.28;250:3.07;500:2.95;750:2.77;1000:2.63; | O11: =IFERROR(VALUE(_xlfn.TEXTBEFORE(_xlfn.TEXTAFTER(";"&$N11,";"&SUBSTITUTE(O$1,"Qty ","")&":"),";")),"") -> 9.74 | P11: =IFERROR(VALUE(_xlfn.TEXTBEFORE(_xlfn.TEXTAFTER(";"&$N11,";"&SUBSTITUTE(P$1,"Qty ","")&":"),";")),"") -> 9.33 | Q11: =IFERROR(VALUE(_xlfn.TEXTBEFORE(_xlfn.TEXTAFTER(";"&$N11,";"&SUBSTITUTE(Q$1,"Qty ","")&":"),";")),"") -> 5.3 | R11: =IFERROR(VALUE(_xlfn.TEXTBEFORE(_xlfn.TEXTAFTER(";"&$N11,";"&SUBSTITUTE(R$1,"Qty ","")&":"),";")),"") -> 3.77 | S11: =IFERROR(VALUE(_xlfn.TEXTBEFORE(_xlfn.TEXTAFTER(";"&$N11,";"&SUBSTITUTE(S$1,"Qty ","")&":"),";")),"") -> 3.28 | T11: =IFERROR(VALUE(_xlfn.TEXTBEFORE(_xlfn.TEXTAFTER(";"&$N11,";"&SUBSTITUTE(T$1,"Qty ","")&":"),";")),"") -> 3.07 | U11: =IFERROR(VALUE(_xlfn.TEXTBEFORE(_xlfn.TEXTAFTER(";"&$N11,";"&SUBSTITUTE(U$1,"Qty ","")&":"),";")),"") -> 2.95 | V11: =IFERROR(VALUE(_xlfn.TEXTBEFORE(_xlfn.TEXTAFTER(";"&$N11,";"&SUBSTITUTE(V$1,"Qty ","")&":"),";")),"") -> 2.77 | W11: =IFERROR(VALUE(_xlfn.TEXTBEFORE(_xlfn.TEXTAFTER(";"&$N11,";"&SUBSTITUTE(W$1,"Qty ","")&":"),";")),"") -> 2.63 | X11: {=IF(Y11="","",_xlfn.TEXTJOIN(";",TRUE,SUBSTITUTE($Y$1:$AG$1,"Qty ","")&":"&TEXT(Y11:AG11,"0.00"))&";")} -> 1:13.16;10:11.96;25:7.13;50:5.27;100:4.66;250:4.33;500:4.15;750:3.94;1000:3.77; | Y11: ='Blocking Prices'!$C$14+O11 -> 13.16 | Z11: ='Blocking Prices'!$D$14+P11 -> 11.96 | AA11: ='Blocking Prices'!$E$14+Q11 -> 7.13 | AB11: ='Blocking Prices'!$F$14+R11 -> 5.27 | AC11: ='Blocking Prices'!$G$14+S11 -> 4.66 | AD11: ='Blocking Prices'!$H$14+T11 -> 4.33 | AE11: ='Blocking Prices'!$I$14+U11 -> 4.15 | AF11: ='Blocking Prices'!$J$14+V11 -> 3.94 | AG11: ='Blocking Prices'!$K$14+W11 -> 3.77 | AL11: Stay organized in style with the Dorchester Bicolor Pocket Diary - Week to View. Featuring a unique bicolour design, cream paper, and a ribbon marker, it offers sophisticated weekly planning in a portable, compact size._x000D_\n<div class="trade-info">_x000D_\n<div class="trade-info__item">_x000D_\n<div class="product-popup-modal__text rte">_x000D_\n_x000D_\n&nbsp;_x000D_\n_x000D_\n</div>_x000D_\n</div>_x000D_\n</div> | AN11: =IFERROR(_xlfn.LET(_xlpm.v,INDEX('product-export-27-8-2026'!$A:$AJ,MATCH($A11,'product-export-27-8-2026'!$A:$A,0),MATCH(AN$1,'product-export-27-8-2026'!$1:$1,0)),IF(_xlpm.v="","",_xlpm.v)),"") | AO11: =IFERROR(_xlfn.LET(_xlpm.v,INDEX('product-export-27-8-2026'!$A:$AJ,MATCH($A11,'product-export-27-8-2026'!$A:$A,0),MATCH(AO$1,'product-export-27-8-2026'!$1:$1,0)),IF(_xlpm.v="","",_xlpm.v)),"") | AP11: =IFERROR(_xlfn.LET(_xlpm.v,INDEX('product-export-27-8-2026'!$A:$AJ,MATCH($A11,'product-export-27-8-2026'!$A:$A,0),MATCH(AP$1,'product-export-27-8-2026'!$1:$1,0)),IF(_xlpm.v="","",_xlpm.v)),"") | AQ11: =IFERROR(_xlfn.LET(_xlpm.v,INDEX('product-export-27-8-2026'!$A:$AJ,MATCH($A11,'product-export-27-8-2026'!$A:$A,0),MATCH(AQ$1,'product-export-27-8-2026'!$1:$1,0)),IF(_xlpm.v="","",_xlpm.v)),"") | AR11: =IFERROR(_xlfn.LET(_xlpm.v,INDEX('product-export-27-8-2026'!$A:$AJ,MATCH($A11,'product-export-27-8-2026'!$A:$A,0),MATCH(AR$1,'product-export-27-8-2026'!$1:$1,0)),IF(_xlpm.v="","",_xlpm.v)),"") -> Diaries, Dorchester Collection, Diaries > Pocket Diaries | AS11: =IFERROR(_xlfn.LET(_xlpm.v,INDEX('product-export-27-8-2026'!$A:$AJ,MATCH($A11,'product-export-27-8-2026'!$A:$A,0),MATCH(AS$1,'product-export-27-8-2026'!$1:$1,0)),IF(_xlpm.v="","",_xlpm.v)),"") -> Dorchester-Newhide-Bicolor-Pocket-Week-to-View
A12: 622 | B12: Dorchester Bicolor Pocket, Week to View, Black-Red | C12: Diary | D12: NB-BK/RD-U-096 | E12: NB-BK/RD-U-096 | F12: NB96U | G12: Pocket | H12: Black-Red | I12: Week to View | J12: Cream | K12: 18mm x 18mm | L12: 0.42 | M12: 9.99 | N12: 1:9.74;10:9.33;25:5.30;50:3.77;100:3.28;250:3.07;500:2.95;750:2.77;1000:2.63; | O12: =IFERROR(VALUE(_xlfn.TEXTBEFORE(_xlfn.TEXTAFTER(";"&$N12,";"&SUBSTITUTE(O$1,"Qty ","")&":"),";")),"") -> 9.74 | P12: =IFERROR(VALUE(_xlfn.TEXTBEFORE(_xlfn.TEXTAFTER(";"&$N12,";"&SUBSTITUTE(P$1,"Qty ","")&":"),";")),"") -> 9.33 | Q12: =IFERROR(VALUE(_xlfn.TEXTBEFORE(_xlfn.TEXTAFTER(";"&$N12,";"&SUBSTITUTE(Q$1,"Qty ","")&":"),";")),"") -> 5.3 | R12: =IFERROR(VALUE(_xlfn.TEXTBEFORE(_xlfn.TEXTAFTER(";"&$N12,";"&SUBSTITUTE(R$1,"Qty ","")&":"),";")),"") -> 3.77 | S12: =IFERROR(VALUE(_xlfn.TEXTBEFORE(_xlfn.TEXTAFTER(";"&$N12,";"&SUBSTITUTE(S$1,"Qty ","")&":"),";")),"") -> 3.28 | T12: =IFERROR(VALUE(_xlfn.TEXTBEFORE(_xlfn.TEXTAFTER(";"&$N12,";"&SUBSTITUTE(T$1,"Qty ","")&":"),";")),"") -> 3.07 | U12: =IFERROR(VALUE(_xlfn.TEXTBEFORE(_xlfn.TEXTAFTER(";"&$N12,";"&SUBSTITUTE(U$1,"Qty ","")&":"),";")),"") -> 2.95 | V12: =IFERROR(VALUE(_xlfn.TEXTBEFORE(_xlfn.TEXTAFTER(";"&$N12,";"&SUBSTITUTE(V$1,"Qty ","")&":"),";")),"") -> 2.77 | W12: =IFERROR(VALUE(_xlfn.TEXTBEFORE(_xlfn.TEXTAFTER(";"&$N12,";"&SUBSTITUTE(W$1,"Qty ","")&":"),";")),"") -> 2.63 | X12: {=IF(Y12="","",_xlfn.TEXTJOIN(";",TRUE,SUBSTITUTE($Y$1:$AG$1,"Qty ","")&":"&TEXT(Y12:AG12,"0.00"))&";")} -> 1:13.16;10:11.96;25:7.13;50:5.27;100:4.66;250:4.33;500:4.15;750:3.94;1000:3.77; | Y12: ='Blocking Prices'!$C$14+O12 -> 13.16 | Z12: ='Blocking Prices'!$D$14+P12 -> 11.96 | AA12: ='Blocking Prices'!$E$14+Q12 -> 7.13 | AB12: ='Blocking Prices'!$F$14+R12 -> 5.27 | AC12: ='Blocking Prices'!$G$14+S12 -> 4.66 | AD12: ='Blocking Prices'!$H$14+T12 -> 4.33 | AE12: ='Blocking Prices'!$I$14+U12 -> 4.15 | AF12: ='Blocking Prices'!$J$14+V12 -> 3.94 | AG12: ='Blocking Prices'!$K$14+W12 -> 3.77 | AL12: Stay organized in style with the Dorchester Bicolor Pocket Diary - Week to View. Featuring a unique bicolour design, cream paper, and a ribbon marker, it offers sophisticated weekly planning in a portable, compact size. | AN12: =IFERROR(_xlfn.LET(_xlpm.v,INDEX('product-export-27-8-2026'!$A:$AJ,MATCH($A12,'product-export-27-8-2026'!$A:$A,0),MATCH(AN$1,'product-export-27-8-2026'!$1:$1,0)),IF(_xlpm.v="","",_xlpm.v)),"") | AO12: =IFERROR(_xlfn.LET(_xlpm.v,INDEX('product-export-27-8-2026'!$A:$AJ,MATCH($A12,'product-export-27-8-2026'!$A:$A,0),MATCH(AO$1,'product-export-27-8-2026'!$1:$1,0)),IF(_xlpm.v="","",_xlpm.v)),"") | AP12: =IFERROR(_xlfn.LET(_xlpm.v,INDEX('product-export-27-8-2026'!$A:$AJ,MATCH($A12,'product-export-27-8-2026'!$A:$A,0),MATCH(AP$1,'product-export-27-8-2026'!$1:$1,0)),IF(_xlpm.v="","",_xlpm.v)),"") | AQ12: =IFERROR(_xlfn.LET(_xlpm.v,INDEX('product-export-27-8-2026'!$A:$AJ,MATCH($A12,'product-export-27-8-2026'!$A:$A,0),MATCH(AQ$1,'product-export-27-8-2026'!$1:$1,0)),IF(_xlpm.v="","",_xlpm.v)),"") | AR12: =IFERROR(_xlfn.LET(_xlpm.v,INDEX('product-export-27-8-2026'!$A:$AJ,MATCH($A12,'product-export-27-8-2026'!$A:$A,0),MATCH(AR$1,'product-export-27-8-2026'!$1:$1,0)),IF(_xlpm.v="","",_xlpm.v)),"") -> Diaries, Dorchester Collection, Diaries > Pocket Diaries | AS12: =IFERROR(_xlfn.LET(_xlpm.v,INDEX('product-export-27-8-2026'!$A:$AJ,MATCH($A12,'product-export-27-8-2026'!$A:$A,0),MATCH(AS$1,'product-export-27-8-2026'!$1:$1,0)),IF(_xlpm.v="","",_xlpm.v)),"") -> Dorchester-Newhide-Bicolor-Pocket-Week-to-View
A13: 624 | B13: Dorchester Bicolor Pocket, Week to View, Blue- Royal Blue | C13: Diary | D13: NB-BK/RB-U-096 | E13: NB-BK/RB-U-096 | F13: NB96U | G13: Pocket | H13: Blue-Royal Blue | I13: Week to View | J13: Cream | K13: 18mm x 18mm | L13: 0.42 | M13: 9.99 | N13: 1:9.74;10:9.33;25:5.30;50:3.77;100:3.28;250:3.07;500:2.95;750:2.77;1000:2.63; | O13: =IFERROR(VALUE(_xlfn.TEXTBEFORE(_xlfn.TEXTAFTER(";"&$N13,";"&SUBSTITUTE(O$1,"Qty ","")&":"),";")),"") -> 9.74 | P13: =IFERROR(VALUE(_xlfn.TEXTBEFORE(_xlfn.TEXTAFTER(";"&$N13,";"&SUBSTITUTE(P$1,"Qty ","")&":"),";")),"") -> 9.33 | Q13: 5.3 | R13: =IFERROR(VALUE(_xlfn.TEXTBEFORE(_xlfn.TEXTAFTER(";"&$N13,";"&SUBSTITUTE(R$1,"Qty ","")&":"),";")),"") -> 3.77 | S13: =IFERROR(VALUE(_xlfn.TEXTBEFORE(_xlfn.TEXTAFTER(";"&$N13,";"&SUBSTITUTE(S$1,"Qty ","")&":"),";")),"") -> 3.28 | T13: =IFERROR(VALUE(_xlfn.TEXTBEFORE(_xlfn.TEXTAFTER(";"&$N13,";"&SUBSTITUTE(T$1,"Qty ","")&":"),";")),"") -> 3.07 | U13: =IFERROR(VALUE(_xlfn.TEXTBEFORE(_xlfn.TEXTAFTER(";"&$N13,";"&SUBSTITUTE(U$1,"Qty ","")&":"),";")),"") -> 2.95 | V13: =IFERROR(VALUE(_xlfn.TEXTBEFORE(_xlfn.TEXTAFTER(";"&$N13,";"&SUBSTITUTE(V$1,"Qty ","")&":"),";")),"") -> 2.77 | W13: =IFERROR(VALUE(_xlfn.TEXTBEFORE(_xlfn.TEXTAFTER(";"&$N13,";"&SUBSTITUTE(W$1,"Qty ","")&":"),";")),"") -> 2.63 | X13: {=IF(Y13="","",_xlfn.TEXTJOIN(";",TRUE,SUBSTITUTE($Y$1:$AG$1,"Qty ","")&":"&TEXT(Y13:AG13,"0.00"))&";")} -> 1:13.16;10:11.96;25:7.13;50:5.27;100:4.66;250:4.33;500:4.15;750:3.94;1000:3.77; | Y13: ='Blocking Prices'!$C$14+O13 -> 13.16 | Z13: ='Blocking Prices'!$D$14+P13 -> 11.96 | AA13: ='Blocking Prices'!$E$14+Q13 -> 7.13 | AB13: ='Blocking Prices'!$F$14+R13 -> 5.27 | AC13: ='Blocking Prices'!$G$14+S13 -> 4.66 | AD13: ='Blocking Prices'!$H$14+T13 -> 4.33 | AE13: ='Blocking Prices'!$I$14+U13 -> 4.15 | AF13: ='Blocking Prices'!$J$14+V13 -> 3.94 | AG13: ='Blocking Prices'!$K$14+W13 -> 3.77 | AL13: Stay organized in style with the Dorchester Bicolor Pocket Diary - Week to View. Featuring a unique bicolour design, cream paper, and a ribbon marker, it offers sophisticated weekly planning in a portable, compact size. | AN13: =IFERROR(_xlfn.LET(_xlpm.v,INDEX('product-export-27-8-2026'!$A:$AJ,MATCH($A13,'product-export-27-8-2026'!$A:$A,0),MATCH(AN$1,'product-export-27-8-2026'!$1:$1,0)),IF(_xlpm.v="","",_xlpm.v)),"") | AO13: =IFERROR(_xlfn.LET(_xlpm.v,INDEX('product-export-27-8-2026'!$A:$AJ,MATCH($A13,'product-export-27-8-2026'!$A:$A,0),MATCH(AO$1,'product-export-27-8-2026'!$1:$1,0)),IF(_xlpm.v="","",_xlpm.v)),"") | AP13: =IFERROR(_xlfn.LET(_xlpm.v,INDEX('product-export-27-8-2026'!$A:$AJ,MATCH($A13,'product-export-27-8-2026'!$A:$A,0),MATCH(AP$1,'product-export-27-8-2026'!$1:$1,0)),IF(_xlpm.v="","",_xlpm.v)),"") | AQ13: =IFERROR(_xlfn.LET(_xlpm.v,INDEX('product-export-27-8-2026'!$A:$AJ,MATCH($A13,'product-export-27-8-2026'!$A:$A,0),MATCH(AQ$1,'product-export-27-8-2026'!$1:$1,0)),IF(_xlpm.v="","",_xlpm.v)),"") | AR13: =IFERROR(_xlfn.LET(_xlpm.v,INDEX('product-export-27-8-2026'!$A:$AJ,MATCH($A13,'product-export-27-8-2026'!$A:$A,0),MATCH(AR$1,'product-export-27-8-2026'!$1:$1,0)),IF(_xlpm.v="","",_xlpm.v)),"") -> Diaries, Dorchester Collection, Diaries > Pocket Diaries | AS13: =IFERROR(_xlfn.LET(_xlpm.v,INDEX('product-export-27-8-2026'!$A:$AJ,MATCH($A13,'product-export-27-8-2026'!$A:$A,0),MATCH(AS$1,'product-export-27-8-2026'!$1:$1,0)),IF(_xlpm.v="","",_xlpm.v)),"") -> Dorchester-Newhide-Bicolor-Pocket-Week-to-View
A14: 626 | B14: Dorchester Pocket, Week to View, Aqua | C14: Diary | D14: NF-AQ-U-095 | E14: NF-AQ-U-095 | F14: NF95U | G14: Pocket | H14: Aqua | I14: Week to View | J14: White | K14: 18mm x 18mm | L14: 0.42 | M14: 8.99 | N14: 1:9.09;10:8.71;25:5.20;50:4.33;100:3.60;250:2.98;500:2.61;750:2.50;1000:2.31; | O14: =IFERROR(VALUE(_xlfn.TEXTBEFORE(_xlfn.TEXTAFTER(";"&$N14,";"&SUBSTITUTE(O$1,"Qty ","")&":"),";")),"") -> 9.09 | P14: =IFERROR(VALUE(_xlfn.TEXTBEFORE(_xlfn.TEXTAFTER(";"&$N14,";"&SUBSTITUTE(P$1,"Qty ","")&":"),";")),"") -> 8.71 | Q14: =IFERROR(VALUE(_xlfn.TEXTBEFORE(_xlfn.TEXTAFTER(";"&$N14,";"&SUBSTITUTE(Q$1,"Qty ","")&":"),";")),"") -> 5.2 | R14: =IFERROR(VALUE(_xlfn.TEXTBEFORE(_xlfn.TEXTAFTER(";"&$N14,";"&SUBSTITUTE(R$1,"Qty ","")&":"),";")),"") -> 4.33 | S14: =IFERROR(VALUE(_xlfn.TEXTBEFORE(_xlfn.TEXTAFTER(";"&$N14,";"&SUBSTITUTE(S$1,"Qty ","")&":"),";")),"") -> 3.6 | T14: =IFERROR(VALUE(_xlfn.TEXTBEFORE(_xlfn.TEXTAFTER(";"&$N14,";"&SUBSTITUTE(T$1,"Qty ","")&":"),";")),"") -> 2.98 | U14: =IFERROR(VALUE(_xlfn.TEXTBEFORE(_xlfn.TEXTAFTER(";"&$N14,";"&SUBSTITUTE(U$1,"Qty ","")&":"),";")),"") -> 2.61 | V14: =IFERROR(VALUE(_xlfn.TEXTBEFORE(_xlfn.TEXTAFTER(";"&$N14,";"&SUBSTITUTE(V$1,"Qty ","")&":"),";")),"") -> 2.5 | W14: =IFERROR(VALUE(_xlfn.TEXTBEFORE(_xlfn.TEXTAFTER(";"&$N14,";"&SUBSTITUTE(W$1,"Qty ","")&":"),";")),"") -> 2.31 | X14: {=IF(Y14="","",_xlfn.TEXTJOIN(";",TRUE,SUBSTITUTE($Y$1:$AG$1,"Qty ","")&":"&TEXT(Y14:AG14,"0.00"))&";")} -> 1:12.51;10:11.34;25:7.03;50:5.83;100:4.98;250:4.24;500:3.81;750:3.67;1000:3.45; | Y14: ='Blocking Prices'!$C$14+O14 -> 12.51 | Z14: ='Blocking Prices'!$D$14+P14 -> 11.34 | AA14: ='Blocking Prices'!$E$14+Q14 -> 7.03 | AB14: ='Blocking Prices'!$F$14+R14 -> 5.83 | AC14: ='Blocking Prices'!$G$14+S14 -> 4.98 | AD14: ='Blocking Prices'!$H$14+T14 -> 4.24 | AE14: ='Blocking Prices'!$I$14+U14 -> 3.81 | AF14: ='Blocking Prices'!$J$14+V14 -> 3.67 | AG14: ='Blocking Prices'!$K$14+W14 -> 3.45 | AL14: Organize your 2026 in style with the Dorchester Premium Pocket Diary?featuring a soft faux leather cover, recycled white paper, and a convenient Week to View layout. Eco-friendly and elegant_x000D_\n<div class="trade-info">_x000D_\n<div class="trade-info__item">_x000D_\n<div class="product-popup-modal__text rte">_x000D_\n_x000D_\n&nbsp;_x000D_\n_x000D_\n</div>_x000D_\n</div>_x000D_\n</div> | AN14: =IFERROR(_xlfn.LET(_xlpm.v,INDEX('product-export-27-8-2026'!$A:$AJ,MATCH($A14,'product-export-27-8-2026'!$A:$A,0),MATCH(AN$1,'product-export-27-8-2026'!$1:$1,0)),IF(_xlpm.v="","",_xlpm.v)),"") | AO14: =IFERROR(_xlfn.LET(_xlpm.v,INDEX('product-export-27-8-2026'!$A:$AJ,MATCH($A14,'product-export-27-8-2026'!$A:$A,0),MATCH(AO$1,'product-export-27-8-2026'!$1:$1,0)),IF(_xlpm.v="","",_xlpm.v)),"") | AP14: =IFERROR(_xlfn.LET(_xlpm.v,INDEX('product-export-27-8-2026'!$A:$AJ,MATCH($A14,'product-export-27-8-2026'!$A:$A,0),MATCH(AP$1,'product-export-27-8-2026'!$1:$1,0)),IF(_xlpm.v="","",_xlpm.v)),"") | AQ14: =IFERROR(_xlfn.LET(_xlpm.v,INDEX('product-export-27-8-2026'!$A:$AJ,MATCH($A14,'product-export-27-8-2026'!$A:$A,0),MATCH(AQ$1,'product-export-27-8-2026'!$1:$1,0)),IF(_xlpm.v="","",_xlpm.v)),"") | AR14: =IFERROR(_xlfn.LET(_xlpm.v,INDEX('product-export-27-8-2026'!$A:$AJ,MATCH($A14,'product-export-27-8-2026'!$A:$A,0),MATCH(AR$1,'product-export-27-8-2026'!$1:$1,0)),IF(_xlpm.v="","",_xlpm.v)),"") -> Diaries, Dorchester Collection, Diaries > Pocket Diaries | AS14: =IFERROR(_xlfn.LET(_xlpm.v,INDEX('product-export-27-8-2026'!$A:$AJ,MATCH($A14,'product-export-27-8-2026'!$A:$A,0),MATCH(AS$1,'product-export-27-8-2026'!$1:$1,0)),IF(_xlpm.v="","",_xlpm.v)),"") -> Dorchester-NewHide-Pocket-Week-to-View
A15: 628 | B15: Dorchester Pocket, Week to View, Black | C15: Diary | D15: NF-BK-U-095 | E15: NF-BK-U-095 | F15: NF95U | G15: Pocket | H15: Black | I15: Week to View | J15: White | K15: 18mm x 18mm | L15: 0.42 | M15: 8.99 | N15: 1:9.09;10:8.71;25:5.20;50:4.33;100:3.60;250:2.98;500:2.61;750:2.50;1000:2.31; | O15: =IFERROR(VALUE(_xlfn.TEXTBEFORE(_xlfn.TEXTAFTER(";"&$N15,";"&SUBSTITUTE(O$1,"Qty ","")&":"),";")),"") -> 9.09 | P15: =IFERROR(VALUE(_xlfn.TEXTBEFORE(_xlfn.TEXTAFTER(";"&$N15,";"&SUBSTITUTE(P$1,"Qty ","")&":"),";")),"") -> 8.71 | Q15: =IFERROR(VALUE(_xlfn.TEXTBEFORE(_xlfn.TEXTAFTER(";"&$N15,";"&SUBSTITUTE(Q$1,"Qty ","")&":"),";")),"") -> 5.2 | R15: =IFERROR(VALUE(_xlfn.TEXTBEFORE(_xlfn.TEXTAFTER(";"&$N15,";"&SUBSTITUTE(R$1,"Qty ","")&":"),";")),"") -> 4.33 | S15: =IFERROR(VALUE(_xlfn.TEXTBEFORE(_xlfn.TEXTAFTER(";"&$N15,";"&SUBSTITUTE(S$1,"Qty ","")&":"),";")),"") -> 3.6 | T15: =IFERROR(VALUE(_xlfn.TEXTBEFORE(_xlfn.TEXTAFTER(";"&$N15,";"&SUBSTITUTE(T$1,"Qty ","")&":"),";")),"") -> 2.98 | U15: =IFERROR(VALUE(_xlfn.TEXTBEFORE(_xlfn.TEXTAFTER(";"&$N15,";"&SUBSTITUTE(U$1,"Qty ","")&":"),";")),"") -> 2.61 | V15: =IFERROR(VALUE(_xlfn.TEXTBEFORE(_xlfn.TEXTAFTER(";"&$N15,";"&SUBSTITUTE(V$1,"Qty ","")&":"),";")),"") -> 2.5 | W15: =IFERROR(VALUE(_xlfn.TEXTBEFORE(_xlfn.TEXTAFTER(";"&$N15,";"&SUBSTITUTE(W$1,"Qty ","")&":"),";")),"") -> 2.31 | X15: {=IF(Y15="","",_xlfn.TEXTJOIN(";",TRUE,SUBSTITUTE($Y$1:$AG$1,"Qty ","")&":"&TEXT(Y15:AG15,"0.00"))&";")} -> 1:12.51;10:11.34;25:7.03;50:5.83;100:4.98;250:4.24;500:3.81;750:3.67;1000:3.45; | Y15: ='Blocking Prices'!$C$14+O15 -> 12.51 | Z15: ='Blocking Prices'!$D$14+P15 -> 11.34 | AA15: ='Blocking Prices'!$E$14+Q15 -> 7.03 | AB15: ='Blocking Prices'!$F$14+R15 -> 5.83 | AC15: ='Blocking Prices'!$G$14+S15 -> 4.98 | AD15: ='Blocking Prices'!$H$14+T15 -> 4.24 | AE15: ='Blocking Prices'!$I$14+U15 -> 3.81 | AF15: ='Blocking Prices'!$J$14+V15 -> 3.67 | AG15: ='Blocking Prices'!$K$14+W15 -> 3.45 | AL15: Organize your 2026 in style with the Dorchester Premium Pocket Diary?featuring a soft faux leather cover, recycled white paper, and a convenient Week to View layout. Eco-friendly and elegant | AN15: =IFERROR(_xlfn.LET(_xlpm.v,INDEX('product-export-27-8-2026'!$A:$AJ,MATCH($A15,'product-export-27-8-2026'!$A:$A,0),MATCH(AN$1,'product-export-27-8-2026'!$1:$1,0)),IF(_xlpm.v="","",_xlpm.v)),"") | AO15: =IFERROR(_xlfn.LET(_xlpm.v,INDEX('product-export-27-8-2026'!$A:$AJ,MATCH($A15,'product-export-27-8-2026'!$A:$A,0),MATCH(AO$1,'product-export-27-8-2026'!$1:$1,0)),IF(_xlpm.v="","",_xlpm.v)),"") | AP15: =IFERROR(_xlfn.LET(_xlpm.v,INDEX('product-export-27-8-2026'!$A:$AJ,MATCH($A15,'product-export-27-8-2026'!$A:$A,0),MATCH(AP$1,'product-export-27-8-2026'!$1:$1,0)),IF(_xlpm.v="","",_xlpm.v)),"") | AQ15: =IFERROR(_xlfn.LET(_xlpm.v,INDEX('product-export-27-8-2026'!$A:$AJ,MATCH($A15,'product-export-27-8-2026'!$A:$A,0),MATCH(AQ$1,'product-export-27-8-2026'!$1:$1,0)),IF(_xlpm.v="","",_xlpm.v)),"") | AR15: =IFERROR(_xlfn.LET(_xlpm.v,INDEX('product-export-27-8-2026'!$A:$AJ,MATCH($A15,'product-export-27-8-2026'!$A:$A,0),MATCH(AR$1,'product-export-27-8-2026'!$1:$1,0)),IF(_xlpm.v="","",_xlpm.v)),"") -> Diaries, Dorchester Collection, Diaries > Pocket Diaries | AS15: =IFERROR(_xlfn.LET(_xlpm.v,INDEX('product-export-27-8-2026'!$A:$AJ,MATCH($A15,'product-export-27-8-2026'!$A:$A,0),MATCH(AS$1,'product-export-27-8-2026'!$1:$1,0)),IF(_xlpm.v="","",_xlpm.v)),"") -> Dorchester-NewHide-Pocket-Week-to-View
A16: 630 | B16: Dorchester Pocket, Week to View, Blue | C16: Diary | D16: NF-BL-U-095 | E16: NF-BL-U-095 | F16: NF95U | G16: Pocket | H16: Blue | I16: Week to View | J16: White | K16: 18mm x 18mm | L16: 0.42 | M16: 8.99 | N16: 1:9.09;10:8.71;25:5.20;50:4.33;100:3.60;250:2.98;500:2.61;750:2.50;1000:2.31; | O16: =IFERROR(VALUE(_xlfn.TEXTBEFORE(_xlfn.TEXTAFTER(";"&$N16,";"&SUBSTITUTE(O$1,"Qty ","")&":"),";")),"") -> 9.09 | P16: =IFERROR(VALUE(_xlfn.TEXTBEFORE(_xlfn.TEXTAFTER(";"&$N16,";"&SUBSTITUTE(P$1,"Qty ","")&":"),";")),"") -> 8.71 | Q16: =IFERROR(VALUE(_xlfn.TEXTBEFORE(_xlfn.TEXTAFTER(";"&$N16,";"&SUBSTITUTE(Q$1,"Qty ","")&":"),";")),"") -> 5.2 | R16: =IFERROR(VALUE(_xlfn.TEXTBEFORE(_xlfn.TEXTAFTER(";"&$N16,";"&SUBSTITUTE(R$1,"Qty ","")&":"),";")),"") -> 4.33 | S16: =IFERROR(VALUE(_xlfn.TEXTBEFORE(_xlfn.TEXTAFTER(";"&$N16,";"&SUBSTITUTE(S$1,"Qty ","")&":"),";")),"") -> 3.6 | T16: =IFERROR(VALUE(_xlfn.TEXTBEFORE(_xlfn.TEXTAFTER(";"&$N16,";"&SUBSTITUTE(T$1,"Qty ","")&":"),";")),"") -> 2.98 | U16: =IFERROR(VALUE(_xlfn.TEXTBEFORE(_xlfn.TEXTAFTER(";"&$N16,";"&SUBSTITUTE(U$1,"Qty ","")&":"),";")),"") -> 2.61 | V16: =IFERROR(VALUE(_xlfn.TEXTBEFORE(_xlfn.TEXTAFTER(";"&$N16,";"&SUBSTITUTE(V$1,"Qty ","")&":"),";")),"") -> 2.5 | W16: =IFERROR(VALUE(_xlfn.TEXTBEFORE(_xlfn.TEXTAFTER(";"&$N16,";"&SUBSTITUTE(W$1,"Qty ","")&":"),";")),"") -> 2.31 | X16: {=IF(Y16="","",_xlfn.TEXTJOIN(";",TRUE,SUBSTITUTE($Y$1:$AG$1,"Qty ","")&":"&TEXT(Y16:AG16,"0.00"))&";")} -> 1:12.51;10:11.34;25:7.03;50:5.83;100:4.98;250:4.24;500:3.81;750:3.67;1000:3.45; | Y16: ='Blocking Prices'!$C$14+O16 -> 12.51 | Z16: ='Blocking Prices'!$D$14+P16 -> 11.34 | AA16: ='Blocking Prices'!$E$14+Q16 -> 7.03 | AB16: ='Blocking Prices'!$F$14+R16 -> 5.83 | AC16: ='Blocking Prices'!$G$14+S16 -> 4.98 | AD16: ='Blocking Prices'!$H$14+T16 -> 4.24 | AE16: ='Blocking Prices'!$I$14+U16 -> 3.81 | AF16: ='Blocking Prices'!$J$14+V16 -> 3.67 | AG16: ='Blocking Prices'!$K$14+W16 -> 3.45 | AL16: Organize your 2026 in style with the Dorchester Premium Pocket Diary?featuring a soft faux leather cover, recycled white paper, and a convenient Week to View layout. Eco-friendly and elegant | AN16: =IFERROR(_xlfn.LET(_xlpm.v,INDEX('product-export-27-8-2026'!$A:$AJ,MATCH($A16,'product-export-27-8-2026'!$A:$A,0),MATCH(AN$1,'product-export-27-8-2026'!$1:$1,0)),IF(_xlpm.v="","",_xlpm.v)),"") | AO16: =IFERROR(_xlfn.LET(_xlpm.v,INDEX('product-export-27-8-2026'!$A:$AJ,MATCH($A16,'product-export-27-8-2026'!$A:$A,0),MATCH(AO$1,'product-export-27-8-2026'!$1:$1,0)),IF(_xlpm.v="","",_xlpm.v)),"") | AP16: =IFERROR(_xlfn.LET(_xlpm.v,INDEX('product-export-27-8-2026'!$A:$AJ,MATCH($A16,'product-export-27-8-2026'!$A:$A,0),MATCH(AP$1,'product-export-27-8-2026'!$1:$1,0)),IF(_xlpm.v="","",_xlpm.v)),"") | AQ16: =IFERROR(_xlfn.LET(_xlpm.v,INDEX('product-export-27-8-2026'!$A:$AJ,MATCH($A16,'product-export-27-8-2026'!$A:$A,0),MATCH(AQ$1,'product-export-27-8-2026'!$1:$1,0)),IF(_xlpm.v="","",_xlpm.v)),"") | AR16: =IFERROR(_xlfn.LET(_xlpm.v,INDEX('product-export-27-8-2026'!$A:$AJ,MATCH($A16,'product-export-27-8-2026'!$A:$A,0),MATCH(AR$1,'product-export-27-8-2026'!$1:$1,0)),IF(_xlpm.v="","",_xlpm.v)),"") -> Diaries, Dorchester Collection, Diaries > Pocket Diaries | AS16: =IFERROR(_xlfn.LET(_xlpm.v,INDEX('product-export-27-8-2026'!$A:$AJ,MATCH($A16,'product-export-27-8-2026'!$A:$A,0),MATCH(AS$1,'product-export-27-8-2026'!$1:$1,0)),IF(_xlpm.v="","",_xlpm.v)),"") -> Dorchester-NewHide-Pocket-Week-to-View
A17: 632 | B17: Dorchester Pocket, Week to View, Burgundy | C17: Diary | D17: NF-BG-U-095 | E17: NF-BG-U-095 | F17: NF95U | G17: Pocket | H17: Burgundy | I17: Week to View | J17: White | K17: 18mm x 18mm | L17: 0.42 | M17: 8.99 | N17: 1:9.09;10:8.71;25:5.20;50:4.33;100:3.60;250:2.98;500:2.61;750:2.50;1000:2.31; | O17: =IFERROR(VALUE(_xlfn.TEXTBEFORE(_xlfn.TEXTAFTER(";"&$N17,";"&SUBSTITUTE(O$1,"Qty ","")&":"),";")),"") -> 9.09 | P17: =IFERROR(VALUE(_xlfn.TEXTBEFORE(_xlfn.TEXTAFTER(";"&$N17,";"&SUBSTITUTE(P$1,"Qty ","")&":"),";")),"") -> 8.71 | Q17: =IFERROR(VALUE(_xlfn.TEXTBEFORE(_xlfn.TEXTAFTER(";"&$N17,";"&SUBSTITUTE(Q$1,"Qty ","")&":"),";")),"") -> 5.2 | R17: =IFERROR(VALUE(_xlfn.TEXTBEFORE(_xlfn.TEXTAFTER(";"&$N17,";"&SUBSTITUTE(R$1,"Qty ","")&":"),";")),"") -> 4.33 | S17: =IFERROR(VALUE(_xlfn.TEXTBEFORE(_xlfn.TEXTAFTER(";"&$N17,";"&SUBSTITUTE(S$1,"Qty ","")&":"),";")),"") -> 3.6 | T17: =IFERROR(VALUE(_xlfn.TEXTBEFORE(_xlfn.TEXTAFTER(";"&$N17,";"&SUBSTITUTE(T$1,"Qty ","")&":"),";")),"") -> 2.98 | U17: =IFERROR(VALUE(_xlfn.TEXTBEFORE(_xlfn.TEXTAFTER(";"&$N17,";"&SUBSTITUTE(U$1,"Qty ","")&":"),";")),"") -> 2.61 | V17: =IFERROR(VALUE(_xlfn.TEXTBEFORE(_xlfn.TEXTAFTER(";"&$N17,";"&SUBSTITUTE(V$1,"Qty ","")&":"),";")),"") -> 2.5 | W17: =IFERROR(VALUE(_xlfn.TEXTBEFORE(_xlfn.TEXTAFTER(";"&$N17,";"&SUBSTITUTE(W$1,"Qty ","")&":"),";")),"") -> 2.31 | X17: {=IF(Y17="","",_xlfn.TEXTJOIN(";",TRUE,SUBSTITUTE($Y$1:$AG$1,"Qty ","")&":"&TEXT(Y17:AG17,"0.00"))&";")} -> 1:12.51;10:11.34;25:7.03;50:5.83;100:4.98;250:4.24;500:3.81;750:3.67;1000:3.45; | Y17: ='Blocking Prices'!$C$14+O17 -> 12.51 | Z17: ='Blocking Prices'!$D$14+P17 -> 11.34 | AA17: ='Blocking Prices'!$E$14+Q17 -> 7.03 | AB17: ='Blocking Prices'!$F$14+R17 -> 5.83 | AC17: ='Blocking Prices'!$G$14+S17 -> 4.98 | AD17: ='Blocking Prices'!$H$14+T17 -> 4.24 | AE17: ='Blocking Prices'!$I$14+U17 -> 3.81 | AF17: ='Blocking Prices'!$J$14+V17 -> 3.67 | AG17: ='Blocking Prices'!$K$14+W17 -> 3.45 | AL17: Organize your 2026 in style with the Dorchester Premium Pocket Diary?featuring a soft faux leather cover, recycled white paper, and a convenient Week to View layout. Eco-friendly and elegant_x000D_\n<div class="trade-info">_x000D_\n<div class="trade-info__item">_x000D_\n<div class="product-popup-modal__text rte">_x000D_\n_x000D_\n&nbsp;_x000D_\n_x000D_\n</div>_x000D_\n</div>_x000D_\n</div> | AN17: =IFERROR(_xlfn.LET(_xlpm.v,INDEX('product-export-27-8-2026'!$A:$AJ,MATCH($A17,'product-export-27-8-2026'!$A:$A,0),MATCH(AN$1,'product-export-27-8-2026'!$1:$1,0)),IF(_xlpm.v="","",_xlpm.v)),"") | AO17: =IFERROR(_xlfn.LET(_xlpm.v,INDEX('product-export-27-8-2026'!$A:$AJ,MATCH($A17,'product-export-27-8-2026'!$A:$A,0),MATCH(AO$1,'product-export-27-8-2026'!$1:$1,0)),IF(_xlpm.v="","",_xlpm.v)),"") | AP17: =IFERROR(_xlfn.LET(_xlpm.v,INDEX('product-export-27-8-2026'!$A:$AJ,MATCH($A17,'product-export-27-8-2026'!$A:$A,0),MATCH(AP$1,'product-export-27-8-2026'!$1:$1,0)),IF(_xlpm.v="","",_xlpm.v)),"") | AQ17: =IFERROR(_xlfn.LET(_xlpm.v,INDEX('product-export-27-8-2026'!$A:$AJ,MATCH($A17,'product-export-27-8-2026'!$A:$A,0),MATCH(AQ$1,'product-export-27-8-2026'!$1:$1,0)),IF(_xlpm.v="","",_xlpm.v)),"") | AR17: =IFERROR(_xlfn.LET(_xlpm.v,INDEX('product-export-27-8-2026'!$A:$AJ,MATCH($A17,'product-export-27-8-2026'!$A:$A,0),MATCH(AR$1,'product-export-27-8-2026'!$1:$1,0)),IF(_xlpm.v="","",_xlpm.v)),"") -> Diaries, Dorchester Collection, Diaries > Pocket Diaries | AS17: =IFERROR(_xlfn.LET(_xlpm.v,INDEX('product-export-27-8-2026'!$A:$AJ,MATCH($A17,'product-export-27-8-2026'!$A:$A,0),MATCH(AS$1,'product-export-27-8-2026'!$1:$1,0)),IF(_xlpm.v="","",_xlpm.v)),"") -> Dorchester-NewHide-Pocket-Week-to-View
A18: 681 | B18: Chelsea Leather A5 Desk Diary, Day Per Page, Blue | C18: Diary | D18: CL-BL-U-71 | E18: CL-BL-U-71 | F18: CL71U | G18: A5 | H18: Blue | I18: Day Per Page | J18: White | K18: 22mm x 22mm | L18: 0.48 | M18: 21.99 | N18: 1:19.98;10:19.06;25:15.93;50:11.89;100:10.70;250:10.01;500:9.56;750:9.13;1000:8.54; | O18: =IFERROR(VALUE(_xlfn.TEXTBEFORE(_xlfn.TEXTAFTER(";"&$N18,";"&SUBSTITUTE(O$1,"Qty ","")&":"),";")),"") -> 19.98 | P18: =IFERROR(VALUE(_xlfn.TEXTBEFORE(_xlfn.TEXTAFTER(";"&$N18,";"&SUBSTITUTE(P$1,"Qty ","")&":"),";")),"") -> 19.06 | Q18: =IFERROR(VALUE(_xlfn.TEXTBEFORE(_xlfn.TEXTAFTER(";"&$N18,";"&SUBSTITUTE(Q$1,"Qty ","")&":"),";")),"") -> 15.93 | R18: =IFERROR(VALUE(_xlfn.TEXTBEFORE(_xlfn.TEXTAFTER(";"&$N18,";"&SUBSTITUTE(R$1,"Qty ","")&":"),";")),"") -> 11.89 | S18: =IFERROR(VALUE(_xlfn.TEXTBEFORE(_xlfn.TEXTAFTER(";"&$N18,";"&SUBSTITUTE(S$1,"Qty ","")&":"),";")),"") -> 10.7 | T18: =IFERROR(VALUE(_xlfn.TEXTBEFORE(_xlfn.TEXTAFTER(";"&$N18,";"&SUBSTITUTE(T$1,"Qty ","")&":"),";")),"") -> 10.01 | U18: =IFERROR(VALUE(_xlfn.TEXTBEFORE(_xlfn.TEXTAFTER(";"&$N18,";"&SUBSTITUTE(U$1,"Qty ","")&":"),";")),"") -> 9.56 | V18: =IFERROR(VALUE(_xlfn.TEXTBEFORE(_xlfn.TEXTAFTER(";"&$N18,";"&SUBSTITUTE(V$1,"Qty ","")&":"),";")),"") -> 9.13 | W18: =IFERROR(VALUE(_xlfn.TEXTBEFORE(_xlfn.TEXTAFTER(";"&$N18,";"&SUBSTITUTE(W$1,"Qty ","")&":"),";")),"") -> 8.54 | X18: {=IF(Y18="","",_xlfn.TEXTJOIN(";",TRUE,SUBSTITUTE($Y$1:$AG$1,"Qty ","")&":"&TEXT(Y18:AG18,"0.00"))&";")} -> 1:25.20;10:23.46;25:19.50;50:14.86;100:13.43;250:12.39;500:11.93;750:11.44;1000:10.79; | Y18: ='Blocking Prices'!$C$15+O18 -> 25.2 | Z18: ='Blocking Prices'!$D$15+P18 -> 23.46 | AA18: ='Blocking Prices'!$E$15+Q18 -> 19.5 | AB18: ='Blocking Prices'!$F$15+R18 -> 14.86 | AC18: ='Blocking Prices'!$G$15+S18 -> 13.43 | AD18: ='Blocking Prices'!$H$15+T18 -> 12.39 | AE18: ='Blocking Prices'!$I$15+U18 -> 11.93 | AF18: ='Blocking Prices'!$J$15+V18 -> 11.44 | AG18: ='Blocking Prices'!$K$15+W18 -> 10.79 | AL18: <p class="p1">Chelsea Leather range, luxury soft grained real leather?day per page layout.<span class="Apple-converted-space">?</span>Smyth sewn sections for strength and durability printed on white or cream FSC paper.<span class="Apple-converted-space">?</span>Self-colour cotton perimeter stitched flexible cover, ribbon marker, general information pages, forward planners, UK and international holidays, contacts directory, notes page and full colour map section</p> | AM18: Chelsea Leather range, luxury soft grained real leather day per page layout. Smyth sewn sections for strength and durability printed on white or cream FSC paper. Self-colour cotton perimeter stitched flexible cover, ribbon marker, general information pages, forward planners, UK and international holidays, contacts directory, notes page and full colour map section | AN18: =IFERROR(_xlfn.LET(_xlpm.v,INDEX('product-export-27-8-2026'!$A:$AJ,MATCH($A18,'product-export-27-8-2026'!$A:$A,0),MATCH(AN$1,'product-export-27-8-2026'!$1:$1,0)),IF(_xlpm.v="","",_xlpm.v)),"") | AO18: =IFERROR(_xlfn.LET(_xlpm.v,INDEX('product-export-27-8-2026'!$A:$AJ,MATCH($A18,'product-export-27-8-2026'!$A:$A,0),MATCH(AO$1,'product-export-27-8-2026'!$1:$1,0)),IF(_xlpm.v="","",_xlpm.v)),"") | AP18: =IFERROR(_xlfn.LET(_xlpm.v,INDEX('product-export-27-8-2026'!$A:$AJ,MATCH($A18,'product-export-27-8-2026'!$A:$A,0),MATCH(AP$1,'product-export-27-8-2026'!$1:$1,0)),IF(_xlpm.v="","",_xlpm.v)),"") | AQ18: =IFERROR(_xlfn.LET(_xlpm.v,INDEX('product-export-27-8-2026'!$A:$AJ,MATCH($A18,'product-export-27-8-2026'!$A:$A,0),MATCH(AQ$1,'product-export-27-8-2026'!$1:$1,0)),IF(_xlpm.v="","",_xlpm.v)),"") | AR18: =IFERROR(_xlfn.LET(_xlpm.v,INDEX('product-export-27-8-2026'!$A:$AJ,MATCH($A18,'product-export-27-8-2026'!$A:$A,0),MATCH(AR$1,'product-export-27-8-2026'!$1:$1,0)),IF(_xlpm.v="","",_xlpm.v)),"") -> Diaries > A5 Diary, Chelsea Collection, Diaries, Diaries > A5 Diary > DPP, Foil blocked, Diaries > Real Leather | AS18: =IFERROR(_xlfn.LET(_xlpm.v,INDEX('product-export-27-8-2026'!$A:$AJ,MATCH($A18,'product-export-27-8-2026'!$A:$A,0),MATCH(AS$1,'product-export-27-8-2026'!$1:$1,0)),IF(_xlpm.v="","",_xlpm.v)),"")
A19: 685 | B19: Dorchester Horizon A5 Desk Diary, Day Per Page, Black-Black | C19: Diary | D19: HZ-BK/BK-P-071 | E19: HZ-BK/BK-P-071 | F19: HZ76P | G19: A5 | H19: Black-Black | I19: Day Per Page | J19: White | K19: 22mm x 22mm | L19: 0.48 | M19: 15.99 | N19: 1:15.44;10:14.78;25:10.01;50:8.94;100:8.47;250:8.09;500:7.44;750:7.15;1000:6.70; | O19: =IFERROR(VALUE(_xlfn.TEXTBEFORE(_xlfn.TEXTAFTER(";"&$N19,";"&SUBSTITUTE(O$1,"Qty ","")&":"),";")),"") -> 15.44 | P19: =IFERROR(VALUE(_xlfn.TEXTBEFORE(_xlfn.TEXTAFTER(";"&$N19,";"&SUBSTITUTE(P$1,"Qty ","")&":"),";")),"") -> 14.78 | Q19: =IFERROR(VALUE(_xlfn.TEXTBEFORE(_xlfn.TEXTAFTER(";"&$N19,";"&SUBSTITUTE(Q$1,"Qty ","")&":"),";")),"") -> 10.01 | R19: =IFERROR(VALUE(_xlfn.TEXTBEFORE(_xlfn.TEXTAFTER(";"&$N19,";"&SUBSTITUTE(R$1,"Qty ","")&":"),";")),"") -> 8.94 | S19: =IFERROR(VALUE(_xlfn.TEXTBEFORE(_xlfn.TEXTAFTER(";"&$N19,";"&SUBSTITUTE(S$1,"Qty ","")&":"),";")),"") -> 8.47 | T19: =IFERROR(VALUE(_xlfn.TEXTBEFORE(_xlfn.TEXTAFTER(";"&$N19,";"&SUBSTITUTE(T$1,"Qty ","")&":"),";")),"") -> 8.09 | U19: =IFERROR(VALUE(_xlfn.TEXTBEFORE(_xlfn.TEXTAFTER(";"&$N19,";"&SUBSTITUTE(U$1,"Qty ","")&":"),";")),"") -> 7.44 | V19: =IFERROR(VALUE(_xlfn.TEXTBEFORE(_xlfn.TEXTAFTER(";"&$N19,";"&SUBSTITUTE(V$1,"Qty ","")&":"),";")),"") -> 7.15 | W19: =IFERROR(VALUE(_xlfn.TEXTBEFORE(_xlfn.TEXTAFTER(";"&$N19,";"&SUBSTITUTE(W$1,"Qty ","")&":"),";")),"") -> 6.7 | X19: {=IF(Y19="","",_xlfn.TEXTJOIN(";",TRUE,SUBSTITUTE($Y$1:$AG$1,"Qty ","")&":"&TEXT(Y19:AG19,"0.00"))&";")} -> 1:20.66;10:19.18;25:13.58;50:11.91;100:11.20;250:10.47;500:9.81;750:9.46;1000:8.95; | Y19: ='Blocking Prices'!$C$15+O19 -> 20.66 | Z19: ='Blocking Prices'!$D$15+P19 -> 19.18 | AA19: ='Blocking Prices'!$E$15+Q19 -> 13.58 | AB19: ='Blocking Prices'!$F$15+R19 -> 11.91 | AC19: ='Blocking Prices'!$G$15+S19 -> 11.2 | AD19: ='Blocking Prices'!$H$15+T19 -> 10.47 | AE19: ='Blocking Prices'!$I$15+U19 -> 9.81 | AF19: ='Blocking Prices'!$J$15+V19 -> 9.46 | AG19: ='Blocking Prices'!$K$15+W19 -> 8.95 | AL19: <p class="p1">Organize your day with the Dorchester Horizon A5 Desk Diary - Day per Page. Featuring a sleek Horizon design, white paper, and ample space for daily planning, this stylish diary is perfect for busy professionals on the go.</p> | AM19: The Dorchester horizon A5 Diary - White Paper ? Day per Page is designed for those who need both elegance and practicality in their daily planning. Featuring a striking bicolour design, this A5-sized diary is bound in premium materials that offer a smooth, luxurious feel, while its contrasting colours add a modern touch to your desk or workspace. This diary is the perfect balance of style and function, ideal for busy professionals or anyone looking for an organized, high-quality planning solution._x000D_\n_x000D_\nWith a day-per-page layout, each page offers ample space for your appointments, notes, and to-do lists. The white paper enhances readability and provides a clean, crisp backdrop for your writing. Whether you need to keep track of meetings, deadlines, or personal goals, this diary ensures you have everything in one place, clearly organized. The real perimeter stitching and elegant ribbon marker add both durability and style, making this diary a practical and luxurious choice for anyone who values attention to detail in their organizational tools. | AN19: =IFERROR(_xlfn.LET(_xlpm.v,INDEX('product-export-27-8-2026'!$A:$AJ,MATCH($A19,'product-export-27-8-2026'!$A:$A,0),MATCH(AN$1,'product-export-27-8-2026'!$1:$1,0)),IF(_xlpm.v="","",_xlpm.v)),"") | AO19: =IFERROR(_xlfn.LET(_xlpm.v,INDEX('product-export-27-8-2026'!$A:$AJ,MATCH($A19,'product-export-27-8-2026'!$A:$A,0),MATCH(AO$1,'product-export-27-8-2026'!$1:$1,0)),IF(_xlpm.v="","",_xlpm.v)),"") | AP19: =IFERROR(_xlfn.LET(_xlpm.v,INDEX('product-export-27-8-2026'!$A:$AJ,MATCH($A19,'product-export-27-8-2026'!$A:$A,0),MATCH(AP$1,'product-export-27-8-2026'!$1:$1,0)),IF(_xlpm.v="","",_xlpm.v)),"") | AQ19: =IFERROR(_xlfn.LET(_xlpm.v,INDEX('product-export-27-8-2026'!$A:$AJ,MATCH($A19,'product-export-27-8-2026'!$A:$A,0),MATCH(AQ$1,'product-export-27-8-2026'!$1:$1,0)),IF(_xlpm.v="","",_xlpm.v)),"") | AR19: =IFERROR(_xlfn.LET(_xlpm.v,INDEX('product-export-27-8-2026'!$A:$AJ,MATCH($A19,'product-export-27-8-2026'!$A:$A,0),MATCH(AR$1,'product-export-27-8-2026'!$1:$1,0)),IF(_xlpm.v="","",_xlpm.v)),"") -> Diaries > A5 Diary, Diaries, Dorchester Collection, Diaries > A5 Diary > DPP | AS19: =IFERROR(_xlfn.LET(_xlpm.v,INDEX('product-export-27-8-2026'!$A:$AJ,MATCH($A19,'product-export-27-8-2026'!$A:$A,0),MATCH(AS$1,'product-export-27-8-2026'!$1:$1,0)),IF(_xlpm.v="","",_xlpm.v)),"") -> Dorchester-Horizon-A5-Desk-Diary-Day-Per-Page
A20: 687 | B20: Dorchester Horizon A5 Desk Diary, Day Per Page, Black-Grey | C20: Diary | D20: HZ-BK/GY-P-071 | E20: HZ-BK/GY-P-071 | F20: HZ76P | G20: A5 | H20: Black-Grey | I20: Day Per Page | J20: White | K20: 22mm x 22mm | L20: 0.48 | M20: 15.99 | N20: 1:15.44;10:14.78;25:10.01;50:8.94;100:8.47;250:8.09;500:7.44;750:7.15;1000:6.70; | O20: =IFERROR(VALUE(_xlfn.TEXTBEFORE(_xlfn.TEXTAFTER(";"&$N20,";"&SUBSTITUTE(O$1,"Qty ","")&":"),";")),"") -> 15.44 | P20: =IFERROR(VALUE(_xlfn.TEXTBEFORE(_xlfn.TEXTAFTER(";"&$N20,";"&SUBSTITUTE(P$1,"Qty ","")&":"),";")),"") -> 14.78 | Q20: =IFERROR(VALUE(_xlfn.TEXTBEFORE(_xlfn.TEXTAFTER(";"&$N20,";"&SUBSTITUTE(Q$1,"Qty ","")&":"),";")),"") -> 10.01 | R20: =IFERROR(VALUE(_xlfn.TEXTBEFORE(_xlfn.TEXTAFTER(";"&$N20,";"&SUBSTITUTE(R$1,"Qty ","")&":"),";")),"") -> 8.94 | S20: =IFERROR(VALUE(_xlfn.TEXTBEFORE(_xlfn.TEXTAFTER(";"&$N20,";"&SUBSTITUTE(S$1,"Qty ","")&":"),";")),"") -> 8.47 | T20: =IFERROR(VALUE(_xlfn.TEXTBEFORE(_xlfn.TEXTAFTER(";"&$N20,";"&SUBSTITUTE(T$1,"Qty ","")&":"),";")),"") -> 8.09 | U20: =IFERROR(VALUE(_xlfn.TEXTBEFORE(_xlfn.TEXTAFTER(";"&$N20,";"&SUBSTITUTE(U$1,"Qty ","")&":"),";")),"") -> 7.44 | V20: =IFERROR(VALUE(_xlfn.TEXTBEFORE(_xlfn.TEXTAFTER(";"&$N20,";"&SUBSTITUTE(V$1,"Qty ","")&":"),";")),"") -> 7.15 | W20: =IFERROR(VALUE(_xlfn.TEXTBEFORE(_xlfn.TEXTAFTER(";"&$N20,";"&SUBSTITUTE(W$1,"Qty ","")&":"),";")),"") -> 6.7 | X20: {=IF(Y20="","",_xlfn.TEXTJOIN(";",TRUE,SUBSTITUTE($Y$1:$AG$1,"Qty ","")&":"&TEXT(Y20:AG20,"0.00"))&";")} -> 1:20.66;10:19.18;25:13.58;50:11.91;100:11.20;250:10.47;500:9.81;750:9.46;1000:8.95; | Y20: ='Blocking Prices'!$C$15+O20 -> 20.66 | Z20: ='Blocking Prices'!$D$15+P20 -> 19.18 | AA20: ='Blocking Prices'!$E$15+Q20 -> 13.58 | AB20: ='Blocking Prices'!$F$15+R20 -> 11.91 | AC20: ='Blocking Prices'!$G$15+S20 -> 11.2 | AD20: ='Blocking Prices'!$H$15+T20 -> 10.47 | AE20: ='Blocking Prices'!$I$15+U20 -> 9.81 | AF20: ='Blocking Prices'!$J$15+V20 -> 9.46 | AG20: ='Blocking Prices'!$K$15+W20 -> 8.95 | AL20: <p class="p1">Organize your day with the Dorchester Horizon A5 Desk Diary - Day per Page. Featuring a sleek Horizon design, white paper, and ample space for daily planning, this stylish diary is perfect for busy professionals on the go.</p>_x000D_\n&nbsp; | AM20: The Dorchester horizon A5 Diary - White Paper ? Day per Page is designed for those who need both elegance and practicality in their daily planning. Featuring a striking bicolour design, this A5-sized diary is bound in premium materials that offer a smooth, luxurious feel, while its contrasting colours add a modern touch to your desk or workspace. This diary is the perfect balance of style and function, ideal for busy professionals or anyone looking for an organized, high-quality planning solution._x000D_\n_x000D_\nWith a day-per-page layout, each page offers ample space for your appointments, notes, and to-do lists. The white paper enhances readability and provides a clean, crisp backdrop for your writing. Whether you need to keep track of meetings, deadlines, or personal goals, this diary ensures you have everything in one place, clearly organized. The real perimeter stitching and elegant ribbon marker add both durability and style, making this diary a practical and luxurious choice for anyone who values attention to detail in their organizational tools. | AN20: =IFERROR(_xlfn.LET(_xlpm.v,INDEX('product-export-27-8-2026'!$A:$AJ,MATCH($A20,'product-export-27-8-2026'!$A:$A,0),MATCH(AN$1,'product-export-27-8-2026'!$1:$1,0)),IF(_xlpm.v="","",_xlpm.v)),"") | AO20: =IFERROR(_xlfn.LET(_xlpm.v,INDEX('product-export-27-8-2026'!$A:$AJ,MATCH($A20,'product-export-27-8-2026'!$A:$A,0),MATCH(AO$1,'product-export-27-8-2026'!$1:$1,0)),IF(_xlpm.v="","",_xlpm.v)),"") | AP20: =IFERROR(_xlfn.LET(_xlpm.v,INDEX('product-export-27-8-2026'!$A:$AJ,MATCH($A20,'product-export-27-8-2026'!$A:$A,0),MATCH(AP$1,'product-export-27-8-2026'!$1:$1,0)),IF(_xlpm.v="","",_xlpm.v)),"") | AQ20: =IFERROR(_xlfn.LET(_xlpm.v,INDEX('product-export-27-8-2026'!$A:$AJ,MATCH($A20,'product-export-27-8-2026'!$A:$A,0),MATCH(AQ$1,'product-export-27-8-2026'!$1:$1,0)),IF(_xlpm.v="","",_xlpm.v)),"") | AR20: =IFERROR(_xlfn.LET(_xlpm.v,INDEX('product-export-27-8-2026'!$A:$AJ,MATCH($A20,'product-export-27-8-2026'!$A:$A,0),MATCH(AR$1,'product-export-27-8-2026'!$1:$1,0)),IF(_xlpm.v="","",_xlpm.v)),"") -> Diaries > A5 Diary, Diaries, Dorchester Collection, Diaries > A5 Diary > DPP | AS20: =IFERROR(_xlfn.LET(_xlpm.v,INDEX('product-export-27-8-2026'!$A:$AJ,MATCH($A20,'product-export-27-8-2026'!$A:$A,0),MATCH(AS$1,'product-export-27-8-2026'!$1:$1,0)),IF(_xlpm.v="","",_xlpm.v)),"") -> Dorchester-Horizon-A5-Desk-Diary-Day-Per-Page
A21: 689 | B21: Dorchester Horizon A5 Desk Diary, Day Per Page, Black-Red | C21: Diary | D21: HZ-BK/RD-P-071 | E21: HZ-BK/RD-P-071 | F21: HZ76P | G21: A5 | H21: Black-Red | I21: Day Per Page | J21: White | K21: 22mm x 22mm | L21: 0.48 | M21: 15.99 | N21: 1:15.44;10:14.78;25:10.01;50:8.94;100:8.47;250:8.09;500:7.44;750:7.15;1000:6.70; | O21: =IFERROR(VALUE(_xlfn.TEXTBEFORE(_xlfn.TEXTAFTER(";"&$N21,";"&SUBSTITUTE(O$1,"Qty ","")&":"),";")),"") -> 15.44 | P21: =IFERROR(VALUE(_xlfn.TEXTBEFORE(_xlfn.TEXTAFTER(";"&$N21,";"&SUBSTITUTE(P$1,"Qty ","")&":"),";")),"") -> 14.78 | Q21: =IFERROR(VALUE(_xlfn.TEXTBEFORE(_xlfn.TEXTAFTER(";"&$N21,";"&SUBSTITUTE(Q$1,"Qty ","")&":"),";")),"") -> 10.01 | R21: =IFERROR(VALUE(_xlfn.TEXTBEFORE(_xlfn.TEXTAFTER(";"&$N21,";"&SUBSTITUTE(R$1,"Qty ","")&":"),";")),"") -> 8.94 | S21: =IFERROR(VALUE(_xlfn.TEXTBEFORE(_xlfn.TEXTAFTER(";"&$N21,";"&SUBSTITUTE(S$1,"Qty ","")&":"),";")),"") -> 8.47 | T21: =IFERROR(VALUE(_xlfn.TEXTBEFORE(_xlfn.TEXTAFTER(";"&$N21,";"&SUBSTITUTE(T$1,"Qty ","")&":"),";")),"") -> 8.09 | U21: =IFERROR(VALUE(_xlfn.TEXTBEFORE(_xlfn.TEXTAFTER(";"&$N21,";"&SUBSTITUTE(U$1,"Qty ","")&":"),";")),"") -> 7.44 | V21: =IFERROR(VALUE(_xlfn.TEXTBEFORE(_xlfn.TEXTAFTER(";"&$N21,";"&SUBSTITUTE(V$1,"Qty ","")&":"),";")),"") -> 7.15 | W21: =IFERROR(VALUE(_xlfn.TEXTBEFORE(_xlfn.TEXTAFTER(";"&$N21,";"&SUBSTITUTE(W$1,"Qty ","")&":"),";")),"") -> 6.7 | X21: {=IF(Y21="","",_xlfn.TEXTJOIN(";",TRUE,SUBSTITUTE($Y$1:$AG$1,"Qty ","")&":"&TEXT(Y21:AG21,"0.00"))&";")} -> 1:20.66;10:19.18;25:13.58;50:11.91;100:11.20;250:10.47;500:9.81;750:9.46;1000:8.95; | Y21: ='Blocking Prices'!$C$15+O21 -> 20.66 | Z21: ='Blocking Prices'!$D$15+P21 -> 19.18 | AA21: ='Blocking Prices'!$E$15+Q21 -> 13.58 | AB21: ='Blocking Prices'!$F$15+R21 -> 11.91 | AC21: ='Blocking Prices'!$G$15+S21 -> 11.2 | AD21: ='Blocking Prices'!$H$15+T21 -> 10.47 | AE21: ='Blocking Prices'!$I$15+U21 -> 9.81 | AF21: ='Blocking Prices'!$J$15+V21 -> 9.46 | AG21: ='Blocking Prices'!$K$15+W21 -> 8.95 | AL21: <p class="p1">Organize your day with the Dorchester Horizon A5 Desk Diary - Day per Page. Featuring a sleek Horizon design, white paper, and ample space for daily planning, this stylish diary is perfect for busy professionals on the go.</p>_x000D_\n&nbsp; | AM21: The Dorchester horizon A5 Diary - White Paper ? Day per Page is designed for those who need both elegance and practicality in their daily planning. Featuring a striking bicolour design, this A5-sized diary is bound in premium materials that offer a smooth, luxurious feel, while its contrasting colours add a modern touch to your desk or workspace. This diary is the perfect balance of style and function, ideal for busy professionals or anyone looking for an organized, high-quality planning solution._x000D_\n_x000D_\nWith a day-per-page layout, each page offers ample space for your appointments, notes, and to-do lists. The white paper enhances readability and provides a clean, crisp backdrop for your writing. Whether you need to keep track of meetings, deadlines, or personal goals, this diary ensures you have everything in one place, clearly organized. The real perimeter stitching and elegant ribbon marker add both durability and style, making this diary a practical and luxurious choice for anyone who values attention to detail in their organizational tools. | AN21: =IFERROR(_xlfn.LET(_xlpm.v,INDEX('product-export-27-8-2026'!$A:$AJ,MATCH($A21,'product-export-27-8-2026'!$A:$A,0),MATCH(AN$1,'product-export-27-8-2026'!$1:$1,0)),IF(_xlpm.v="","",_xlpm.v)),"") | AO21: =IFERROR(_xlfn.LET(_xlpm.v,INDEX('product-export-27-8-2026'!$A:$AJ,MATCH($A21,'product-export-27-8-2026'!$A:$A,0),MATCH(AO$1,'product-export-27-8-2026'!$1:$1,0)),IF(_xlpm.v="","",_xlpm.v)),"") | AP21: =IFERROR(_xlfn.LET(_xlpm.v,INDEX('product-export-27-8-2026'!$A:$AJ,MATCH($A21,'product-export-27-8-2026'!$A:$A,0),MATCH(AP$1,'product-export-27-8-2026'!$1:$1,0)),IF(_xlpm.v="","",_xlpm.v)),"") | AQ21: =IFERROR(_xlfn.LET(_xlpm.v,INDEX('product-export-27-8-2026'!$A:$AJ,MATCH($A21,'product-export-27-8-2026'!$A:$A,0),MATCH(AQ$1,'product-export-27-8-2026'!$1:$1,0)),IF(_xlpm.v="","",_xlpm.v)),"") | AR21: =IFERROR(_xlfn.LET(_xlpm.v,INDEX('product-export-27-8-2026'!$A:$AJ,MATCH($A21,'product-export-27-8-2026'!$A:$A,0),MATCH(AR$1,'product-export-27-8-2026'!$1:$1,0)),IF(_xlpm.v="","",_xlpm.v)),"") -> Diaries > A5 Diary, Diaries, Dorchester Collection, Diaries > A5 Diary > DPP | AS21: =IFERROR(_xlfn.LET(_xlpm.v,INDEX('product-export-27-8-2026'!$A:$AJ,MATCH($A21,'product-export-27-8-2026'!$A:$A,0),MATCH(AS$1,'product-export-27-8-2026'!$1:$1,0)),IF(_xlpm.v="","",_xlpm.v)),"") -> Dorchester-Horizon-A5-Desk-Diary-Day-Per-Page
A22: 691 | B22: Dorchester Horizon A5 Desk Diary, Day Per Page, Black-Yellow | C22: Diary | D22: HZ-BK/YE-P-071 | E22: HZ-BK/YE-P-071 | F22: HZ76P | G22: A5 | H22: Black-Yellow | I22: Day Per Page | J22: White | K22: 22mm x 22mm | L22: 0.48 | M22: 15.99 | N22: 1:15.44;10:14.78;25:10.01;50:8.94;100:8.47;250:8.09;500:7.44;750:7.15;1000:6.70; | O22: =IFERROR(VALUE(_xlfn.TEXTBEFORE(_xlfn.TEXTAFTER(";"&$N22,";"&SUBSTITUTE(O$1,"Qty ","")&":"),";")),"") -> 15.44 | P22: =IFERROR(VALUE(_xlfn.TEXTBEFORE(_xlfn.TEXTAFTER(";"&$N22,";"&SUBSTITUTE(P$1,"Qty ","")&":"),";")),"") -> 14.78 | Q22: =IFERROR(VALUE(_xlfn.TEXTBEFORE(_xlfn.TEXTAFTER(";"&$N22,";"&SUBSTITUTE(Q$1,"Qty ","")&":"),";")),"") -> 10.01 | R22: =IFERROR(VALUE(_xlfn.TEXTBEFORE(_xlfn.TEXTAFTER(";"&$N22,";"&SUBSTITUTE(R$1,"Qty ","")&":"),";")),"") -> 8.94 | S22: =IFERROR(VALUE(_xlfn.TEXTBEFORE(_xlfn.TEXTAFTER(";"&$N22,";"&SUBSTITUTE(S$1,"Qty ","")&":"),";")),"") -> 8.47 | T22: =IFERROR(VALUE(_xlfn.TEXTBEFORE(_xlfn.TEXTAFTER(";"&$N22,";"&SUBSTITUTE(T$1,"Qty ","")&":"),";")),"") -> 8.09 | U22: =IFERROR(VALUE(_xlfn.TEXTBEFORE(_xlfn.TEXTAFTER(";"&$N22,";"&SUBSTITUTE(U$1,"Qty ","")&":"),";")),"") -> 7.44 | V22: =IFERROR(VALUE(_xlfn.TEXTBEFORE(_xlfn.TEXTAFTER(";"&$N22,";"&SUBSTITUTE(V$1,"Qty ","")&":"),";")),"") -> 7.15 | W22: =IFERROR(VALUE(_xlfn.TEXTBEFORE(_xlfn.TEXTAFTER(";"&$N22,";"&SUBSTITUTE(W$1,"Qty ","")&":"),";")),"") -> 6.7 | X22: {=IF(Y22="","",_xlfn.TEXTJOIN(";",TRUE,SUBSTITUTE($Y$1:$AG$1,"Qty ","")&":"&TEXT(Y22:AG22,"0.00"))&";")} -> 1:20.66;10:19.18;25:13.58;50:11.91;100:11.20;250:10.47;500:9.81;750:9.46;1000:8.95; | Y22: ='Blocking Prices'!$C$15+O22 -> 20.66 | Z22: ='Blocking Prices'!$D$15+P22 -> 19.18 | AA22: ='Blocking Prices'!$E$15+Q22 -> 13.58 | AB22: ='Blocking Prices'!$F$15+R22 -> 11.91 | AC22: ='Blocking Prices'!$G$15+S22 -> 11.2 | AD22: ='Blocking Prices'!$H$15+T22 -> 10.47 | AE22: ='Blocking Prices'!$I$15+U22 -> 9.81 | AF22: ='Blocking Prices'!$J$15+V22 -> 9.46 | AG22: ='Blocking Prices'!$K$15+W22 -> 8.95 | AL22: <p class="p1">Organize your day with the Dorchester Horizon A5 Desk Diary - Day per Page. Featuring a sleek Horizon design, white paper, and ample space for daily planning, this stylish diary is perfect for busy professionals on the go.</p>_x000D_\n&nbsp; | AM22: The Dorchester horizon A5 Diary - White Paper ? Day per Page is designed for those who need both elegance and practicality in their daily planning. Featuring a striking bicolour design, this A5-sized diary is bound in premium materials that offer a smooth, luxurious feel, while its contrasting colours add a modern touch to your desk or workspace. This diary is the perfect balance of style and function, ideal for busy professionals or anyone looking for an organized, high-quality planning solution._x000D_\n_x000D_\nWith a day-per-page layout, each page offers ample space for your appointments, notes, and to-do lists. The white paper enhances readability and provides a clean, crisp backdrop for your writing. Whether you need to keep track of meetings, deadlines, or personal goals, this diary ensures you have everything in one place, clearly organized. The real perimeter stitching and elegant ribbon marker add both durability and style, making this diary a practical and luxurious choice for anyone who values attention to detail in their organizational tools. | AN22: =IFERROR(_xlfn.LET(_xlpm.v,INDEX('product-export-27-8-2026'!$A:$AJ,MATCH($A22,'product-export-27-8-2026'!$A:$A,0),MATCH(AN$1,'product-export-27-8-2026'!$1:$1,0)),IF(_xlpm.v="","",_xlpm.v)),"") | AO22: =IFERROR(_xlfn.LET(_xlpm.v,INDEX('product-export-27-8-2026'!$A:$AJ,MATCH($A22,'product-export-27-8-2026'!$A:$A,0),MATCH(AO$1,'product-export-27-8-2026'!$1:$1,0)),IF(_xlpm.v="","",_xlpm.v)),"") | AP22: =IFERROR(_xlfn.LET(_xlpm.v,INDEX('product-export-27-8-2026'!$A:$AJ,MATCH($A22,'product-export-27-8-2026'!$A:$A,0),MATCH(AP$1,'product-export-27-8-2026'!$1:$1,0)),IF(_xlpm.v="","",_xlpm.v)),"") | AQ22: =IFERROR(_xlfn.LET(_xlpm.v,INDEX('product-export-27-8-2026'!$A:$AJ,MATCH($A22,'product-export-27-8-2026'!$A:$A,0),MATCH(AQ$1,'product-export-27-8-2026'!$1:$1,0)),IF(_xlpm.v="","",_xlpm.v)),"") | AR22: =IFERROR(_xlfn.LET(_xlpm.v,INDEX('product-export-27-8-2026'!$A:$AJ,MATCH($A22,'product-export-27-8-2026'!$A:$A,0),MATCH(AR$1,'product-export-27-8-2026'!$1:$1,0)),IF(_xlpm.v="","",_xlpm.v)),"") -> Diaries > A5 Diary, Diaries, Dorchester Collection, Diaries > A5 Diary > DPP | AS22: =IFERROR(_xlfn.LET(_xlpm.v,INDEX('product-export-27-8-2026'!$A:$AJ,MATCH($A22,'product-export-27-8-2026'!$A:$A,0),MATCH(AS$1,'product-export-27-8-2026'!$1:$1,0)),IF(_xlpm.v="","",_xlpm.v)),"") -> Dorchester-Horizon-A5-Desk-Diary-Day-Per-Page
A23: 693 | B23: Dorchester Horizon A5 Desk Diary, Day Per Page, Green-Green | C23: Diary | D23: HZ-GN/GN-P-071 | E23: HZ-GN/GN-P-071 | F23: HZ76P | G23: A5 | H23: Green-Green | I23: Day Per Page | J23: White | K23: 22mm x 22mm | L23: 0.48 | M23: 15.99 | N23: 1:15.44;10:14.78;25:10.01;50:8.94;100:8.47;250:8.09;500:7.44;750:7.15;1000:6.70; | O23: =IFERROR(VALUE(_xlfn.TEXTBEFORE(_xlfn.TEXTAFTER(";"&$N23,";"&SUBSTITUTE(O$1,"Qty ","")&":"),";")),"") -> 15.44 | P23: =IFERROR(VALUE(_xlfn.TEXTBEFORE(_xlfn.TEXTAFTER(";"&$N23,";"&SUBSTITUTE(P$1,"Qty ","")&":"),";")),"") -> 14.78 | Q23: =IFERROR(VALUE(_xlfn.TEXTBEFORE(_xlfn.TEXTAFTER(";"&$N23,";"&SUBSTITUTE(Q$1,"Qty ","")&":"),";")),"") -> 10.01 | R23: =IFERROR(VALUE(_xlfn.TEXTBEFORE(_xlfn.TEXTAFTER(";"&$N23,";"&SUBSTITUTE(R$1,"Qty ","")&":"),";")),"") -> 8.94 | S23: =IFERROR(VALUE(_xlfn.TEXTBEFORE(_xlfn.TEXTAFTER(";"&$N23,";"&SUBSTITUTE(S$1,"Qty ","")&":"),";")),"") -> 8.47 | T23: =IFERROR(VALUE(_xlfn.TEXTBEFORE(_xlfn.TEXTAFTER(";"&$N23,";"&SUBSTITUTE(T$1,"Qty ","")&":"),";")),"") -> 8.09 | U23: =IFERROR(VALUE(_xlfn.TEXTBEFORE(_xlfn.TEXTAFTER(";"&$N23,";"&SUBSTITUTE(U$1,"Qty ","")&":"),";")),"") -> 7.44 | V23: =IFERROR(VALUE(_xlfn.TEXTBEFORE(_xlfn.TEXTAFTER(";"&$N23,";"&SUBSTITUTE(V$1,"Qty ","")&":"),";")),"") -> 7.15 | W23: =IFERROR(VALUE(_xlfn.TEXTBEFORE(_xlfn.TEXTAFTER(";"&$N23,";"&SUBSTITUTE(W$1,"Qty ","")&":"),";")),"") -> 6.7 | X23: {=IF(Y23="","",_xlfn.TEXTJOIN(";",TRUE,SUBSTITUTE($Y$1:$AG$1,"Qty ","")&":"&TEXT(Y23:AG23,"0.00"))&";")} -> 1:20.66;10:19.18;25:13.58;50:11.91;100:11.20;250:10.47;500:9.81;750:9.46;1000:8.95; | Y23: ='Blocking Prices'!$C$15+O23 -> 20.66 | Z23: ='Blocking Prices'!$D$15+P23 -> 19.18 | AA23: ='Blocking Prices'!$E$15+Q23 -> 13.58 | AB23: ='Blocking Prices'!$F$15+R23 -> 11.91 | AC23: ='Blocking Prices'!$G$15+S23 -> 11.2 | AD23: ='Blocking Prices'!$H$15+T23 -> 10.47 | AE23: ='Blocking Prices'!$I$15+U23 -> 9.81 | AF23: ='Blocking Prices'!$J$15+V23 -> 9.46 | AG23: ='Blocking Prices'!$K$15+W23 -> 8.95 | AL23: <p class="p1">Organize your day with the Dorchester Horizon A5 Desk Diary - Day per Page. Featuring a sleek Horizon design, white paper, and ample space for daily planning, this stylish diary is perfect for busy professionals on the go.</p>_x000D_\n&nbsp; | AM23: The Dorchester horizon A5 Diary - White Paper ? Day per Page is designed for those who need both elegance and practicality in their daily planning. Featuring a striking bicolour design, this A5-sized diary is bound in premium materials that offer a smooth, luxurious feel, while its contrasting colours add a modern touch to your desk or workspace. This diary is the perfect balance of style and function, ideal for busy professionals or anyone looking for an organized, high-quality planning solution._x000D_\n_x000D_\nWith a day-per-page layout, each page offers ample space for your appointments, notes, and to-do lists. The white paper enhances readability and provides a clean, crisp backdrop for your writing. Whether you need to keep track of meetings, deadlines, or personal goals, this diary ensures you have everything in one place, clearly organized. The real perimeter stitching and elegant ribbon marker add both durability and style, making this diary a practical and luxurious choice for anyone who values attention to detail in their organizational tools. | AN23: =IFERROR(_xlfn.LET(_xlpm.v,INDEX('product-export-27-8-2026'!$A:$AJ,MATCH($A23,'product-export-27-8-2026'!$A:$A,0),MATCH(AN$1,'product-export-27-8-2026'!$1:$1,0)),IF(_xlpm.v="","",_xlpm.v)),"") | AO23: =IFERROR(_xlfn.LET(_xlpm.v,INDEX('product-export-27-8-2026'!$A:$AJ,MATCH($A23,'product-export-27-8-2026'!$A:$A,0),MATCH(AO$1,'product-export-27-8-2026'!$1:$1,0)),IF(_xlpm.v="","",_xlpm.v)),"") | AP23: =IFERROR(_xlfn.LET(_xlpm.v,INDEX('product-export-27-8-2026'!$A:$AJ,MATCH($A23,'product-export-27-8-2026'!$A:$A,0),MATCH(AP$1,'product-export-27-8-2026'!$1:$1,0)),IF(_xlpm.v="","",_xlpm.v)),"") | AQ23: =IFERROR(_xlfn.LET(_xlpm.v,INDEX('product-export-27-8-2026'!$A:$AJ,MATCH($A23,'product-export-27-8-2026'!$A:$A,0),MATCH(AQ$1,'product-export-27-8-2026'!$1:$1,0)),IF(_xlpm.v="","",_xlpm.v)),"") | AR23: =IFERROR(_xlfn.LET(_xlpm.v,INDEX('product-export-27-8-2026'!$A:$AJ,MATCH($A23,'product-export-27-8-2026'!$A:$A,0),MATCH(AR$1,'product-export-27-8-2026'!$1:$1,0)),IF(_xlpm.v="","",_xlpm.v)),"") -> Diaries > A5 Diary, Diaries, Dorchester Collection, Diaries > A5 Diary > DPP | AS23: =IFERROR(_xlfn.LET(_xlpm.v,INDEX('product-export-27-8-2026'!$A:$AJ,MATCH($A23,'product-export-27-8-2026'!$A:$A,0),MATCH(AS$1,'product-export-27-8-2026'!$1:$1,0)),IF(_xlpm.v="","",_xlpm.v)),"") -> Dorchester-Horizon-A5-Desk-Diary-Day-Per-Page
A24: 843 | B24: Dorchester A5 Desk Diary, Day Per Page, Black | C24: Diary | D24: NF-BK-U-071 | E24: NF-BK-U-071 | F24: NF71U | G24: A5 | H24: Black | I24: Day Per Page | J24: White | K24: 22mm x 22mm | L24: 0.48 | M24: 17.99 | N24: 1:16.98;10:16.23;25:12.35;50:9.38;100:8.62;250:7.78;500:6.70;750:6.33;1000:5.76; | O24: =IFERROR(VALUE(_xlfn.TEXTBEFORE(_xlfn.TEXTAFTER(";"&$N24,";"&SUBSTITUTE(O$1,"Qty ","")&":"),";")),"") -> 16.98 | P24: =IFERROR(VALUE(_xlfn.TEXTBEFORE(_xlfn.TEXTAFTER(";"&$N24,";"&SUBSTITUTE(P$1,"Qty ","")&":"),";")),"") -> 16.23 | Q24: =IFERROR(VALUE(_xlfn.TEXTBEFORE(_xlfn.TEXTAFTER(";"&$N24,";"&SUBSTITUTE(Q$1,"Qty ","")&":"),";")),"") -> 12.35 | R24: =IFERROR(VALUE(_xlfn.TEXTBEFORE(_xlfn.TEXTAFTER(";"&$N24,";"&SUBSTITUTE(R$1,"Qty ","")&":"),";")),"") -> 9.38 | S24: =IFERROR(VALUE(_xlfn.TEXTBEFORE(_xlfn.TEXTAFTER(";"&$N24,";"&SUBSTITUTE(S$1,"Qty ","")&":"),";")),"") -> 8.62 | T24: =IFERROR(VALUE(_xlfn.TEXTBEFORE(_xlfn.TEXTAFTER(";"&$N24,";"&SUBSTITUTE(T$1,"Qty ","")&":"),";")),"") -> 7.78 | U24: =IFERROR(VALUE(_xlfn.TEXTBEFORE(_xlfn.TEXTAFTER(";"&$N24,";"&SUBSTITUTE(U$1,"Qty ","")&":"),";")),"") -> 6.7 | V24: =IFERROR(VALUE(_xlfn.TEXTBEFORE(_xlfn.TEXTAFTER(";"&$N24,";"&SUBSTITUTE(V$1,"Qty ","")&":"),";")),"") -> 6.33 | W24: =IFERROR(VALUE(_xlfn.TEXTBEFORE(_xlfn.TEXTAFTER(";"&$N24,";"&SUBSTITUTE(W$1,"Qty ","")&":"),";")),"") -> 5.76 | X24: {=IF(Y24="","",_xlfn.TEXTJOIN(";",TRUE,SUBSTITUTE($Y$1:$AG$1,"Qty ","")&":"&TEXT(Y24:AG24,"0.00"))&";")} -> 1:22.20;10:20.63;25:15.92;50:12.35;100:11.35;250:10.16;500:9.07;750:8.64;1000:8.01; | Y24: ='Blocking Prices'!$C$15+O24 -> 22.2 | Z24: ='Blocking Prices'!$D$15+P24 -> 20.63 | AA24: ='Blocking Prices'!$E$15+Q24 -> 15.92 | AB24: ='Blocking Prices'!$F$15+R24 -> 12.35 | AC24: ='Blocking Prices'!$G$15+S24 -> 11.35 | AD24: ='Blocking Prices'!$H$15+T24 -> 10.16 | AE24: ='Blocking Prices'!$I$15+U24 -> 9.07 | AF24: ='Blocking Prices'!$J$15+V24 -> 8.64 | AG24: ='Blocking Prices'!$K$15+W24 -> 8.01 | AL24: Plan your 2026 in detail with the Dorchester newhide A5 Desk Diary? Self?colour perimeter cotton stitched flexible cover, FSC-certified recycled white paper, and a Day per Page layout. Elegant, sustainable, and practical._x000D_\n_x000D_\n&nbsp; | AM24: <div class="about">_x000D_\n<div class="about__accordion-item">_x000D_\n<div class="about__accordion-description richtext__content">_x000D_\n<div class="metafield-rich_text_field">_x000D_\n_x000D_\nIntroducing the Dorchester Newhide A5 Desk Diary ? White Paper ? Day per Page, the perfect planning solution for those who need detailed, day-by-day organization in 2025. Crafted from the same high-quality, vegan leather durable as the rest of our Dorchester range, this diary has been designed for maximum comfort and practicality. Its soft, lightweight, and flexible cover combines luxury with functionality, ensuring it holds up to daily use while feeling great in hand._x000D_\n_x000D_\nThe diary is meticulously finished with coordinated perimeter stitching, giving it a refined and polished appearance. Inside, you?ll find FSC-certified recycled white paper, offering an eco-conscious choice for professionals and planners alike. The Day per Page layout provides ample space for detailed scheduling, note-taking, or task tracking, allowing you to manage each day with precision._x000D_\n_x000D_\nIdeal for busy professionals, students, or anyone who values structured, daily planning, this A5 desk diary is compact enough to sit neatly on your desk or slip into your bag for on-the-go organization. Its thoughtful design, premium feel, and sustainability make it more than just a diary?it?s an essential tool for maintaining productivity and style throughout the year._x000D_\n_x000D_\n</div>_x000D_\n</div>_x000D_\n</div>_x000D_\n</div>_x000D_\n<div class="about">_x000D_\n<div id="special_features" class="about__accordion-item"><button class="about__accordion-toggle focus-inset button--unstyled" aria-label="Special Features" aria-controls="special_features-content"><span class="about__accordion-title">Special Features</span></button></div>_x000D_\n</div> | AN24: =IFERROR(_xlfn.LET(_xlpm.v,INDEX('product-export-27-8-2026'!$A:$AJ,MATCH($A24,'product-export-27-8-2026'!$A:$A,0),MATCH(AN$1,'product-export-27-8-2026'!$1:$1,0)),IF(_xlpm.v="","",_xlpm.v)),"") | AO24: =IFERROR(_xlfn.LET(_xlpm.v,INDEX('product-export-27-8-2026'!$A:$AJ,MATCH($A24,'product-export-27-8-2026'!$A:$A,0),MATCH(AO$1,'product-export-27-8-2026'!$1:$1,0)),IF(_xlpm.v="","",_xlpm.v)),"") | AP24: =IFERROR(_xlfn.LET(_xlpm.v,INDEX('product-export-27-8-2026'!$A:$AJ,MATCH($A24,'product-export-27-8-2026'!$A:$A,0),MATCH(AP$1,'product-export-27-8-2026'!$1:$1,0)),IF(_xlpm.v="","",_xlpm.v)),"") | AQ24: =IFERROR(_xlfn.LET(_xlpm.v,INDEX('product-export-27-8-2026'!$A:$AJ,MATCH($A24,'product-export-27-8-2026'!$A:$A,0),MATCH(AQ$1,'product-export-27-8-2026'!$1:$1,0)),IF(_xlpm.v="","",_xlpm.v)),"") | AR24: =IFERROR(_xlfn.LET(_xlpm.v,INDEX('product-export-27-8-2026'!$A:$AJ,MATCH($A24,'product-export-27-8-2026'!$A:$A,0),MATCH(AR$1,'product-export-27-8-2026'!$1:$1,0)),IF(_xlpm.v="","",_xlpm.v)),"") -> Diaries > A5 Diary, Diaries, Dorchester Collection, Diaries > A5 Diary > DPP | AS24: =IFERROR(_xlfn.LET(_xlpm.v,INDEX('product-export-27-8-2026'!$A:$AJ,MATCH($A24,'product-export-27-8-2026'!$A:$A,0),MATCH(AS$1,'product-export-27-8-2026'!$1:$1,0)),IF(_xlpm.v="","",_xlpm.v)),"") -> Dorchester-NewHide-A5-Desk-Diary-Day-Per-Page
A25: 847 | B25: Dorchester A5 Desk Diary, Day Per Page, Blue | C25: Diary | D25: NF-BL-U-071 | E25: NF-BL-U-071 | F25: NF71U | G25: A5 | H25: Blue | I25: Day Per Page | J25: White | K25: 22mm x 22mm | L25: 0.48 | M25: 17.99 | N25: 1:16.98;10:16.23;25:12.35;50:9.38;100:8.62;250:7.78;500:6.70;750:6.33;1000:5.76; | O25: =IFERROR(VALUE(_xlfn.TEXTBEFORE(_xlfn.TEXTAFTER(";"&$N25,";"&SUBSTITUTE(O$1,"Qty ","")&":"),";")),"") -> 16.98 | P25: =IFERROR(VALUE(_xlfn.TEXTBEFORE(_xlfn.TEXTAFTER(";"&$N25,";"&SUBSTITUTE(P$1,"Qty ","")&":"),";")),"") -> 16.23 | Q25: =IFERROR(VALUE(_xlfn.TEXTBEFORE(_xlfn.TEXTAFTER(";"&$N25,";"&SUBSTITUTE(Q$1,"Qty ","")&":"),";")),"") -> 12.35 | R25: =IFERROR(VALUE(_xlfn.TEXTBEFORE(_xlfn.TEXTAFTER(";"&$N25,";"&SUBSTITUTE(R$1,"Qty ","")&":"),";")),"") -> 9.38 | S25: =IFERROR(VALUE(_xlfn.TEXTBEFORE(_xlfn.TEXTAFTER(";"&$N25,";"&SUBSTITUTE(S$1,"Qty ","")&":"),";")),"") -> 8.62 | T25: =IFERROR(VALUE(_xlfn.TEXTBEFORE(_xlfn.TEXTAFTER(";"&$N25,";"&SUBSTITUTE(T$1,"Qty ","")&":"),";")),"") -> 7.78 | U25: =IFERROR(VALUE(_xlfn.TEXTBEFORE(_xlfn.TEXTAFTER(";"&$N25,";"&SUBSTITUTE(U$1,"Qty ","")&":"),";")),"") -> 6.7 | V25: =IFERROR(VALUE(_xlfn.TEXTBEFORE(_xlfn.TEXTAFTER(";"&$N25,";"&SUBSTITUTE(V$1,"Qty ","")&":"),";")),"") -> 6.33 | W25: =IFERROR(VALUE(_xlfn.TEXTBEFORE(_xlfn.TEXTAFTER(";"&$N25,";"&SUBSTITUTE(W$1,"Qty ","")&":"),";")),"") -> 5.76 | X25: {=IF(Y25="","",_xlfn.TEXTJOIN(";",TRUE,SUBSTITUTE($Y$1:$AG$1,"Qty ","")&":"&TEXT(Y25:AG25,"0.00"))&";")} -> 1:22.20;10:20.63;25:15.92;50:12.35;100:11.35;250:10.16;500:9.07;750:8.64;1000:8.01; | Y25: ='Blocking Prices'!$C$15+O25 -> 22.2 | Z25: ='Blocking Prices'!$D$15+P25 -> 20.63 | AA25: ='Blocking Prices'!$E$15+Q25 -> 15.92 | AB25: ='Blocking Prices'!$F$15+R25 -> 12.35 | AC25: ='Blocking Prices'!$G$15+S25 -> 11.35 | AD25: ='Blocking Prices'!$H$15+T25 -> 10.16 | AE25: ='Blocking Prices'!$I$15+U25 -> 9.07 | AF25: ='Blocking Prices'!$J$15+V25 -> 8.64 | AG25: ='Blocking Prices'!$K$15+W25 -> 8.01 | AL25: Plan your 2026 in detail with the Dorchester newhide A5 Desk Diary? Self?colour perimeter cotton stitched flexible cover, FSC-certified recycled white paper, and a Day per Page layout. Elegant, sustainable, and practical. | AM25: <div class="about">_x000D_\n<div class="about__accordion-item">_x000D_\n<div class="about__accordion-description richtext__content">_x000D_\n<div class="metafield-rich_text_field">_x000D_\n_x000D_\nIntroducing the Dorchester Newhide A5 Desk Diary ? White Paper ? Day per Page, the perfect planning solution for those who need detailed, day-by-day organization in 2025. Crafted from the same high-quality, vegan leather durable as the rest of our Dorchester range, this diary has been designed for maximum comfort and practicality. Its soft, lightweight, and flexible cover combines luxury with functionality, ensuring it holds up to daily use while feeling great in hand._x000D_\n_x000D_\nThe diary is meticulously finished with coordinated perimeter stitching, giving it a refined and polished appearance. Inside, you?ll find FSC-certified recycled white paper, offering an eco-conscious choice for professionals and planners alike. The Day per Page layout provides ample space for detailed scheduling, note-taking, or task tracking, allowing you to manage each day with precision._x000D_\n_x000D_\nIdeal for busy professionals, students, or anyone who values structured, daily planning, this A5 desk diary is compact enough to sit neatly on your desk or slip into your bag for on-the-go organization. Its thoughtful design, premium feel, and sustainability make it more than just a diary?it?s an essential tool for maintaining productivity and style throughout the year._x000D_\n_x000D_\n</div>_x000D_\n</div>_x000D_\n</div>_x000D_\n</div>_x000D_\n<div class="about">_x000D_\n<div id="special_features" class="about__accordion-item"></div>_x000D_\n</div> | AN25: =IFERROR(_xlfn.LET(_xlpm.v,INDEX('product-export-27-8-2026'!$A:$AJ,MATCH($A25,'product-export-27-8-2026'!$A:$A,0),MATCH(AN$1,'product-export-27-8-2026'!$1:$1,0)),IF(_xlpm.v="","",_xlpm.v)),"") | AO25: =IFERROR(_xlfn.LET(_xlpm.v,INDEX('product-export-27-8-2026'!$A:$AJ,MATCH($A25,'product-export-27-8-2026'!$A:$A,0),MATCH(AO$1,'product-export-27-8-2026'!$1:$1,0)),IF(_xlpm.v="","",_xlpm.v)),"") | AP25: =IFERROR(_xlfn.LET(_xlpm.v,INDEX('product-export-27-8-2026'!$A:$AJ,MATCH($A25,'product-export-27-8-2026'!$A:$A,0),MATCH(AP$1,'product-export-27-8-2026'!$1:$1,0)),IF(_xlpm.v="","",_xlpm.v)),"") | AQ25: =IFERROR(_xlfn.LET(_xlpm.v,INDEX('product-export-27-8-2026'!$A:$AJ,MATCH($A25,'product-export-27-8-2026'!$A:$A,0),MATCH(AQ$1,'product-export-27-8-2026'!$1:$1,0)),IF(_xlpm.v="","",_xlpm.v)),"") | AR25: =IFERROR(_xlfn.LET(_xlpm.v,INDEX('product-export-27-8-2026'!$A:$AJ,MATCH($A25,'product-export-27-8-2026'!$A:$A,0),MATCH(AR$1,'product-export-27-8-2026'!$1:$1,0)),IF(_xlpm.v="","",_xlpm.v)),"") -> Diaries > A5 Diary, Diaries, Dorchester Collection, Diaries > A5 Diary > DPP | AS25: =IFERROR(_xlfn.LET(_xlpm.v,INDEX('product-export-27-8-2026'!$A:$AJ,MATCH($A25,'product-export-27-8-2026'!$A:$A,0),MATCH(AS$1,'product-export-27-8-2026'!$1:$1,0)),IF(_xlpm.v="","",_xlpm.v)),"") -> Dorchester-NewHide-A5-Desk-Diary-Day-Per-Page
A26: 849 | B26: Dorchester A5 Desk Diary, Day Per Page, Green | C26: Diary | D26: NF-GN-U-071 | E26: NF-GN-U-071 | F26: NF71U | G26: A5 | H26: Green | I26: Day Per Page | J26: White | K26: 22mm x 22mm | L26: 0.48 | M26: 17.99 | N26: 1:16.98;10:16.23;25:12.35;50:9.38;100:8.62;250:7.78;500:6.70;750:6.33;1000:5.76; | O26: =IFERROR(VALUE(_xlfn.TEXTBEFORE(_xlfn.TEXTAFTER(";"&$N26,";"&SUBSTITUTE(O$1,"Qty ","")&":"),";")),"") -> 16.98 | P26: =IFERROR(VALUE(_xlfn.TEXTBEFORE(_xlfn.TEXTAFTER(";"&$N26,";"&SUBSTITUTE(P$1,"Qty ","")&":"),";")),"") -> 16.23 | Q26: =IFERROR(VALUE(_xlfn.TEXTBEFORE(_xlfn.TEXTAFTER(";"&$N26,";"&SUBSTITUTE(Q$1,"Qty ","")&":"),";")),"") -> 12.35 | R26: =IFERROR(VALUE(_xlfn.TEXTBEFORE(_xlfn.TEXTAFTER(";"&$N26,";"&SUBSTITUTE(R$1,"Qty ","")&":"),";")),"") -> 9.38 | S26: =IFERROR(VALUE(_xlfn.TEXTBEFORE(_xlfn.TEXTAFTER(";"&$N26,";"&SUBSTITUTE(S$1,"Qty ","")&":"),";")),"") -> 8.62 | T26: =IFERROR(VALUE(_xlfn.TEXTBEFORE(_xlfn.TEXTAFTER(";"&$N26,";"&SUBSTITUTE(T$1,"Qty ","")&":"),";")),"") -> 7.78 | U26: =IFERROR(VALUE(_xlfn.TEXTBEFORE(_xlfn.TEXTAFTER(";"&$N26,";"&SUBSTITUTE(U$1,"Qty ","")&":"),";")),"") -> 6.7 | V26: =IFERROR(VALUE(_xlfn.TEXTBEFORE(_xlfn.TEXTAFTER(";"&$N26,";"&SUBSTITUTE(V$1,"Qty ","")&":"),";")),"") -> 6.33 | W26: =IFERROR(VALUE(_xlfn.TEXTBEFORE(_xlfn.TEXTAFTER(";"&$N26,";"&SUBSTITUTE(W$1,"Qty ","")&":"),";")),"") -> 5.76 | X26: {=IF(Y26="","",_xlfn.TEXTJOIN(";",TRUE,SUBSTITUTE($Y$1:$AG$1,"Qty ","")&":"&TEXT(Y26:AG26,"0.00"))&";")} -> 1:22.20;10:20.63;25:15.92;50:12.35;100:11.35;250:10.16;500:9.07;750:8.64;1000:8.01; | Y26: ='Blocking Prices'!$C$15+O26 -> 22.2 | Z26: ='Blocking Prices'!$D$15+P26 -> 20.63 | AA26: ='Blocking Prices'!$E$15+Q26 -> 15.92 | AB26: ='Blocking Prices'!$F$15+R26 -> 12.35 | AC26: ='Blocking Prices'!$G$15+S26 -> 11.35 | AD26: ='Blocking Prices'!$H$15+T26 -> 10.16 | AE26: ='Blocking Prices'!$I$15+U26 -> 9.07 | AF26: ='Blocking Prices'!$J$15+V26 -> 8.64 | AG26: ='Blocking Prices'!$K$15+W26 -> 8.01 | AL26: Plan your 2026 in detail with the Dorchester newhide A5 Desk Diary? Self?colour perimeter cotton stitched flexible cover, FSC-certified recycled white paper, and a Day per Page layout. Elegant, sustainable, and practical._x000D_\n_x000D_\n&nbsp; | AM26: <div class="about">_x000D_\n<div class="about__accordion-item">_x000D_\n<div class="about__accordion-description richtext__content">_x000D_\n<div class="metafield-rich_text_field">_x000D_\n_x000D_\nIntroducing the Dorchester Newhide A5 Desk Diary ? White Paper ? Day per Page, the perfect planning solution for those who need detailed, day-by-day organization in 2025. Crafted from the same high-quality, vegan leather durable as the rest of our Dorchester range, this diary has been designed for maximum comfort and practicality. Its soft, lightweight, and flexible cover combines luxury with functionality, ensuring it holds up to daily use while feeling great in hand._x000D_\n_x000D_\nThe diary is meticulously finished with coordinated perimeter stitching, giving it a refined and polished appearance. Inside, you?ll find FSC-certified recycled white paper, offering an eco-conscious choice for professionals and planners alike. The Day per Page layout provides ample space for detailed scheduling, note-taking, or task tracking, allowing you to manage each day with precision._x000D_\n_x000D_\nIdeal for busy professionals, students, or anyone who values structured, daily planning, this A5 desk diary is compact enough to sit neatly on your desk or slip into your bag for on-the-go organization. Its thoughtful design, premium feel, and sustainability make it more than just a diary?it?s an essential tool for maintaining productivity and style throughout the year._x000D_\n_x000D_\n</div>_x000D_\n</div>_x000D_\n</div>_x000D_\n</div>_x000D_\n<div class="about">_x000D_\n<div id="special_features" class="about__accordion-item"></div>_x000D_\n</div> | AN26: =IFERROR(_xlfn.LET(_xlpm.v,INDEX('product-export-27-8-2026'!$A:$AJ,MATCH($A26,'product-export-27-8-2026'!$A:$A,0),MATCH(AN$1,'product-export-27-8-2026'!$1:$1,0)),IF(_xlpm.v="","",_xlpm.v)),"") | AO26: =IFERROR(_xlfn.LET(_xlpm.v,INDEX('product-export-27-8-2026'!$A:$AJ,MATCH($A26,'product-export-27-8-2026'!$A:$A,0),MATCH(AO$1,'product-export-27-8-2026'!$1:$1,0)),IF(_xlpm.v="","",_xlpm.v)),"") | AP26: =IFERROR(_xlfn.LET(_xlpm.v,INDEX('product-export-27-8-2026'!$A:$AJ,MATCH($A26,'product-export-27-8-2026'!$A:$A,0),MATCH(AP$1,'product-export-27-8-2026'!$1:$1,0)),IF(_xlpm.v="","",_xlpm.v)),"") | AQ26: =IFERROR(_xlfn.LET(_xlpm.v,INDEX('product-export-27-8-2026'!$A:$AJ,MATCH($A26,'product-export-27-8-2026'!$A:$A,0),MATCH(AQ$1,'product-export-27-8-2026'!$1:$1,0)),IF(_xlpm.v="","",_xlpm.v)),"") | AR26: =IFERROR(_xlfn.LET(_xlpm.v,INDEX('product-export-27-8-2026'!$A:$AJ,MATCH($A26,'product-export-27-8-2026'!$A:$A,0),MATCH(AR$1,'product-export-27-8-2026'!$1:$1,0)),IF(_xlpm.v="","",_xlpm.v)),"") -> Diaries > A5 Diary, Diaries, Dorchester Collection, Diaries > A5 Diary > DPP | AS26: =IFERROR(_xlfn.LET(_xlpm.v,INDEX('product-export-27-8-2026'!$A:$AJ,MATCH($A26,'product-export-27-8-2026'!$A:$A,0),MATCH(AS$1,'product-export-27-8-2026'!$1:$1,0)),IF(_xlpm.v="","",_xlpm.v)),"") -> Dorchester-NewHide-A5-Desk-Diary-Day-Per-Page
A27: 851 | B27: Dorchester A5 Desk Diary, Day Per Page, Grey | C27: Diary | D27: NF-GY-U-071 | E27: NF-GY-U-071 | F27: NF71U | G27: A5 | H27: Grey | I27: Day Per Page | J27: White | K27: 22mm x 22mm | L27: 0.48 | M27: 17.99 | N27: 1:16.98;10:16.23;25:12.35;50:9.38;100:8.62;250:7.78;500:6.70;750:6.33;1000:5.76; | O27: =IFERROR(VALUE(_xlfn.TEXTBEFORE(_xlfn.TEXTAFTER(";"&$N27,";"&SUBSTITUTE(O$1,"Qty ","")&":"),";")),"") -> 16.98 | P27: =IFERROR(VALUE(_xlfn.TEXTBEFORE(_xlfn.TEXTAFTER(";"&$N27,";"&SUBSTITUTE(P$1,"Qty ","")&":"),";")),"") -> 16.23 | Q27: =IFERROR(VALUE(_xlfn.TEXTBEFORE(_xlfn.TEXTAFTER(";"&$N27,";"&SUBSTITUTE(Q$1,"Qty ","")&":"),";")),"") -> 12.35 | R27: =IFERROR(VALUE(_xlfn.TEXTBEFORE(_xlfn.TEXTAFTER(";"&$N27,";"&SUBSTITUTE(R$1,"Qty ","")&":"),";")),"") -> 9.38 | S27: =IFERROR(VALUE(_xlfn.TEXTBEFORE(_xlfn.TEXTAFTER(";"&$N27,";"&SUBSTITUTE(S$1,"Qty ","")&":"),";")),"") -> 8.62 | T27: =IFERROR(VALUE(_xlfn.TEXTBEFORE(_xlfn.TEXTAFTER(";"&$N27,";"&SUBSTITUTE(T$1,"Qty ","")&":"),";")),"") -> 7.78 | U27: =IFERROR(VALUE(_xlfn.TEXTBEFORE(_xlfn.TEXTAFTER(";"&$N27,";"&SUBSTITUTE(U$1,"Qty ","")&":"),";")),"") -> 6.7 | V27: =IFERROR(VALUE(_xlfn.TEXTBEFORE(_xlfn.TEXTAFTER(";"&$N27,";"&SUBSTITUTE(V$1,"Qty ","")&":"),";")),"") -> 6.33 | W27: =IFERROR(VALUE(_xlfn.TEXTBEFORE(_xlfn.TEXTAFTER(";"&$N27,";"&SUBSTITUTE(W$1,"Qty ","")&":"),";")),"") -> 5.76 | X27: {=IF(Y27="","",_xlfn.TEXTJOIN(";",TRUE,SUBSTITUTE($Y$1:$AG$1,"Qty ","")&":"&TEXT(Y27:AG27,"0.00"))&";")} -> 1:22.20;10:20.63;25:15.92;50:12.35;100:11.35;250:10.16;500:9.07;750:8.64;1000:8.01; | Y27: ='Blocking Prices'!$C$15+O27 -> 22.2 | Z27: ='Blocking Prices'!$D$15+P27 -> 20.63 | AA27: ='Blocking Prices'!$E$15+Q27 -> 15.92 | AB27: ='Blocking Prices'!$F$15+R27 -> 12.35 | AC27: ='Blocking Prices'!$G$15+S27 -> 11.35 | AD27: ='Blocking Prices'!$H$15+T27 -> 10.16 | AE27: ='Blocking Prices'!$I$15+U27 -> 9.07 | AF27: ='Blocking Prices'!$J$15+V27 -> 8.64 | AG27: ='Blocking Prices'!$K$15+W27 -> 8.01 | AL27: Plan your 2026 in detail with the Dorchester newhide A5 Desk Diary? Self?colour perimeter cotton stitched flexible cover, FSC-certified recycled white paper, and a Day per Page layout. Elegant, sustainable, and practical._x000D_\n_x000D_\n&nbsp; | AM27: <div class="about">_x000D_\n<div class="about__accordion-item">_x000D_\n<div class="about__accordion-description richtext__content">_x000D_\n<div class="metafield-rich_text_field">_x000D_\n_x000D_\nIntroducing the Dorchester Newhide A5 Desk Diary ? White Paper ? Day per Page, the perfect planning solution for those who need detailed, day-by-day organization in 2025. Crafted from the same high-quality, vegan leather durable as the rest of our Dorchester range, this diary has been designed for maximum comfort and practicality. Its soft, lightweight, and flexible cover combines luxury with functionality, ensuring it holds up to daily use while feeling great in hand._x000D_\n_x000D_\nThe diary is meticulously finished with coordinated perimeter stitching, giving it a refined and polished appearance. Inside, you?ll find FSC-certified recycled white paper, offering an eco-conscious choice for professionals and planners alike. The Day per Page layout provides ample space for detailed scheduling, note-taking, or task tracking, allowing you to manage each day with precision._x000D_\n_x000D_\nIdeal for busy professionals, students, or anyone who values structured, daily planning, this A5 desk diary is compact enough to sit neatly on your desk or slip into your bag for on-the-go organization. Its thoughtful design, premium feel, and sustainability make it more than just a diary?it?s an essential tool for maintaining productivity and style throughout the year._x000D_\n_x000D_\n</div>_x000D_\n</div>_x000D_\n</div>_x000D_\n</div>_x000D_\n<div class="about">_x000D_\n<div id="special_features" class="about__accordion-item"><button class="about__accordion-toggle focus-inset button--unstyled" aria-label="Special Features" aria-controls="special_features-content"><span class="about__accordion-title">Special Features</span></button></div>_x000D_\n</div> | AN27: =IFERROR(_xlfn.LET(_xlpm.v,INDEX('product-export-27-8-2026'!$A:$AJ,MATCH($A27,'product-export-27-8-2026'!$A:$A,0),MATCH(AN$1,'product-export-27-8-2026'!$1:$1,0)),IF(_xlpm.v="","",_xlpm.v)),"") | AO27: =IFERROR(_xlfn.LET(_xlpm.v,INDEX('product-export-27-8-2026'!$A:$AJ,MATCH($A27,'product-export-27-8-2026'!$A:$A,0),MATCH(AO$1,'product-export-27-8-2026'!$1:$1,0)),IF(_xlpm.v="","",_xlpm.v)),"") | AP27: =IFERROR(_xlfn.LET(_xlpm.v,INDEX('product-export-27-8-2026'!$A:$AJ,MATCH($A27,'product-export-27-8-2026'!$A:$A,0),MATCH(AP$1,'product-export-27-8-2026'!$1:$1,0)),IF(_xlpm.v="","",_xlpm.v)),"") | AQ27: =IFERROR(_xlfn.LET(_xlpm.v,INDEX('product-export-27-8-2026'!$A:$AJ,MATCH($A27,'product-export-27-8-2026'!$A:$A,0),MATCH(AQ$1,'product-export-27-8-2026'!$1:$1,0)),IF(_xlpm.v="","",_xlpm.v)),"") | AR27: =IFERROR(_xlfn.LET(_xlpm.v,INDEX('product-export-27-8-2026'!$A:$AJ,MATCH($A27,'product-export-27-8-2026'!$A:$A,0),MATCH(AR$1,'product-export-27-8-2026'!$1:$1,0)),IF(_xlpm.v="","",_xlpm.v)),"") -> Diaries > A5 Diary, Diaries, Dorchester Collection, Diaries > A5 Diary > DPP | AS27: =IFERROR(_xlfn.LET(_xlpm.v,INDEX('product-export-27-8-2026'!$A:$AJ,MATCH($A27,'product-export-27-8-2026'!$A:$A,0),MATCH(AS$1,'product-export-27-8-2026'!$1:$1,0)),IF(_xlpm.v="","",_xlpm.v)),"") -> Dorchester-NewHide-A5-Desk-Diary-Day-Per-Page
A28: 853 | B28: Dorchester A5 Desk Diary, Day Per Page, Red | C28: Diary | D28: NF-RD-U-071 | E28: NF-RD-U-071 | F28: NF71U | G28: A5 | H28: Red | I28: Day Per Page | J28: White | K28: 22mm x 22mm | L28: 0.48 | M28: 17.99 | N28: 1:16.98;10:16.23;25:12.35;50:9.38;100:8.62;250:7.78;500:6.70;750:6.33;1000:5.76; | O28: =IFERROR(VALUE(_xlfn.TEXTBEFORE(_xlfn.TEXTAFTER(";"&$N28,";"&SUBSTITUTE(O$1,"Qty ","")&":"),";")),"") -> 16.98 | P28: =IFERROR(VALUE(_xlfn.TEXTBEFORE(_xlfn.TEXTAFTER(";"&$N28,";"&SUBSTITUTE(P$1,"Qty ","")&":"),";")),"") -> 16.23 | Q28: =IFERROR(VALUE(_xlfn.TEXTBEFORE(_xlfn.TEXTAFTER(";"&$N28,";"&SUBSTITUTE(Q$1,"Qty ","")&":"),";")),"") -> 12.35 | R28: =IFERROR(VALUE(_xlfn.TEXTBEFORE(_xlfn.TEXTAFTER(";"&$N28,";"&SUBSTITUTE(R$1,"Qty ","")&":"),";")),"") -> 9.38 | S28: =IFERROR(VALUE(_xlfn.TEXTBEFORE(_xlfn.TEXTAFTER(";"&$N28,";"&SUBSTITUTE(S$1,"Qty ","")&":"),";")),"") -> 8.62 | T28: =IFERROR(VALUE(_xlfn.TEXTBEFORE(_xlfn.TEXTAFTER(";"&$N28,";"&SUBSTITUTE(T$1,"Qty ","")&":"),";")),"") -> 7.78 | U28: =IFERROR(VALUE(_xlfn.TEXTBEFORE(_xlfn.TEXTAFTER(";"&$N28,";"&SUBSTITUTE(U$1,"Qty ","")&":"),";")),"") -> 6.7 | V28: =IFERROR(VALUE(_xlfn.TEXTBEFORE(_xlfn.TEXTAFTER(";"&$N28,";"&SUBSTITUTE(V$1,"Qty ","")&":"),";")),"") -> 6.33 | W28: =IFERROR(VALUE(_xlfn.TEXTBEFORE(_xlfn.TEXTAFTER(";"&$N28,";"&SUBSTITUTE(W$1,"Qty ","")&":"),";")),"") -> 5.76 | X28: {=IF(Y28="","",_xlfn.TEXTJOIN(";",TRUE,SUBSTITUTE($Y$1:$AG$1,"Qty ","")&":"&TEXT(Y28:AG28,"0.00"))&";")} -> 1:22.20;10:20.63;25:15.92;50:12.35;100:11.35;250:10.16;500:9.07;750:8.64;1000:8.01; | Y28: ='Blocking Prices'!$C$15+O28 -> 22.2 | Z28: ='Blocking Prices'!$D$15+P28 -> 20.63 | AA28: ='Blocking Prices'!$E$15+Q28 -> 15.92 | AB28: ='Blocking Prices'!$F$15+R28 -> 12.35 | AC28: ='Blocking Prices'!$G$15+S28 -> 11.35 | AD28: ='Blocking Prices'!$H$15+T28 -> 10.16 | AE28: ='Blocking Prices'!$I$15+U28 -> 9.07 | AF28: ='Blocking Prices'!$J$15+V28 -> 8.64 | AG28: ='Blocking Prices'!$K$15+W28 -> 8.01 | AL28: Plan your 2026 in detail with the Dorchester newhide A5 Desk Diary? Self?colour perimeter cotton stitched flexible cover, FSC-certified recycled white paper, and a Day per Page layout. Elegant, sustainable, and practical._x000D_\n_x000D_\n&nbsp; | AM28: <div class="about">_x000D_\n<div class="about__accordion-item">_x000D_\n<div class="about__accordion-description richtext__content">_x000D_\n<div class="metafield-rich_text_field">_x000D_\n_x000D_\nIntroducing the Dorchester Newhide A5 Desk Diary ? White Paper ? Day per Page, the perfect planning solution for those who need detailed, day-by-day organization in 2025. Crafted from the same high-quality, vegan leather durable as the rest of our Dorchester range, this diary has been designed for maximum comfort and practicality. Its soft, lightweight, and flexible cover combines luxury with functionality, ensuring it holds up to daily use while feeling great in hand._x000D_\n_x000D_\nThe diary is meticulously finished with coordinated perimeter stitching, giving it a refined and polished appearance. Inside, you?ll find FSC-certified recycled white paper, offering an eco-conscious choice for professionals and planners alike. The Day per Page layout provides ample space for detailed scheduling, note-taking, or task tracking, allowing you to manage each day with precision._x000D_\n_x000D_\nIdeal for busy professionals, students, or anyone who values structured, daily planning, this A5 desk diary is compact enough to sit neatly on your desk or slip into your bag for on-the-go organization. Its thoughtful design, premium feel, and sustainability make it more than just a diary?it?s an essential tool for maintaining productivity and style throughout the year._x000D_\n_x000D_\n</div>_x000D_\n</div>_x000D_\n</div>_x000D_\n</div>_x000D_\n<div class="about">_x000D_\n<div id="special_features" class="about__accordion-item"></div>_x000D_\n</div> | AN28: =IFERROR(_xlfn.LET(_xlpm.v,INDEX('product-export-27-8-2026'!$A:$AJ,MATCH($A28,'product-export-27-8-2026'!$A:$A,0),MATCH(AN$1,'product-export-27-8-2026'!$1:$1,0)),IF(_xlpm.v="","",_xlpm.v)),"") | AO28: =IFERROR(_xlfn.LET(_xlpm.v,INDEX('product-export-27-8-2026'!$A:$AJ,MATCH($A28,'product-export-27-8-2026'!$A:$A,0),MATCH(AO$1,'product-export-27-8-2026'!$1:$1,0)),IF(_xlpm.v="","",_xlpm.v)),"") | AP28: =IFERROR(_xlfn.LET(_xlpm.v,INDEX('product-export-27-8-2026'!$A:$AJ,MATCH($A28,'product-export-27-8-2026'!$A:$A,0),MATCH(AP$1,'product-export-27-8-2026'!$1:$1,0)),IF(_xlpm.v="","",_xlpm.v)),"") | AQ28: =IFERROR(_xlfn.LET(_xlpm.v,INDEX('product-export-27-8-2026'!$A:$AJ,MATCH($A28,'product-export-27-8-2026'!$A:$A,0),MATCH(AQ$1,'product-export-27-8-2026'!$1:$1,0)),IF(_xlpm.v="","",_xlpm.v)),"") | AR28: =IFERROR(_xlfn.LET(_xlpm.v,INDEX('product-export-27-8-2026'!$A:$AJ,MATCH($A28,'product-export-27-8-2026'!$A:$A,0),MATCH(AR$1,'product-export-27-8-2026'!$1:$1,0)),IF(_xlpm.v="","",_xlpm.v)),"") -> Diaries > A5 Diary, Diaries, Dorchester Collection, Diaries > A5 Diary > DPP | AS28: =IFERROR(_xlfn.LET(_xlpm.v,INDEX('product-export-27-8-2026'!$A:$AJ,MATCH($A28,'product-export-27-8-2026'!$A:$A,0),MATCH(AS$1,'product-export-27-8-2026'!$1:$1,0)),IF(_xlpm.v="","",_xlpm.v)),"") -> Dorchester-NewHide-A5-Desk-Diary-Day-Per-Page
A29: 855 | B29: Dorchester A5 Desk Diary, Day Per Page, Tan | C29: Diary | D29: NF-TN-U-071 | E29: NF-TN-U-071 | F29: NF71U | G29: A5 | H29: Tan | I29: Day Per Page | J29: White | K29: 22mm x 22mm | L29: 0.48 | M29: 17.99 | N29: 1:16.98;10:16.23;25:12.35;50:9.38;100:8.62;250:7.78;500:6.70;750:6.33;1000:5.76; | O29: =IFERROR(VALUE(_xlfn.TEXTBEFORE(_xlfn.TEXTAFTER(";"&$N29,";"&SUBSTITUTE(O$1,"Qty ","")&":"),";")),"") -> 16.98 | P29: =IFERROR(VALUE(_xlfn.TEXTBEFORE(_xlfn.TEXTAFTER(";"&$N29,";"&SUBSTITUTE(P$1,"Qty ","")&":"),";")),"") -> 16.23 | Q29: =IFERROR(VALUE(_xlfn.TEXTBEFORE(_xlfn.TEXTAFTER(";"&$N29,";"&SUBSTITUTE(Q$1,"Qty ","")&":"),";")),"") -> 12.35 | R29: =IFERROR(VALUE(_xlfn.TEXTBEFORE(_xlfn.TEXTAFTER(";"&$N29,";"&SUBSTITUTE(R$1,"Qty ","")&":"),";")),"") -> 9.38 | S29: =IFERROR(VALUE(_xlfn.TEXTBEFORE(_xlfn.TEXTAFTER(";"&$N29,";"&SUBSTITUTE(S$1,"Qty ","")&":"),";")),"") -> 8.62 | T29: =IFERROR(VALUE(_xlfn.TEXTBEFORE(_xlfn.TEXTAFTER(";"&$N29,";"&SUBSTITUTE(T$1,"Qty ","")&":"),";")),"") -> 7.78 | U29: =IFERROR(VALUE(_xlfn.TEXTBEFORE(_xlfn.TEXTAFTER(";"&$N29,";"&SUBSTITUTE(U$1,"Qty ","")&":"),";")),"") -> 6.7 | V29: =IFERROR(VALUE(_xlfn.TEXTBEFORE(_xlfn.TEXTAFTER(";"&$N29,";"&SUBSTITUTE(V$1,"Qty ","")&":"),";")),"") -> 6.33 | W29: =IFERROR(VALUE(_xlfn.TEXTBEFORE(_xlfn.TEXTAFTER(";"&$N29,";"&SUBSTITUTE(W$1,"Qty ","")&":"),";")),"") -> 5.76 | X29: {=IF(Y29="","",_xlfn.TEXTJOIN(";",TRUE,SUBSTITUTE($Y$1:$AG$1,"Qty ","")&":"&TEXT(Y29:AG29,"0.00"))&";")} -> 1:22.20;10:20.63;25:15.92;50:12.35;100:11.35;250:10.16;500:9.07;750:8.64;1000:8.01; | Y29: ='Blocking Prices'!$C$15+O29 -> 22.2 | Z29: ='Blocking Prices'!$D$15+P29 -> 20.63 | AA29: ='Blocking Prices'!$E$15+Q29 -> 15.92 | AB29: ='Blocking Prices'!$F$15+R29 -> 12.35 | AC29: ='Blocking Prices'!$G$15+S29 -> 11.35 | AD29: ='Blocking Prices'!$H$15+T29 -> 10.16 | AE29: ='Blocking Prices'!$I$15+U29 -> 9.07 | AF29: ='Blocking Prices'!$J$15+V29 -> 8.64 | AG29: ='Blocking Prices'!$K$15+W29 -> 8.01 | AL29: Plan your 2026 in detail with the Dorchester newhide A5 Desk Diary? Self?colour perimeter cotton stitched flexible cover, FSC-certified recycled white paper, and a Day per Page layout. Elegant, sustainable, and practical._x000D_\n_x000D_\n&nbsp; | AM29: <div class="about">_x000D_\n<div class="about__accordion-item">_x000D_\n<div class="about__accordion-description richtext__content">_x000D_\n<div class="metafield-rich_text_field">_x000D_\n_x000D_\nIntroducing the Dorchester Newhide A5 Desk Diary ? White Paper ? Day per Page, the perfect planning solution for those who need detailed, day-by-day organization in 2025. Crafted from the same high-quality, vegan leather durable as the rest of our Dorchester range, this diary has been designed for maximum comfort and practicality. Its soft, lightweight, and flexible cover combines luxury with functionality, ensuring it holds up to daily use while feeling great in hand._x000D_\n_x000D_\nThe diary is meticulously finished with coordinated perimeter stitching, giving it a refined and polished appearance. Inside, you?ll find FSC-certified recycled white paper, offering an eco-conscious choice for professionals and planners alike. The Day per Page layout provides ample space for detailed scheduling, note-taking, or task tracking, allowing you to manage each day with precision._x000D_\n_x000D_\nIdeal for busy professionals, students, or anyone who values structured, daily planning, this A5 desk diary is compact enough to sit neatly on your desk or slip into your bag for on-the-go organization. Its thoughtful design, premium feel, and sustainability make it more than just a diary?it?s an essential tool for maintaining productivity and style throughout the year._x000D_\n_x000D_\n</div>_x000D_\n</div>_x000D_\n</div>_x000D_\n</div> | AN29: =IFERROR(_xlfn.LET(_xlpm.v,INDEX('product-export-27-8-2026'!$A:$AJ,MATCH($A29,'product-export-27-8-2026'!$A:$A,0),MATCH(AN$1,'product-export-27-8-2026'!$1:$1,0)),IF(_xlpm.v="","",_xlpm.v)),"") | AO29: =IFERROR(_xlfn.LET(_xlpm.v,INDEX('product-export-27-8-2026'!$A:$AJ,MATCH($A29,'product-export-27-8-2026'!$A:$A,0),MATCH(AO$1,'product-export-27-8-2026'!$1:$1,0)),IF(_xlpm.v="","",_xlpm.v)),"") | AP29: =IFERROR(_xlfn.LET(_xlpm.v,INDEX('product-export-27-8-2026'!$A:$AJ,MATCH($A29,'product-export-27-8-2026'!$A:$A,0),MATCH(AP$1,'product-export-27-8-2026'!$1:$1,0)),IF(_xlpm.v="","",_xlpm.v)),"") | AQ29: =IFERROR(_xlfn.LET(_xlpm.v,INDEX('product-export-27-8-2026'!$A:$AJ,MATCH($A29,'product-export-27-8-2026'!$A:$A,0),MATCH(AQ$1,'product-export-27-8-2026'!$1:$1,0)),IF(_xlpm.v="","",_xlpm.v)),"") | AR29: =IFERROR(_xlfn.LET(_xlpm.v,INDEX('product-export-27-8-2026'!$A:$AJ,MATCH($A29,'product-export-27-8-2026'!$A:$A,0),MATCH(AR$1,'product-export-27-8-2026'!$1:$1,0)),IF(_xlpm.v="","",_xlpm.v)),"") -> Diaries > A5 Diary, Diaries, Dorchester Collection, Diaries > A5 Diary > DPP | AS29: =IFERROR(_xlfn.LET(_xlpm.v,INDEX('product-export-27-8-2026'!$A:$AJ,MATCH($A29,'product-export-27-8-2026'!$A:$A,0),MATCH(AS$1,'product-export-27-8-2026'!$1:$1,0)),IF(_xlpm.v="","",_xlpm.v)),"") -> Dorchester-NewHide-A5-Desk-Diary-Day-Per-Page
... A68: 984 | B68: Richmond A5 Desk Diary, Week to View, Red | C68: Diary | D68: FG-RD-P-073 | E68: FG-RD-P-073 | F68: FG73P | G68: A5 | H68: Red | I68: Week to View | J68: White | K68: 22mm x 22mm | L68: 0.48 | M68: 11.5 | N68: 1:12.11;10:11.63;25:5.36;50:4.25;100:3.74;250:3.47;500:3.30;750:3.27;1000:3.07; | O68: =IFERROR(VALUE(_xlfn.TEXTBEFORE(_xlfn.TEXTAFTER(";"&$N68,";"&SUBSTITUTE(O$1,"Qty ","")&":"),";")),"") -> 12.11 | P68: =IFERROR(VALUE(_xlfn.TEXTBEFORE(_xlfn.TEXTAFTER(";"&$N68,";"&SUBSTITUTE(P$1,"Qty ","")&":"),";")),"") -> 11.63 | Q68: =IFERROR(VALUE(_xlfn.TEXTBEFORE(_xlfn.TEXTAFTER(";"&$N68,";"&SUBSTITUTE(Q$1,"Qty ","")&":"),";")),"") -> 5.36 | R68: =IFERROR(VALUE(_xlfn.TEXTBEFORE(_xlfn.TEXTAFTER(";"&$N68,";"&SUBSTITUTE(R$1,"Qty ","")&":"),";")),"") -> 4.25 | S68: =IFERROR(VALUE(_xlfn.TEXTBEFORE(_xlfn.TEXTAFTER(";"&$N68,";"&SUBSTITUTE(S$1,"Qty ","")&":"),";")),"") -> 3.74 | T68: =IFERROR(VALUE(_xlfn.TEXTBEFORE(_xlfn.TEXTAFTER(";"&$N68,";"&SUBSTITUTE(T$1,"Qty ","")&":"),";")),"") -> 3.47 | U68: =IFERROR(VALUE(_xlfn.TEXTBEFORE(_xlfn.TEXTAFTER(";"&$N68,";"&SUBSTITUTE(U$1,"Qty ","")&":"),";")),"") -> 3.3 | V68: =IFERROR(VALUE(_xlfn.TEXTBEFORE(_xlfn.TEXTAFTER(";"&$N68,";"&SUBSTITUTE(V$1,"Qty ","")&":"),";")),"") -> 3.27 | W68: =IFERROR(VALUE(_xlfn.TEXTBEFORE(_xlfn.TEXTAFTER(";"&$N68,";"&SUBSTITUTE(W$1,"Qty ","")&":"),";")),"") -> 3.07 | X68: {=IF(Y68="","",_xlfn.TEXTJOIN(";",TRUE,SUBSTITUTE($Y$1:$AG$1,"Qty ","")&":"&TEXT(Y68:AG68,"0.00"))&";")} -> 1:17.33;10:16.03;25:8.93;50:7.22;100:6.47;250:5.85;500:5.67;750:5.58;1000:5.32; | Y68: ='Blocking Prices'!$C$15+O68 -> 17.33 | Z68: ='Blocking Prices'!$D$15+P68 -> 16.03 | AA68: ='Blocking Prices'!$E$15+Q68 -> 8.93 | AB68: ='Blocking Prices'!$F$15+R68 -> 7.22 | AC68: ='Blocking Prices'!$G$15+S68 -> 6.47 | AD68: ='Blocking Prices'!$H$15+T68 -> 5.85 | AE68: ='Blocking Prices'!$I$15+U68 -> 5.67 | AF68: ='Blocking Prices'!$J$15+V68 -> 5.58 | AG68: ='Blocking Prices'!$K$15+W68 -> 5.32 | AL68: Stay on top of your schedule with the Richmond FineGrain A5 Diary - Week to View layout. Featuring a luxurious leather-like cover, white FSC recycled paper, and a convenient ribbon marker, it?s a sleek essential for weekly planning. | AM68: The Richmond Faux Leather A5 Diary - White Paper - Week to View is crafted to meet the needs of those who value both elegance and streamlined organization. Featuring our Richmond Faux Leather cover material, this diary has a refined, leather-like texture that offers a classic look and feel. Perfect for professionals and students alike, the Richmond Faux Leather A5 Diary combines a timeless aesthetic with everyday durability, making it an ideal companion for any schedule._x000D_\n_x000D_\nEach week is displayed across two pages, allowing you to see all your engagements, tasks, and notes at a glance. The diary is printed on high-quality white paper, which provides a smooth, crisp writing surface, while a real perimeter-stitched cover and sleek ribbon marker lend a touch of sophistication and practicality. With a compact A5 size, it?s easy to carry on the go, ensuring that you?re organized wherever life takes you._x000D_\n_x000D_\nWhether for personal use or corporate gifting, the Richmond Faux Leather A5 Diary brings together premium quality and classic styling, making it a beautiful yet practical choice for organized living. | AN68: =IFERROR(_xlfn.LET(_xlpm.v,INDEX('product-export-27-8-2026'!$A:$AJ,MATCH($A68,'product-export-27-8-2026'!$A:$A,0),MATCH(AN$1,'product-export-27-8-2026'!$1:$1,0)),IF(_xlpm.v="","",_xlpm.v)),"") | AO68: =IFERROR(_xlfn.LET(_xlpm.v,INDEX('product-export-27-8-2026'!$A:$AJ,MATCH($A68,'product-export-27-8-2026'!$A:$A,0),MATCH(AO$1,'product-export-27-8-2026'!$1:$1,0)),IF(_xlpm.v="","",_xlpm.v)),"") | AP68: =IFERROR(_xlfn.LET(_xlpm.v,INDEX('product-export-27-8-2026'!$A:$AJ,MATCH($A68,'product-export-27-8-2026'!$A:$A,0),MATCH(AP$1,'product-export-27-8-2026'!$1:$1,0)),IF(_xlpm.v="","",_xlpm.v)),"") | AQ68: =IFERROR(_xlfn.LET(_xlpm.v,INDEX('product-export-27-8-2026'!$A:$AJ,MATCH($A68,'product-export-27-8-2026'!$A:$A,0),MATCH(AQ$1,'product-export-27-8-2026'!$1:$1,0)),IF(_xlpm.v="","",_xlpm.v)),"") | AR68: =IFERROR(_xlfn.LET(_xlpm.v,INDEX('product-export-27-8-2026'!$A:$AJ,MATCH($A68,'product-export-27-8-2026'!$A:$A,0),MATCH(AR$1,'product-export-27-8-2026'!$1:$1,0)),IF(_xlpm.v="","",_xlpm.v)),"") -> Diaries > A5 Diary, Diaries, Foil blocked, Richmond Collection, Diaries > A5 Diary > WTV | AS68: =IFERROR(_xlfn.LET(_xlpm.v,INDEX('product-export-27-8-2026'!$A:$AJ,MATCH($A68,'product-export-27-8-2026'!$A:$A,0),MATCH(AS$1,'product-export-27-8-2026'!$1:$1,0)),IF(_xlpm.v="","",_xlpm.v)),"") -> Richmond-FineGrain-A5-Desk-Diary-Week-To-View
A69: 988 | B69: Graphic Prints A5 Diary, Day Per Page, Full Colour | C69: Diary | D69: CX-44-P-071 | E69: CX-44-P-071 | F69: CXF71 | G69: A5 | H69: Full Colour | I69: Day Per Page | J69: White | K69: 22mm x 22mm | L69: 0.48 | M69: 21.99 | N69: 1:19.98;10:19.06;25:12.74;50:9.64;100:8.36;250:7.55;500:5.68;750:5.44;1000:5.30; | O69: =IFERROR(VALUE(_xlfn.TEXTBEFORE(_xlfn.TEXTAFTER(";"&$N69,";"&SUBSTITUTE(O$1,"Qty ","")&":"),";")),"") -> 19.98 | P69: =IFERROR(VALUE(_xlfn.TEXTBEFORE(_xlfn.TEXTAFTER(";"&$N69,";"&SUBSTITUTE(P$1,"Qty ","")&":"),";")),"") -> 19.06 | Q69: =IFERROR(VALUE(_xlfn.TEXTBEFORE(_xlfn.TEXTAFTER(";"&$N69,";"&SUBSTITUTE(Q$1,"Qty ","")&":"),";")),"") -> 12.74 | R69: =IFERROR(VALUE(_xlfn.TEXTBEFORE(_xlfn.TEXTAFTER(";"&$N69,";"&SUBSTITUTE(R$1,"Qty ","")&":"),";")),"") -> 9.64 | S69: =IFERROR(VALUE(_xlfn.TEXTBEFORE(_xlfn.TEXTAFTER(";"&$N69,";"&SUBSTITUTE(S$1,"Qty ","")&":"),";")),"") -> 8.36 | T69: =IFERROR(VALUE(_xlfn.TEXTBEFORE(_xlfn.TEXTAFTER(";"&$N69,";"&SUBSTITUTE(T$1,"Qty ","")&":"),";")),"") -> 7.55 | U69: =IFERROR(VALUE(_xlfn.TEXTBEFORE(_xlfn.TEXTAFTER(";"&$N69,";"&SUBSTITUTE(U$1,"Qty ","")&":"),";")),"") -> 5.68 | V69: =IFERROR(VALUE(_xlfn.TEXTBEFORE(_xlfn.TEXTAFTER(";"&$N69,";"&SUBSTITUTE(V$1,"Qty ","")&":"),";")),"") -> 5.44 | W69: =IFERROR(VALUE(_xlfn.TEXTBEFORE(_xlfn.TEXTAFTER(";"&$N69,";"&SUBSTITUTE(W$1,"Qty ","")&":"),";")),"") -> 5.3 | AL69: Stay organized and stylish with the Graphic Prints Full Colour A5 Diary - Day per Page. Featuring a vibrant, customizable full-colour cover, white paper, and a spacious day-per-page layout, this diary is the perfect tool for detailed daily planning. | AM69: The Graphic Prints Full Colour A5 Diary - White Paper ? Day Per Page combines bold, vibrant design with practicality and sophistication. Bound in high-quality Graphic Prints material, this diary is perfect for those who want a customizable, durable, and sleek way to organize their daily schedule. The full-colour cover allows for complete personalization, making it an excellent choice for businesses or individuals looking to showcase their brand or personality._x000D_\n_x000D_\nWith a day-per-page layout, this diary provides ample space to write down daily appointments, to-do lists, notes, and reminders. Each page offers a clean, white backdrop that enhances readability and makes writing a smooth and enjoyable experience. The A5 size is perfect for those who need a bit more room for their daily planning without being overly bulky. The diary also includes a ribbon marker for easy access to the current day, as well as durable perimeter stitching, ensuring that it stands the test of time. Whether you're managing personal tasks or professional commitments, the Graphic Prints Full Colour A5 Diary ensures you do it in style and with organization. | AN69: =IFERROR(_xlfn.LET(_xlpm.v,INDEX('product-export-27-8-2026'!$A:$AJ,MATCH($A69,'product-export-27-8-2026'!$A:$A,0),MATCH(AN$1,'product-export-27-8-2026'!$1:$1,0)),IF(_xlpm.v="","",_xlpm.v)),"") | AO69: =IFERROR(_xlfn.LET(_xlpm.v,INDEX('product-export-27-8-2026'!$A:$AJ,MATCH($A69,'product-export-27-8-2026'!$A:$A,0),MATCH(AO$1,'product-export-27-8-2026'!$1:$1,0)),IF(_xlpm.v="","",_xlpm.v)),"") | AP69: =IFERROR(_xlfn.LET(_xlpm.v,INDEX('product-export-27-8-2026'!$A:$AJ,MATCH($A69,'product-export-27-8-2026'!$A:$A,0),MATCH(AP$1,'product-export-27-8-2026'!$1:$1,0)),IF(_xlpm.v="","",_xlpm.v)),"") | AQ69: =IFERROR(_xlfn.LET(_xlpm.v,INDEX('product-export-27-8-2026'!$A:$AJ,MATCH($A69,'product-export-27-8-2026'!$A:$A,0),MATCH(AQ$1,'product-export-27-8-2026'!$1:$1,0)),IF(_xlpm.v="","",_xlpm.v)),"") | AR69: =IFERROR(_xlfn.LET(_xlpm.v,INDEX('product-export-27-8-2026'!$A:$AJ,MATCH($A69,'product-export-27-8-2026'!$A:$A,0),MATCH(AR$1,'product-export-27-8-2026'!$1:$1,0)),IF(_xlpm.v="","",_xlpm.v)),"") -> Diaries > A5 Diary, Diaries, Diaries > A5 Diary > DPP, Graphic Print Collection | AS69: =IFERROR(_xlfn.LET(_xlpm.v,INDEX('product-export-27-8-2026'!$A:$AJ,MATCH($A69,'product-export-27-8-2026'!$A:$A,0),MATCH(AS$1,'product-export-27-8-2026'!$1:$1,0)),IF(_xlpm.v="","",_xlpm.v)),"") -> Graphic-Prints-A5-Diary-Week-to-View
A70: 990 | B70: Graphic Prints A5 Diary, Week to View, Full Colour | C70: Diary | D70: CX-44-P-073 | E70: CX-44-P-073 | F70: CXP73 | G70: A5 | H70: Full Colour | I70: Week to View | J70: White | K70: 22mm x 22mm | L70: 0.48 | M70: 15.5 | N70: 1:15.11;10:14.46;25:9.42;50:7.14;100:6.24;250:4.46;500:4.22;750:4.10;1000:4.00; | O70: =IFERROR(VALUE(_xlfn.TEXTBEFORE(_xlfn.TEXTAFTER(";"&$N70,";"&SUBSTITUTE(O$1,"Qty ","")&":"),";")),"") -> 15.11 | P70: =IFERROR(VALUE(_xlfn.TEXTBEFORE(_xlfn.TEXTAFTER(";"&$N70,";"&SUBSTITUTE(P$1,"Qty ","")&":"),";")),"") -> 14.46 | Q70: =IFERROR(VALUE(_xlfn.TEXTBEFORE(_xlfn.TEXTAFTER(";"&$N70,";"&SUBSTITUTE(Q$1,"Qty ","")&":"),";")),"") -> 9.42 | R70: =IFERROR(VALUE(_xlfn.TEXTBEFORE(_xlfn.TEXTAFTER(";"&$N70,";"&SUBSTITUTE(R$1,"Qty ","")&":"),";")),"") -> 7.14 | S70: =IFERROR(VALUE(_xlfn.TEXTBEFORE(_xlfn.TEXTAFTER(";"&$N70,";"&SUBSTITUTE(S$1,"Qty ","")&":"),";")),"") -> 6.24 | T70: =IFERROR(VALUE(_xlfn.TEXTBEFORE(_xlfn.TEXTAFTER(";"&$N70,";"&SUBSTITUTE(T$1,"Qty ","")&":"),";")),"") -> 4.46 | U70: =IFERROR(VALUE(_xlfn.TEXTBEFORE(_xlfn.TEXTAFTER(";"&$N70,";"&SUBSTITUTE(U$1,"Qty ","")&":"),";")),"") -> 4.22 | V70: =IFERROR(VALUE(_xlfn.TEXTBEFORE(_xlfn.TEXTAFTER(";"&$N70,";"&SUBSTITUTE(V$1,"Qty ","")&":"),";")),"") -> 4.1 | W70: =IFERROR(VALUE(_xlfn.TEXTBEFORE(_xlfn.TEXTAFTER(";"&$N70,";"&SUBSTITUTE(W$1,"Qty ","")&":"),";")),"") -> 4 | AL70: Stay organized and stylish with the Graphic Prints Full Colour A5 Diary - Day per Page. Featuring a vibrant, customizable full-colour cover, white paper, and a spacious day-per-page layout, this diary is the perfect tool for detailed daily planning. | AM70: The Graphic Prints Full Colour A5 Diary - White Paper ? Day Per Page combines bold, vibrant design with practicality and sophistication. Bound in high-quality Graphic Prints material, this diary is perfect for those who want a customizable, durable, and sleek way to organize their daily schedule. The full-colour cover allows for complete personalization, making it an excellent choice for businesses or individuals looking to showcase their brand or personality._x000D_\n_x000D_\nWith a day-per-page layout, this diary provides ample space to write down daily appointments, to-do lists, notes, and reminders. Each page offers a clean, white backdrop that enhances readability and makes writing a smooth and enjoyable experience. The A5 size is perfect for those who need a bit more room for their daily planning without being overly bulky. The diary also includes a ribbon marker for easy access to the current day, as well as durable perimeter stitching, ensuring that it stands the test of time. Whether you're managing personal tasks or professional commitments, the Graphic Prints Full Colour A5 Diary ensures you do it in style and with organization. | AN70: =IFERROR(_xlfn.LET(_xlpm.v,INDEX('product-export-27-8-2026'!$A:$AJ,MATCH($A70,'product-export-27-8-2026'!$A:$A,0),MATCH(AN$1,'product-export-27-8-2026'!$1:$1,0)),IF(_xlpm.v="","",_xlpm.v)),"") | AO70: =IFERROR(_xlfn.LET(_xlpm.v,INDEX('product-export-27-8-2026'!$A:$AJ,MATCH($A70,'product-export-27-8-2026'!$A:$A,0),MATCH(AO$1,'product-export-27-8-2026'!$1:$1,0)),IF(_xlpm.v="","",_xlpm.v)),"") | AP70: =IFERROR(_xlfn.LET(_xlpm.v,INDEX('product-export-27-8-2026'!$A:$AJ,MATCH($A70,'product-export-27-8-2026'!$A:$A,0),MATCH(AP$1,'product-export-27-8-2026'!$1:$1,0)),IF(_xlpm.v="","",_xlpm.v)),"") | AQ70: =IFERROR(_xlfn.LET(_xlpm.v,INDEX('product-export-27-8-2026'!$A:$AJ,MATCH($A70,'product-export-27-8-2026'!$A:$A,0),MATCH(AQ$1,'product-export-27-8-2026'!$1:$1,0)),IF(_xlpm.v="","",_xlpm.v)),"") | AR70: =IFERROR(_xlfn.LET(_xlpm.v,INDEX('product-export-27-8-2026'!$A:$AJ,MATCH($A70,'product-export-27-8-2026'!$A:$A,0),MATCH(AR$1,'product-export-27-8-2026'!$1:$1,0)),IF(_xlpm.v="","",_xlpm.v)),"") -> Diaries > A5 Diary, Diaries, Graphic Print Collection, Diaries > A5 Diary > WTV | AS70: =IFERROR(_xlfn.LET(_xlpm.v,INDEX('product-export-27-8-2026'!$A:$AJ,MATCH($A70,'product-export-27-8-2026'!$A:$A,0),MATCH(AS$1,'product-export-27-8-2026'!$1:$1,0)),IF(_xlpm.v="","",_xlpm.v)),"") -> Graphic-Prints-A5-Diary-Week-to-View
A71: 992 | B71: Chelsea Leather Quarto Diary, Week to View, Black | C71: Diary | D71: CL-BK-U-83 | E71: CL-BK-U-83 | F71: CL83U | G71: Quarto | H71: Black | I71: Week to View | J71: White | K71: 27mm x 27mm | L71: 0.48 | M71: 26.99 | N71: 1:24.33;10:23.21;25:19.35;50:15.29;100:13.03;250:12.21;500:11.74;750:11.14;1000:10.37; | O71: =IFERROR(VALUE(_xlfn.TEXTBEFORE(_xlfn.TEXTAFTER(";"&$N71,";"&SUBSTITUTE(O$1,"Qty ","")&":"),";")),"") -> 24.33 | P71: =IFERROR(VALUE(_xlfn.TEXTBEFORE(_xlfn.TEXTAFTER(";"&$N71,";"&SUBSTITUTE(P$1,"Qty ","")&":"),";")),"") -> 23.21 | Q71: =IFERROR(VALUE(_xlfn.TEXTBEFORE(_xlfn.TEXTAFTER(";"&$N71,";"&SUBSTITUTE(Q$1,"Qty ","")&":"),";")),"") -> 19.35 | R71: =IFERROR(VALUE(_xlfn.TEXTBEFORE(_xlfn.TEXTAFTER(";"&$N71,";"&SUBSTITUTE(R$1,"Qty ","")&":"),";")),"") -> 15.29 | S71: =IFERROR(VALUE(_xlfn.TEXTBEFORE(_xlfn.TEXTAFTER(";"&$N71,";"&SUBSTITUTE(S$1,"Qty ","")&":"),";")),"") -> 13.03 | T71: =IFERROR(VALUE(_xlfn.TEXTBEFORE(_xlfn.TEXTAFTER(";"&$N71,";"&SUBSTITUTE(T$1,"Qty ","")&":"),";")),"") -> 12.21 | U71: =IFERROR(VALUE(_xlfn.TEXTBEFORE(_xlfn.TEXTAFTER(";"&$N71,";"&SUBSTITUTE(U$1,"Qty ","")&":"),";")),"") -> 11.74 | V71: =IFERROR(VALUE(_xlfn.TEXTBEFORE(_xlfn.TEXTAFTER(";"&$N71,";"&SUBSTITUTE(V$1,"Qty ","")&":"),";")),"") -> 11.14 | W71: =IFERROR(VALUE(_xlfn.TEXTBEFORE(_xlfn.TEXTAFTER(";"&$N71,";"&SUBSTITUTE(W$1,"Qty ","")&":"),";")),"") -> 10.37 | X71: {=IF(Y71="","",_xlfn.TEXTJOIN(";",TRUE,SUBSTITUTE($Y$1:$AG$1,"Qty ","")&":"&TEXT(Y71:AG71,"0.00"))&";")} -> 1:30.45;10:28.72;25:24.24;50:19.37;100:16.75;250:15.60;500:15.01;750:14.41;1000:13.55; | Y71: ='Blocking Prices'!$C$16+O71 -> 30.45 | Z71: ='Blocking Prices'!$D$16+P71 -> 28.72 | AA71: ='Blocking Prices'!$E$16+Q71 -> 24.24 | AB71: ='Blocking Prices'!$F$16+R71 -> 19.37 | AC71: ='Blocking Prices'!$G$16+S71 -> 16.75 | AD71: ='Blocking Prices'!$H$16+T71 -> 15.6 | AE71: ='Blocking Prices'!$I$16+U71 -> 15.01 | AF71: ='Blocking Prices'!$J$16+V71 -> 14.41 | AG71: ='Blocking Prices'!$K$16+W71 -> 13.55 | AL71: <p class="p1">Chelsea Leather range, luxury soft grained real leather?week to view layout.<span class="Apple-converted-space">?</span>Smyth sewn sections for strength and durability printed on white or cream FSC paper.<span class="Apple-converted-space">?</span>Self-colour cotton perimeter stitched flexible cover, ribbon marker, general information pages, forward planners, UK and international holidays, contacts directory, notes page and full colour map section</p>_x000D_\n&nbsp; | AM71: Chelsea Leather range, luxury soft grained real leather week to view layout. Smyth sewn sections for strength and durability printed on white or cream FSC paper. Self-colour cotton perimeter stitched flexible cover, ribbon marker, general information pages, forward planners, UK and international holidays, contacts directory, notes page and full colour map section | AN71: =IFERROR(_xlfn.LET(_xlpm.v,INDEX('product-export-27-8-2026'!$A:$AJ,MATCH($A71,'product-export-27-8-2026'!$A:$A,0),MATCH(AN$1,'product-export-27-8-2026'!$1:$1,0)),IF(_xlpm.v="","",_xlpm.v)),"") | AO71: =IFERROR(_xlfn.LET(_xlpm.v,INDEX('product-export-27-8-2026'!$A:$AJ,MATCH($A71,'product-export-27-8-2026'!$A:$A,0),MATCH(AO$1,'product-export-27-8-2026'!$1:$1,0)),IF(_xlpm.v="","",_xlpm.v)),"") | AP71: =IFERROR(_xlfn.LET(_xlpm.v,INDEX('product-export-27-8-2026'!$A:$AJ,MATCH($A71,'product-export-27-8-2026'!$A:$A,0),MATCH(AP$1,'product-export-27-8-2026'!$1:$1,0)),IF(_xlpm.v="","",_xlpm.v)),"") | AQ71: =IFERROR(_xlfn.LET(_xlpm.v,INDEX('product-export-27-8-2026'!$A:$AJ,MATCH($A71,'product-export-27-8-2026'!$A:$A,0),MATCH(AQ$1,'product-export-27-8-2026'!$1:$1,0)),IF(_xlpm.v="","",_xlpm.v)),"") | AR71: =IFERROR(_xlfn.LET(_xlpm.v,INDEX('product-export-27-8-2026'!$A:$AJ,MATCH($A71,'product-export-27-8-2026'!$A:$A,0),MATCH(AR$1,'product-export-27-8-2026'!$1:$1,0)),IF(_xlpm.v="","",_xlpm.v)),"") -> Chelsea Collection, Diaries, Foil blocked, Diaries > Quarto Diary, Diaries > Quarto Diary > Quarto WTV, Diaries > Real Leather | AS71: =IFERROR(_xlfn.LET(_xlpm.v,INDEX('product-export-27-8-2026'!$A:$AJ,MATCH($A71,'product-export-27-8-2026'!$A:$A,0),MATCH(AS$1,'product-export-27-8-2026'!$1:$1,0)),IF(_xlpm.v="","",_xlpm.v)),"") -> Chelsea-Leather-Quarto-Diary-Week-To-View
A72: 995 | B72: Chelsea Leather Quarto Diary, Week to View, Blue | C72: Diary | D72: CL-BL-U-83 | E72: CL-BL-U-83 | F72: CL83U | G72: Quarto | H72: Blue | I72: Week to View | J72: White | K72: 27mm x 27mm | L72: 0.48 | M72: 26.99 | N72: 1:24.33;10:23.21;25:19.35;50:15.29;100:13.03;250:12.21;500:11.74;750:11.14;1000:10.37; | O72: =IFERROR(VALUE(_xlfn.TEXTBEFORE(_xlfn.TEXTAFTER(";"&$N72,";"&SUBSTITUTE(O$1,"Qty ","")&":"),";")),"") -> 24.33 | P72: =IFERROR(VALUE(_xlfn.TEXTBEFORE(_xlfn.TEXTAFTER(";"&$N72,";"&SUBSTITUTE(P$1,"Qty ","")&":"),";")),"") -> 23.21 | Q72: =IFERROR(VALUE(_xlfn.TEXTBEFORE(_xlfn.TEXTAFTER(";"&$N72,";"&SUBSTITUTE(Q$1,"Qty ","")&":"),";")),"") -> 19.35 | R72: =IFERROR(VALUE(_xlfn.TEXTBEFORE(_xlfn.TEXTAFTER(";"&$N72,";"&SUBSTITUTE(R$1,"Qty ","")&":"),";")),"") -> 15.29 | S72: =IFERROR(VALUE(_xlfn.TEXTBEFORE(_xlfn.TEXTAFTER(";"&$N72,";"&SUBSTITUTE(S$1,"Qty ","")&":"),";")),"") -> 13.03 | T72: =IFERROR(VALUE(_xlfn.TEXTBEFORE(_xlfn.TEXTAFTER(";"&$N72,";"&SUBSTITUTE(T$1,"Qty ","")&":"),";")),"") -> 12.21 | U72: =IFERROR(VALUE(_xlfn.TEXTBEFORE(_xlfn.TEXTAFTER(";"&$N72,";"&SUBSTITUTE(U$1,"Qty ","")&":"),";")),"") -> 11.74 | V72: =IFERROR(VALUE(_xlfn.TEXTBEFORE(_xlfn.TEXTAFTER(";"&$N72,";"&SUBSTITUTE(V$1,"Qty ","")&":"),";")),"") -> 11.14 | W72: =IFERROR(VALUE(_xlfn.TEXTBEFORE(_xlfn.TEXTAFTER(";"&$N72,";"&SUBSTITUTE(W$1,"Qty ","")&":"),";")),"") -> 10.37 | X72: {=IF(Y72="","",_xlfn.TEXTJOIN(";",TRUE,SUBSTITUTE($Y$1:$AG$1,"Qty ","")&":"&TEXT(Y72:AG72,"0.00"))&";")} -> 1:30.45;10:28.72;25:24.24;50:19.37;100:16.75;250:15.60;500:15.01;750:14.41;1000:13.55; | Y72: ='Blocking Prices'!$C$16+O72 -> 30.45 | Z72: ='Blocking Prices'!$D$16+P72 -> 28.72 | AA72: ='Blocking Prices'!$E$16+Q72 -> 24.24 | AB72: ='Blocking Prices'!$F$16+R72 -> 19.37 | AC72: ='Blocking Prices'!$G$16+S72 -> 16.75 | AD72: ='Blocking Prices'!$H$16+T72 -> 15.6 | AE72: ='Blocking Prices'!$I$16+U72 -> 15.01 | AF72: ='Blocking Prices'!$J$16+V72 -> 14.41 | AG72: ='Blocking Prices'!$K$16+W72 -> 13.55 | AL72: <p class="p1">Chelsea Leather range, luxury soft grained real leather?week to view layout.<span class="Apple-converted-space">?</span>Smyth sewn sections for strength and durability printed on white or cream FSC paper.<span class="Apple-converted-space">?</span>Self-colour cotton perimeter stitched flexible cover, ribbon marker, general information pages, forward planners, UK and international holidays, contacts directory, notes page and full colour map section</p>_x000D_\n&nbsp; | AM72: Chelsea Leather range, luxury soft grained real leather week to view layout. Smyth sewn sections for strength and durability printed on white or cream FSC paper. Self-colour cotton perimeter stitched flexible cover, ribbon marker, general information pages, forward planners, UK and international holidays, contacts directory, notes page and full colour map section | AN72: =IFERROR(_xlfn.LET(_xlpm.v,INDEX('product-export-27-8-2026'!$A:$AJ,MATCH($A72,'product-export-27-8-2026'!$A:$A,0),MATCH(AN$1,'product-export-27-8-2026'!$1:$1,0)),IF(_xlpm.v="","",_xlpm.v)),"") | AO72: =IFERROR(_xlfn.LET(_xlpm.v,INDEX('product-export-27-8-2026'!$A:$AJ,MATCH($A72,'product-export-27-8-2026'!$A:$A,0),MATCH(AO$1,'product-export-27-8-2026'!$1:$1,0)),IF(_xlpm.v="","",_xlpm.v)),"") | AP72: =IFERROR(_xlfn.LET(_xlpm.v,INDEX('product-export-27-8-2026'!$A:$AJ,MATCH($A72,'product-export-27-8-2026'!$A:$A,0),MATCH(AP$1,'product-export-27-8-2026'!$1:$1,0)),IF(_xlpm.v="","",_xlpm.v)),"") | AQ72: =IFERROR(_xlfn.LET(_xlpm.v,INDEX('product-export-27-8-2026'!$A:$AJ,MATCH($A72,'product-export-27-8-2026'!$A:$A,0),MATCH(AQ$1,'product-export-27-8-2026'!$1:$1,0)),IF(_xlpm.v="","",_xlpm.v)),"") | AR72: =IFERROR(_xlfn.LET(_xlpm.v,INDEX('product-export-27-8-2026'!$A:$AJ,MATCH($A72,'product-export-27-8-2026'!$A:$A,0),MATCH(AR$1,'product-export-27-8-2026'!$1:$1,0)),IF(_xlpm.v="","",_xlpm.v)),"") -> Chelsea Collection, Diaries, Foil blocked, Diaries > Quarto Diary, Diaries > Quarto Diary > Quarto WTV, Diaries > Real Leather | AS72: =IFERROR(_xlfn.LET(_xlpm.v,INDEX('product-export-27-8-2026'!$A:$AJ,MATCH($A72,'product-export-27-8-2026'!$A:$A,0),MATCH(AS$1,'product-export-27-8-2026'!$1:$1,0)),IF(_xlpm.v="","",_xlpm.v)),"") -> Chelsea-Leather-Quarto-Diary-Week-To-View
A73: 997 | B73: Dorchester Bicolour Quarto Desk Diary, Week to View, Black-Red | C73: Diary | D73: NB-BK/RD-P-084 | E73: NB-BK/RD-P-084 | F73: NF83U | G73: Quarto | H73: Black-Red | I73: Week to View | J73: Cream | K73: 27mm x 27mm | L73: 0.48 | M73: 15.5 | N73: 1:15.67;10:15.02;25:10.90;50:9.74;100:9.05;250:8.39;500:8.06;750:7.70;1000:7.25; | O73: =IFERROR(VALUE(_xlfn.TEXTBEFORE(_xlfn.TEXTAFTER(";"&$N73,";"&SUBSTITUTE(O$1,"Qty ","")&":"),";")),"") -> 15.67 | P73: =IFERROR(VALUE(_xlfn.TEXTBEFORE(_xlfn.TEXTAFTER(";"&$N73,";"&SUBSTITUTE(P$1,"Qty ","")&":"),";")),"") -> 15.02 | Q73: =IFERROR(VALUE(_xlfn.TEXTBEFORE(_xlfn.TEXTAFTER(";"&$N73,";"&SUBSTITUTE(Q$1,"Qty ","")&":"),";")),"") -> 10.9 | R73: =IFERROR(VALUE(_xlfn.TEXTBEFORE(_xlfn.TEXTAFTER(";"&$N73,";"&SUBSTITUTE(R$1,"Qty ","")&":"),";")),"") -> 9.74 | S73: =IFERROR(VALUE(_xlfn.TEXTBEFORE(_xlfn.TEXTAFTER(";"&$N73,";"&SUBSTITUTE(S$1,"Qty ","")&":"),";")),"") -> 9.05 | T73: =IFERROR(VALUE(_xlfn.TEXTBEFORE(_xlfn.TEXTAFTER(";"&$N73,";"&SUBSTITUTE(T$1,"Qty ","")&":"),";")),"") -> 8.39 | U73: =IFERROR(VALUE(_xlfn.TEXTBEFORE(_xlfn.TEXTAFTER(";"&$N73,";"&SUBSTITUTE(U$1,"Qty ","")&":"),";")),"") -> 8.06 | V73: =IFERROR(VALUE(_xlfn.TEXTBEFORE(_xlfn.TEXTAFTER(";"&$N73,";"&SUBSTITUTE(V$1,"Qty ","")&":"),";")),"") -> 7.7 | W73: =IFERROR(VALUE(_xlfn.TEXTBEFORE(_xlfn.TEXTAFTER(";"&$N73,";"&SUBSTITUTE(W$1,"Qty ","")&":"),";")),"") -> 7.25 | X73: {=IF(Y73="","",_xlfn.TEXTJOIN(";",TRUE,SUBSTITUTE($Y$1:$AG$1,"Qty ","")&":"&TEXT(Y73:AG73,"0.00"))&";")} -> 1:21.79;10:20.53;25:15.79;50:13.82;100:12.77;250:11.78;500:11.33;750:10.97;1000:10.43; | Y73: ='Blocking Prices'!$C$16+O73 -> 21.79 | Z73: ='Blocking Prices'!$D$16+P73 -> 20.53 | AA73: ='Blocking Prices'!$E$16+Q73 -> 15.79 | AB73: ='Blocking Prices'!$F$16+R73 -> 13.82 | AC73: ='Blocking Prices'!$G$16+S73 -> 12.77 | AD73: ='Blocking Prices'!$H$16+T73 -> 11.78 | AE73: ='Blocking Prices'!$I$16+U73 -> 11.33 | AF73: ='Blocking Prices'!$J$16+V73 -> 10.97 | AG73: ='Blocking Prices'!$K$16+W73 -> 10.43 | AL73: Stay organized with the Dorchester Bicolor Quarto Diary - Week to View. With a sleek one or two design,?cream paper?paper, and a spacious week-to-view layout, this stylish diary is perfect for keeping track of your week in a modern, professional format. | AM73: The Dorchester Bicolour Quarto Diary - White Paper ? Week to View brings together functionality and contemporary style in a compact, high-quality design. With its bold bicolour cover and premium construction, this diary is ideal for those who seek a modern solution to their planning needs. The Quarto size offers a spacious layout, making it perfect for professionals, creatives, or anyone who needs ample space for their weekly appointments and tasks._x000D_\n_x000D_\nFeaturing a week-to-view format, the diary presents your schedule across two pages, allowing for easy organization of meetings, deadlines, and personal notes. The crisp white paper enhances readability and adds a touch of sophistication. The diary is also equipped with a ribbon marker and perimeter stitching, adding both durability and style to this must-have planning tool. With its sleek design and practical features, the Dorchester Bicolour Quarto Diary is perfect for anyone who wants a reliable, stylish companion for their week-to-week organization. | AN73: =IFERROR(_xlfn.LET(_xlpm.v,INDEX('product-export-27-8-2026'!$A:$AJ,MATCH($A73,'product-export-27-8-2026'!$A:$A,0),MATCH(AN$1,'product-export-27-8-2026'!$1:$1,0)),IF(_xlpm.v="","",_xlpm.v)),"") | AO73: =IFERROR(_xlfn.LET(_xlpm.v,INDEX('product-export-27-8-2026'!$A:$AJ,MATCH($A73,'product-export-27-8-2026'!$A:$A,0),MATCH(AO$1,'product-export-27-8-2026'!$1:$1,0)),IF(_xlpm.v="","",_xlpm.v)),"") | AP73: =IFERROR(_xlfn.LET(_xlpm.v,INDEX('product-export-27-8-2026'!$A:$AJ,MATCH($A73,'product-export-27-8-2026'!$A:$A,0),MATCH(AP$1,'product-export-27-8-2026'!$1:$1,0)),IF(_xlpm.v="","",_xlpm.v)),"") | AQ73: =IFERROR(_xlfn.LET(_xlpm.v,INDEX('product-export-27-8-2026'!$A:$AJ,MATCH($A73,'product-export-27-8-2026'!$A:$A,0),MATCH(AQ$1,'product-export-27-8-2026'!$1:$1,0)),IF(_xlpm.v="","",_xlpm.v)),"") | AR73: =IFERROR(_xlfn.LET(_xlpm.v,INDEX('product-export-27-8-2026'!$A:$AJ,MATCH($A73,'product-export-27-8-2026'!$A:$A,0),MATCH(AR$1,'product-export-27-8-2026'!$1:$1,0)),IF(_xlpm.v="","",_xlpm.v)),"") -> Diaries, Dorchester Collection, Diaries > Quarto Diary, Diaries > Quarto Diary > Quarto WTV | AS73: =IFERROR(_xlfn.LET(_xlpm.v,INDEX('product-export-27-8-2026'!$A:$AJ,MATCH($A73,'product-export-27-8-2026'!$A:$A,0),MATCH(AS$1,'product-export-27-8-2026'!$1:$1,0)),IF(_xlpm.v="","",_xlpm.v)),"") -> Dorchester-Bicolour-Quarto-Desk-Diary-Week-to-View
A74: 1000 | B74: Dorchester Bicolour Quarto Desk Diary, Week to View, Black-Aqua | C74: Diary | D74: NB-BK/AQ-P-084 | E74: NB-BK/AQ-P-084 | F74: NF83U | G74: Quarto | H74: Black-Aqua | I74: Week to View | J74: Cream | K74: 27mm x 27mm | L74: 0.48 | M74: 15.5 | N74: 1:15.67;10:15.02;25:10.90;50:9.74;100:9.05;250:8.39;500:8.06;750:7.70;1000:7.25; | O74: =IFERROR(VALUE(_xlfn.TEXTBEFORE(_xlfn.TEXTAFTER(";"&$N74,";"&SUBSTITUTE(O$1,"Qty ","")&":"),";")),"") -> 15.67 | P74: =IFERROR(VALUE(_xlfn.TEXTBEFORE(_xlfn.TEXTAFTER(";"&$N74,";"&SUBSTITUTE(P$1,"Qty ","")&":"),";")),"") -> 15.02 | Q74: =IFERROR(VALUE(_xlfn.TEXTBEFORE(_xlfn.TEXTAFTER(";"&$N74,";"&SUBSTITUTE(Q$1,"Qty ","")&":"),";")),"") -> 10.9 | R74: =IFERROR(VALUE(_xlfn.TEXTBEFORE(_xlfn.TEXTAFTER(";"&$N74,";"&SUBSTITUTE(R$1,"Qty ","")&":"),";")),"") -> 9.74 | S74: =IFERROR(VALUE(_xlfn.TEXTBEFORE(_xlfn.TEXTAFTER(";"&$N74,";"&SUBSTITUTE(S$1,"Qty ","")&":"),";")),"") -> 9.05 | T74: =IFERROR(VALUE(_xlfn.TEXTBEFORE(_xlfn.TEXTAFTER(";"&$N74,";"&SUBSTITUTE(T$1,"Qty ","")&":"),";")),"") -> 8.39 | U74: =IFERROR(VALUE(_xlfn.TEXTBEFORE(_xlfn.TEXTAFTER(";"&$N74,";"&SUBSTITUTE(U$1,"Qty ","")&":"),";")),"") -> 8.06 | V74: =IFERROR(VALUE(_xlfn.TEXTBEFORE(_xlfn.TEXTAFTER(";"&$N74,";"&SUBSTITUTE(V$1,"Qty ","")&":"),";")),"") -> 7.7 | W74: =IFERROR(VALUE(_xlfn.TEXTBEFORE(_xlfn.TEXTAFTER(";"&$N74,";"&SUBSTITUTE(W$1,"Qty ","")&":"),";")),"") -> 7.25 | X74: {=IF(Y74="","",_xlfn.TEXTJOIN(";",TRUE,SUBSTITUTE($Y$1:$AG$1,"Qty ","")&":"&TEXT(Y74:AG74,"0.00"))&";")} -> 1:21.79;10:20.53;25:15.79;50:13.82;100:12.77;250:11.78;500:11.33;750:10.97;1000:10.43; | Y74: ='Blocking Prices'!$C$16+O74 -> 21.79 | Z74: ='Blocking Prices'!$D$16+P74 -> 20.53 | AA74: ='Blocking Prices'!$E$16+Q74 -> 15.79 | AB74: ='Blocking Prices'!$F$16+R74 -> 13.82 | AC74: ='Blocking Prices'!$G$16+S74 -> 12.77 | AD74: ='Blocking Prices'!$H$16+T74 -> 11.78 | AE74: ='Blocking Prices'!$I$16+U74 -> 11.33 | AF74: ='Blocking Prices'!$J$16+V74 -> 10.97 | AG74: ='Blocking Prices'!$K$16+W74 -> 10.43 | AL74: Stay organized with the Dorchester Bicolor Quarto Diary - Week to View. With a sleek one or two design,?cream paper?paper, and a spacious week-to-view layout, this stylish diary is perfect for keeping track of your week in a modern, professional format. | AM74: The Dorchester Bicolour Quarto Diary - White Paper ? Week to View brings together functionality and contemporary style in a compact, high-quality design. With its bold bicolour cover and premium construction, this diary is ideal for those who seek a modern solution to their planning needs. The Quarto size offers a spacious layout, making it perfect for professionals, creatives, or anyone who needs ample space for their weekly appointments and tasks._x000D_\n_x000D_\nFeaturing a week-to-view format, the diary presents your schedule across two pages, allowing for easy organization of meetings, deadlines, and personal notes. The crisp white paper enhances readability and adds a touch of sophistication. The diary is also equipped with a ribbon marker and perimeter stitching, adding both durability and style to this must-have planning tool. With its sleek design and practical features, the Dorchester Bicolour Quarto Diary is perfect for anyone who wants a reliable, stylish companion for their week-to-week organization. | AN74: =IFERROR(_xlfn.LET(_xlpm.v,INDEX('product-export-27-8-2026'!$A:$AJ,MATCH($A74,'product-export-27-8-2026'!$A:$A,0),MATCH(AN$1,'product-export-27-8-2026'!$1:$1,0)),IF(_xlpm.v="","",_xlpm.v)),"") | AO74: =IFERROR(_xlfn.LET(_xlpm.v,INDEX('product-export-27-8-2026'!$A:$AJ,MATCH($A74,'product-export-27-8-2026'!$A:$A,0),MATCH(AO$1,'product-export-27-8-2026'!$1:$1,0)),IF(_xlpm.v="","",_xlpm.v)),"") | AP74: =IFERROR(_xlfn.LET(_xlpm.v,INDEX('product-export-27-8-2026'!$A:$AJ,MATCH($A74,'product-export-27-8-2026'!$A:$A,0),MATCH(AP$1,'product-export-27-8-2026'!$1:$1,0)),IF(_xlpm.v="","",_xlpm.v)),"") | AQ74: =IFERROR(_xlfn.LET(_xlpm.v,INDEX('product-export-27-8-2026'!$A:$AJ,MATCH($A74,'product-export-27-8-2026'!$A:$A,0),MATCH(AQ$1,'product-export-27-8-2026'!$1:$1,0)),IF(_xlpm.v="","",_xlpm.v)),"") | AR74: =IFERROR(_xlfn.LET(_xlpm.v,INDEX('product-export-27-8-2026'!$A:$AJ,MATCH($A74,'product-export-27-8-2026'!$A:$A,0),MATCH(AR$1,'product-export-27-8-2026'!$1:$1,0)),IF(_xlpm.v="","",_xlpm.v)),"") -> Diaries, Dorchester Collection, Diaries > Quarto Diary, Diaries > Quarto Diary > Quarto WTV | AS74: =IFERROR(_xlfn.LET(_xlpm.v,INDEX('product-export-27-8-2026'!$A:$AJ,MATCH($A74,'product-export-27-8-2026'!$A:$A,0),MATCH(AS$1,'product-export-27-8-2026'!$1:$1,0)),IF(_xlpm.v="","",_xlpm.v)),"") -> Dorchester-Bicolour-Quarto-Desk-Diary-Week-to-View
A75: 1002 | B75: Dorchester Bicolour Quarto Desk Diary, Week to View, Black-Orange | C75: Diary | D75: NB-BK/OR-P-084 | E75: NB-BK/OR-P-084 | F75: NF83U | G75: Quarto | H75: Black-Orange | I75: Week to View | J75: Cream | K75: 27mm x 27mm | L75: 0.48 | M75: 15.5 | N75: 1:15.67;10:15.02;25:10.90;50:9.74;100:9.05;250:8.39;500:8.06;750:7.70;1000:7.25; | O75: =IFERROR(VALUE(_xlfn.TEXTBEFORE(_xlfn.TEXTAFTER(";"&$N75,";"&SUBSTITUTE(O$1,"Qty ","")&":"),";")),"") -> 15.67 | P75: =IFERROR(VALUE(_xlfn.TEXTBEFORE(_xlfn.TEXTAFTER(";"&$N75,";"&SUBSTITUTE(P$1,"Qty ","")&":"),";")),"") -> 15.02 | Q75: =IFERROR(VALUE(_xlfn.TEXTBEFORE(_xlfn.TEXTAFTER(";"&$N75,";"&SUBSTITUTE(Q$1,"Qty ","")&":"),";")),"") -> 10.9 | R75: =IFERROR(VALUE(_xlfn.TEXTBEFORE(_xlfn.TEXTAFTER(";"&$N75,";"&SUBSTITUTE(R$1,"Qty ","")&":"),";")),"") -> 9.74 | S75: =IFERROR(VALUE(_xlfn.TEXTBEFORE(_xlfn.TEXTAFTER(";"&$N75,";"&SUBSTITUTE(S$1,"Qty ","")&":"),";")),"") -> 9.05 | T75: =IFERROR(VALUE(_xlfn.TEXTBEFORE(_xlfn.TEXTAFTER(";"&$N75,";"&SUBSTITUTE(T$1,"Qty ","")&":"),";")),"") -> 8.39 | U75: =IFERROR(VALUE(_xlfn.TEXTBEFORE(_xlfn.TEXTAFTER(";"&$N75,";"&SUBSTITUTE(U$1,"Qty ","")&":"),";")),"") -> 8.06 | V75: =IFERROR(VALUE(_xlfn.TEXTBEFORE(_xlfn.TEXTAFTER(";"&$N75,";"&SUBSTITUTE(V$1,"Qty ","")&":"),";")),"") -> 7.7 | W75: =IFERROR(VALUE(_xlfn.TEXTBEFORE(_xlfn.TEXTAFTER(";"&$N75,";"&SUBSTITUTE(W$1,"Qty ","")&":"),";")),"") -> 7.25 | X75: {=IF(Y75="","",_xlfn.TEXTJOIN(";",TRUE,SUBSTITUTE($Y$1:$AG$1,"Qty ","")&":"&TEXT(Y75:AG75,"0.00"))&";")} -> 1:21.79;10:20.53;25:15.79;50:13.82;100:12.77;250:11.78;500:11.33;750:10.97;1000:10.43; | Y75: ='Blocking Prices'!$C$16+O75 -> 21.79 | Z75: ='Blocking Prices'!$D$16+P75 -> 20.53 | AA75: ='Blocking Prices'!$E$16+Q75 -> 15.79 | AB75: ='Blocking Prices'!$F$16+R75 -> 13.82 | AC75: ='Blocking Prices'!$G$16+S75 -> 12.77 | AD75: ='Blocking Prices'!$H$16+T75 -> 11.78 | AE75: ='Blocking Prices'!$I$16+U75 -> 11.33 | AF75: ='Blocking Prices'!$J$16+V75 -> 10.97 | AG75: ='Blocking Prices'!$K$16+W75 -> 10.43 | AL75: Stay organized with the Dorchester Bicolor Quarto Diary - Week to View. With a sleek one or two design,?cream paper?paper, and a spacious week-to-view layout, this stylish diary is perfect for keeping track of your week in a modern, professional format._x000D_\n_x000D_\n&nbsp; | AM75: The Dorchester Bicolour Quarto Diary - White Paper ? Week to View brings together functionality and contemporary style in a compact, high-quality design. With its bold bicolour cover and premium construction, this diary is ideal for those who seek a modern solution to their planning needs. The Quarto size offers a spacious layout, making it perfect for professionals, creatives, or anyone who needs ample space for their weekly appointments and tasks._x000D_\n_x000D_\nFeaturing a week-to-view format, the diary presents your schedule across two pages, allowing for easy organization of meetings, deadlines, and personal notes. The crisp white paper enhances readability and adds a touch of sophistication. The diary is also equipped with a ribbon marker and perimeter stitching, adding both durability and style to this must-have planning tool. With its sleek design and practical features, the Dorchester Bicolour Quarto Diary is perfect for anyone who wants a reliable, stylish companion for their week-to-week organization. | AN75: =IFERROR(_xlfn.LET(_xlpm.v,INDEX('product-export-27-8-2026'!$A:$AJ,MATCH($A75,'product-export-27-8-2026'!$A:$A,0),MATCH(AN$1,'product-export-27-8-2026'!$1:$1,0)),IF(_xlpm.v="","",_xlpm.v)),"") | AO75: =IFERROR(_xlfn.LET(_xlpm.v,INDEX('product-export-27-8-2026'!$A:$AJ,MATCH($A75,'product-export-27-8-2026'!$A:$A,0),MATCH(AO$1,'product-export-27-8-2026'!$1:$1,0)),IF(_xlpm.v="","",_xlpm.v)),"") | AP75: =IFERROR(_xlfn.LET(_xlpm.v,INDEX('product-export-27-8-2026'!$A:$AJ,MATCH($A75,'product-export-27-8-2026'!$A:$A,0),MATCH(AP$1,'product-export-27-8-2026'!$1:$1,0)),IF(_xlpm.v="","",_xlpm.v)),"") | AQ75: =IFERROR(_xlfn.LET(_xlpm.v,INDEX('product-export-27-8-2026'!$A:$AJ,MATCH($A75,'product-export-27-8-2026'!$A:$A,0),MATCH(AQ$1,'product-export-27-8-2026'!$1:$1,0)),IF(_xlpm.v="","",_xlpm.v)),"") | AR75: =IFERROR(_xlfn.LET(_xlpm.v,INDEX('product-export-27-8-2026'!$A:$AJ,MATCH($A75,'product-export-27-8-2026'!$A:$A,0),MATCH(AR$1,'product-export-27-8-2026'!$1:$1,0)),IF(_xlpm.v="","",_xlpm.v)),"") -> Diaries, Dorchester Collection, Diaries > Quarto Diary, Diaries > Quarto Diary > Quarto WTV | AS75: =IFERROR(_xlfn.LET(_xlpm.v,INDEX('product-export-27-8-2026'!$A:$AJ,MATCH($A75,'product-export-27-8-2026'!$A:$A,0),MATCH(AS$1,'product-export-27-8-2026'!$1:$1,0)),IF(_xlpm.v="","",_xlpm.v)),"") -> Dorchester-Bicolour-Quarto-Desk-Diary-Week-to-View
A76: 1004 | B76: Dorchester Bicolour Quarto Desk Diary, Week to View, Black-Purple | C76: Diary | D76: NB-BK/PU-P-084 | E76: NB-BK/PU-P-084 | F76: NF83U | G76: Quarto | H76: Black-Purple | I76: Week to View | J76: Cream | K76: 27mm x 27mm | L76: 0.48 | M76: 15.5 | N76: 1:15.67;10:15.02;25:10.90;50:9.74;100:9.05;250:8.39;500:8.06;750:7.70;1000:7.25; | O76: =IFERROR(VALUE(_xlfn.TEXTBEFORE(_xlfn.TEXTAFTER(";"&$N76,";"&SUBSTITUTE(O$1,"Qty ","")&":"),";")),"") -> 15.67 | P76: =IFERROR(VALUE(_xlfn.TEXTBEFORE(_xlfn.TEXTAFTER(";"&$N76,";"&SUBSTITUTE(P$1,"Qty ","")&":"),";")),"") -> 15.02 | Q76: =IFERROR(VALUE(_xlfn.TEXTBEFORE(_xlfn.TEXTAFTER(";"&$N76,";"&SUBSTITUTE(Q$1,"Qty ","")&":"),";")),"") -> 10.9 | R76: =IFERROR(VALUE(_xlfn.TEXTBEFORE(_xlfn.TEXTAFTER(";"&$N76,";"&SUBSTITUTE(R$1,"Qty ","")&":"),";")),"") -> 9.74 | S76: =IFERROR(VALUE(_xlfn.TEXTBEFORE(_xlfn.TEXTAFTER(";"&$N76,";"&SUBSTITUTE(S$1,"Qty ","")&":"),";")),"") -> 9.05 | T76: =IFERROR(VALUE(_xlfn.TEXTBEFORE(_xlfn.TEXTAFTER(";"&$N76,";"&SUBSTITUTE(T$1,"Qty ","")&":"),";")),"") -> 8.39 | U76: =IFERROR(VALUE(_xlfn.TEXTBEFORE(_xlfn.TEXTAFTER(";"&$N76,";"&SUBSTITUTE(U$1,"Qty ","")&":"),";")),"") -> 8.06 | V76: =IFERROR(VALUE(_xlfn.TEXTBEFORE(_xlfn.TEXTAFTER(";"&$N76,";"&SUBSTITUTE(V$1,"Qty ","")&":"),";")),"") -> 7.7 | W76: =IFERROR(VALUE(_xlfn.TEXTBEFORE(_xlfn.TEXTAFTER(";"&$N76,";"&SUBSTITUTE(W$1,"Qty ","")&":"),";")),"") -> 7.25 | X76: {=IF(Y76="","",_xlfn.TEXTJOIN(";",TRUE,SUBSTITUTE($Y$1:$AG$1,"Qty ","")&":"&TEXT(Y76:AG76,"0.00"))&";")} -> 1:21.79;10:20.53;25:15.79;50:13.82;100:12.77;250:11.78;500:11.33;750:10.97;1000:10.43; | Y76: ='Blocking Prices'!$C$16+O76 -> 21.79 | Z76: ='Blocking Prices'!$D$16+P76 -> 20.53 | AA76: ='Blocking Prices'!$E$16+Q76 -> 15.79 | AB76: ='Blocking Prices'!$F$16+R76 -> 13.82 | AC76: ='Blocking Prices'!$G$16+S76 -> 12.77 | AD76: ='Blocking Prices'!$H$16+T76 -> 11.78 | AE76: ='Blocking Prices'!$I$16+U76 -> 11.33 | AF76: ='Blocking Prices'!$J$16+V76 -> 10.97 | AG76: ='Blocking Prices'!$K$16+W76 -> 10.43 | AL76: Stay organized with the Dorchester Bicolor Quarto Diary - Week to View. With a sleek one or two design,?cream paper?paper, and a spacious week-to-view layout, this stylish diary is perfect for keeping track of your week in a modern, professional format._x000D_\n_x000D_\n&nbsp; | AM76: The Dorchester Bicolour Quarto Diary - White Paper ? Week to View brings together functionality and contemporary style in a compact, high-quality design. With its bold bicolour cover and premium construction, this diary is ideal for those who seek a modern solution to their planning needs. The Quarto size offers a spacious layout, making it perfect for professionals, creatives, or anyone who needs ample space for their weekly appointments and tasks._x000D_\n_x000D_\nFeaturing a week-to-view format, the diary presents your schedule across two pages, allowing for easy organization of meetings, deadlines, and personal notes. The crisp white paper enhances readability and adds a touch of sophistication. The diary is also equipped with a ribbon marker and perimeter stitching, adding both durability and style to this must-have planning tool. With its sleek design and practical features, the Dorchester Bicolour Quarto Diary is perfect for anyone who wants a reliable, stylish companion for their week-to-week organization. | AN76: =IFERROR(_xlfn.LET(_xlpm.v,INDEX('product-export-27-8-2026'!$A:$AJ,MATCH($A76,'product-export-27-8-2026'!$A:$A,0),MATCH(AN$1,'product-export-27-8-2026'!$1:$1,0)),IF(_xlpm.v="","",_xlpm.v)),"") | AO76: =IFERROR(_xlfn.LET(_xlpm.v,INDEX('product-export-27-8-2026'!$A:$AJ,MATCH($A76,'product-export-27-8-2026'!$A:$A,0),MATCH(AO$1,'product-export-27-8-2026'!$1:$1,0)),IF(_xlpm.v="","",_xlpm.v)),"") | AP76: =IFERROR(_xlfn.LET(_xlpm.v,INDEX('product-export-27-8-2026'!$A:$AJ,MATCH($A76,'product-export-27-8-2026'!$A:$A,0),MATCH(AP$1,'product-export-27-8-2026'!$1:$1,0)),IF(_xlpm.v="","",_xlpm.v)),"") | AQ76: =IFERROR(_xlfn.LET(_xlpm.v,INDEX('product-export-27-8-2026'!$A:$AJ,MATCH($A76,'product-export-27-8-2026'!$A:$A,0),MATCH(AQ$1,'product-export-27-8-2026'!$1:$1,0)),IF(_xlpm.v="","",_xlpm.v)),"") | AR76: =IFERROR(_xlfn.LET(_xlpm.v,INDEX('product-export-27-8-2026'!$A:$AJ,MATCH($A76,'product-export-27-8-2026'!$A:$A,0),MATCH(AR$1,'product-export-27-8-2026'!$1:$1,0)),IF(_xlpm.v="","",_xlpm.v)),"") -> Diaries, Dorchester Collection, Diaries > Quarto Diary, Diaries > Quarto Diary > Quarto WTV | AS76: =IFERROR(_xlfn.LET(_xlpm.v,INDEX('product-export-27-8-2026'!$A:$AJ,MATCH($A76,'product-export-27-8-2026'!$A:$A,0),MATCH(AS$1,'product-export-27-8-2026'!$1:$1,0)),IF(_xlpm.v="","",_xlpm.v)),"") -> Dorchester-Bicolour-Quarto-Desk-Diary-Week-to-View
A77: 1006 | B77: Dorchester Bicolour Quarto Desk Diary, Week to View, Black-Royal Blue | C77: Diary | D77: NB-BL/RB-P-084 | E77: NB-BL/RB-P-084 | F77: NF83U | G77: Quarto | H77: Black-Royal Blue | I77: Week to View | J77: Cream | K77: 27mm x 27mm | L77: 0.48 | M77: 15.5 | N77: 1:15.67;10:15.02;25:10.90;50:9.74;100:9.05;250:8.39;500:8.06;750:7.70;1000:7.25; | O77: =IFERROR(VALUE(_xlfn.TEXTBEFORE(_xlfn.TEXTAFTER(";"&$N77,";"&SUBSTITUTE(O$1,"Qty ","")&":"),";")),"") -> 15.67 | P77: =IFERROR(VALUE(_xlfn.TEXTBEFORE(_xlfn.TEXTAFTER(";"&$N77,";"&SUBSTITUTE(P$1,"Qty ","")&":"),";")),"") -> 15.02 | Q77: =IFERROR(VALUE(_xlfn.TEXTBEFORE(_xlfn.TEXTAFTER(";"&$N77,";"&SUBSTITUTE(Q$1,"Qty ","")&":"),";")),"") -> 10.9 | R77: =IFERROR(VALUE(_xlfn.TEXTBEFORE(_xlfn.TEXTAFTER(";"&$N77,";"&SUBSTITUTE(R$1,"Qty ","")&":"),";")),"") -> 9.74 | S77: =IFERROR(VALUE(_xlfn.TEXTBEFORE(_xlfn.TEXTAFTER(";"&$N77,";"&SUBSTITUTE(S$1,"Qty ","")&":"),";")),"") -> 9.05 | T77: =IFERROR(VALUE(_xlfn.TEXTBEFORE(_xlfn.TEXTAFTER(";"&$N77,";"&SUBSTITUTE(T$1,"Qty ","")&":"),";")),"") -> 8.39 | U77: =IFERROR(VALUE(_xlfn.TEXTBEFORE(_xlfn.TEXTAFTER(";"&$N77,";"&SUBSTITUTE(U$1,"Qty ","")&":"),";")),"") -> 8.06 | V77: =IFERROR(VALUE(_xlfn.TEXTBEFORE(_xlfn.TEXTAFTER(";"&$N77,";"&SUBSTITUTE(V$1,"Qty ","")&":"),";")),"") -> 7.7 | W77: =IFERROR(VALUE(_xlfn.TEXTBEFORE(_xlfn.TEXTAFTER(";"&$N77,";"&SUBSTITUTE(W$1,"Qty ","")&":"),";")),"") -> 7.25 | X77: {=IF(Y77="","",_xlfn.TEXTJOIN(";",TRUE,SUBSTITUTE($Y$1:$AG$1,"Qty ","")&":"&TEXT(Y77:AG77,"0.00"))&";")} -> 1:21.79;10:20.53;25:15.79;50:13.82;100:12.77;250:11.78;500:11.33;750:10.97;1000:10.43; | Y77: ='Blocking Prices'!$C$16+O77 -> 21.79 | Z77: ='Blocking Prices'!$D$16+P77 -> 20.53 | AA77: ='Blocking Prices'!$E$16+Q77 -> 15.79 | AB77: ='Blocking Prices'!$F$16+R77 -> 13.82 | AC77: ='Blocking Prices'!$G$16+S77 -> 12.77 | AD77: ='Blocking Prices'!$H$16+T77 -> 11.78 | AE77: ='Blocking Prices'!$I$16+U77 -> 11.33 | AF77: ='Blocking Prices'!$J$16+V77 -> 10.97 | AG77: ='Blocking Prices'!$K$16+W77 -> 10.43 | AL77: Stay organized with the Dorchester Bicolor Quarto Diary - Week to View. With a sleek one or two design,?cream paper?paper, and a spacious week-to-view layout, this stylish diary is perfect for keeping track of your week in a modern, professional format. | AM77: The Dorchester Bicolour Quarto Diary - White Paper ? Week to View brings together functionality and contemporary style in a compact, high-quality design. With its bold bicolour cover and premium construction, this diary is ideal for those who seek a modern solution to their planning needs. The Quarto size offers a spacious layout, making it perfect for professionals, creatives, or anyone who needs ample space for their weekly appointments and tasks._x000D_\n_x000D_\nFeaturing a week-to-view format, the diary presents your schedule across two pages, allowing for easy organization of meetings, deadlines, and personal notes. The crisp white paper enhances readability and adds a touch of sophistication. The diary is also equipped with a ribbon marker and perimeter stitching, adding both durability and style to this must-have planning tool. With its sleek design and practical features, the Dorchester Bicolour Quarto Diary is perfect for anyone who wants a reliable, stylish companion for their week-to-week organization. | AN77: =IFERROR(_xlfn.LET(_xlpm.v,INDEX('product-export-27-8-2026'!$A:$AJ,MATCH($A77,'product-export-27-8-2026'!$A:$A,0),MATCH(AN$1,'product-export-27-8-2026'!$1:$1,0)),IF(_xlpm.v="","",_xlpm.v)),"") | AO77: =IFERROR(_xlfn.LET(_xlpm.v,INDEX('product-export-27-8-2026'!$A:$AJ,MATCH($A77,'product-export-27-8-2026'!$A:$A,0),MATCH(AO$1,'product-export-27-8-2026'!$1:$1,0)),IF(_xlpm.v="","",_xlpm.v)),"") | AP77: =IFERROR(_xlfn.LET(_xlpm.v,INDEX('product-export-27-8-2026'!$A:$AJ,MATCH($A77,'product-export-27-8-2026'!$A:$A,0),MATCH(AP$1,'product-export-27-8-2026'!$1:$1,0)),IF(_xlpm.v="","",_xlpm.v)),"") | AQ77: =IFERROR(_xlfn.LET(_xlpm.v,INDEX('product-export-27-8-2026'!$A:$AJ,MATCH($A77,'product-export-27-8-2026'!$A:$A,0),MATCH(AQ$1,'product-export-27-8-2026'!$1:$1,0)),IF(_xlpm.v="","",_xlpm.v)),"") | AR77: =IFERROR(_xlfn.LET(_xlpm.v,INDEX('product-export-27-8-2026'!$A:$AJ,MATCH($A77,'product-export-27-8-2026'!$A:$A,0),MATCH(AR$1,'product-export-27-8-2026'!$1:$1,0)),IF(_xlpm.v="","",_xlpm.v)),"") -> Diaries, Dorchester Collection, Diaries > Quarto Diary, Diaries > Quarto Diary > Quarto WTV | AS77: =IFERROR(_xlfn.LET(_xlpm.v,INDEX('product-export-27-8-2026'!$A:$AJ,MATCH($A77,'product-export-27-8-2026'!$A:$A,0),MATCH(AS$1,'product-export-27-8-2026'!$1:$1,0)),IF(_xlpm.v="","",_xlpm.v)),"") -> Dorchester-Bicolour-Quarto-Desk-Diary-Week-to-View
A78: 1009 | B78: Dorchester Horizon Quarto Desk Dairy, Week to View, Black-Royal Blue | C78: Diary | D78: HZ-BK/RB-P-084 | E78: HZ-BK/RB-P-084 | F78: HZ84P | G78: Quarto | H78: Black-Royal Blue | I78: Week to View | J78: Cream | K78: 27mm x 27mm | L78: 0.48 | M78: 16.99 | N78: 1:16.79;10:16.09;25:11.80;50:10.67;100:9.71;250:9.64;500:8.50;750:7.95;1000:7.36; | O78: =IFERROR(VALUE(_xlfn.TEXTBEFORE(_xlfn.TEXTAFTER(";"&$N78,";"&SUBSTITUTE(O$1,"Qty ","")&":"),";")),"") -> 16.79 | P78: =IFERROR(VALUE(_xlfn.TEXTBEFORE(_xlfn.TEXTAFTER(";"&$N78,";"&SUBSTITUTE(P$1,"Qty ","")&":"),";")),"") -> 16.09 | Q78: =IFERROR(VALUE(_xlfn.TEXTBEFORE(_xlfn.TEXTAFTER(";"&$N78,";"&SUBSTITUTE(Q$1,"Qty ","")&":"),";")),"") -> 11.8 | R78: =IFERROR(VALUE(_xlfn.TEXTBEFORE(_xlfn.TEXTAFTER(";"&$N78,";"&SUBSTITUTE(R$1,"Qty ","")&":"),";")),"") -> 10.67 | S78: =IFERROR(VALUE(_xlfn.TEXTBEFORE(_xlfn.TEXTAFTER(";"&$N78,";"&SUBSTITUTE(S$1,"Qty ","")&":"),";")),"") -> 9.71 | T78: =IFERROR(VALUE(_xlfn.TEXTBEFORE(_xlfn.TEXTAFTER(";"&$N78,";"&SUBSTITUTE(T$1,"Qty ","")&":"),";")),"") -> 9.64 | U78: =IFERROR(VALUE(_xlfn.TEXTBEFORE(_xlfn.TEXTAFTER(";"&$N78,";"&SUBSTITUTE(U$1,"Qty ","")&":"),";")),"") -> 8.5 | V78: =IFERROR(VALUE(_xlfn.TEXTBEFORE(_xlfn.TEXTAFTER(";"&$N78,";"&SUBSTITUTE(V$1,"Qty ","")&":"),";")),"") -> 7.95 | W78: =IFERROR(VALUE(_xlfn.TEXTBEFORE(_xlfn.TEXTAFTER(";"&$N78,";"&SUBSTITUTE(W$1,"Qty ","")&":"),";")),"") -> 7.36 | X78: {=IF(Y78="","",_xlfn.TEXTJOIN(";",TRUE,SUBSTITUTE($Y$1:$AG$1,"Qty ","")&":"&TEXT(Y78:AG78,"0.00"))&";")} -> 1:22.91;10:21.60;25:16.69;50:14.75;100:13.43;250:13.03;500:11.77;750:11.22;1000:10.54; | Y78: ='Blocking Prices'!$C$16+O78 -> 22.91 | Z78: ='Blocking Prices'!$D$16+P78 -> 21.6 | AA78: ='Blocking Prices'!$E$16+Q78 -> 16.69 | AB78: ='Blocking Prices'!$F$16+R78 -> 14.75 | AC78: ='Blocking Prices'!$G$16+S78 -> 13.43 | AD78: ='Blocking Prices'!$H$16+T78 -> 13.03 | AE78: ='Blocking Prices'!$I$16+U78 -> 11.77 | AF78: ='Blocking Prices'!$J$16+V78 -> 11.22 | AG78: ='Blocking Prices'!$K$16+W78 -> 10.54 | AL78: Stay organized with the Dorchester Bicolor Quarto Diary - Week to View. With a sleek one or two design,?cream paper?paper, and a spacious week-to-view layout, this stylish diary is perfect for keeping track of your week in a modern, professional format._x000D_\n_x000D_\n&nbsp; | AM78: The Dorchester Bicolour Quarto Diary - White Paper ? Week to View brings together functionality and contemporary style in a compact, high-quality design. With its bold bicolour cover and premium construction, this diary is ideal for those who seek a modern solution to their planning needs. The Quarto size offers a spacious layout, making it perfect for professionals, creatives, or anyone who needs ample space for their weekly appointments and tasks._x000D_\n_x000D_\nFeaturing a week-to-view format, the diary presents your schedule across two pages, allowing for easy organization of meetings, deadlines, and personal notes. The crisp white paper enhances readability and adds a touch of sophistication. The diary is also equipped with a ribbon marker and perimeter stitching, adding both durability and style to this must-have planning tool. With its sleek design and practical features, the Dorchester Bicolour Quarto Diary is perfect for anyone who wants a reliable, stylish companion for their week-to-week organization. | AN78: =IFERROR(_xlfn.LET(_xlpm.v,INDEX('product-export-27-8-2026'!$A:$AJ,MATCH($A78,'product-export-27-8-2026'!$A:$A,0),MATCH(AN$1,'product-export-27-8-2026'!$1:$1,0)),IF(_xlpm.v="","",_xlpm.v)),"") | AO78: =IFERROR(_xlfn.LET(_xlpm.v,INDEX('product-export-27-8-2026'!$A:$AJ,MATCH($A78,'product-export-27-8-2026'!$A:$A,0),MATCH(AO$1,'product-export-27-8-2026'!$1:$1,0)),IF(_xlpm.v="","",_xlpm.v)),"") | AP78: =IFERROR(_xlfn.LET(_xlpm.v,INDEX('product-export-27-8-2026'!$A:$AJ,MATCH($A78,'product-export-27-8-2026'!$A:$A,0),MATCH(AP$1,'product-export-27-8-2026'!$1:$1,0)),IF(_xlpm.v="","",_xlpm.v)),"") | AQ78: =IFERROR(_xlfn.LET(_xlpm.v,INDEX('product-export-27-8-2026'!$A:$AJ,MATCH($A78,'product-export-27-8-2026'!$A:$A,0),MATCH(AQ$1,'product-export-27-8-2026'!$1:$1,0)),IF(_xlpm.v="","",_xlpm.v)),"") | AR78: =IFERROR(_xlfn.LET(_xlpm.v,INDEX('product-export-27-8-2026'!$A:$AJ,MATCH($A78,'product-export-27-8-2026'!$A:$A,0),MATCH(AR$1,'product-export-27-8-2026'!$1:$1,0)),IF(_xlpm.v="","",_xlpm.v)),"") -> Diaries, Dorchester Collection, Diaries > Quarto Diary, Diaries > Quarto Diary > Quarto WTV | AS78: =IFERROR(_xlfn.LET(_xlpm.v,INDEX('product-export-27-8-2026'!$A:$AJ,MATCH($A78,'product-export-27-8-2026'!$A:$A,0),MATCH(AS$1,'product-export-27-8-2026'!$1:$1,0)),IF(_xlpm.v="","",_xlpm.v)),"") -> Dorchester-Horizon-Quarto-Desk-Diary-Week-to-View
A79: 1012 | B79: Dorchester Horizon Quarto Desk Diary, Week to View, Black-Black | C79: Diary | D79: HZ-BK/BK-P-084 | E79: HZ-BK/BK-P-084 | F79: HZ84P | G79: Quarto | H79: Black-Black | I79: Week to View | J79: Cream | K79: 27mm x 27mm | L79: 0.48 | M79: 16.99 | N79: 1:16.79;10:16.09;25:11.80;50:10.67;100:9.71;250:9.64;500:8.50;750:7.95;1000:7.36; | O79: =IFERROR(VALUE(_xlfn.TEXTBEFORE(_xlfn.TEXTAFTER(";"&$N79,";"&SUBSTITUTE(O$1,"Qty ","")&":"),";")),"") -> 16.79 | P79: =IFERROR(VALUE(_xlfn.TEXTBEFORE(_xlfn.TEXTAFTER(";"&$N79,";"&SUBSTITUTE(P$1,"Qty ","")&":"),";")),"") -> 16.09 | Q79: =IFERROR(VALUE(_xlfn.TEXTBEFORE(_xlfn.TEXTAFTER(";"&$N79,";"&SUBSTITUTE(Q$1,"Qty ","")&":"),";")),"") -> 11.8 | R79: =IFERROR(VALUE(_xlfn.TEXTBEFORE(_xlfn.TEXTAFTER(";"&$N79,";"&SUBSTITUTE(R$1,"Qty ","")&":"),";")),"") -> 10.67 | S79: =IFERROR(VALUE(_xlfn.TEXTBEFORE(_xlfn.TEXTAFTER(";"&$N79,";"&SUBSTITUTE(S$1,"Qty ","")&":"),";")),"") -> 9.71 | T79: =IFERROR(VALUE(_xlfn.TEXTBEFORE(_xlfn.TEXTAFTER(";"&$N79,";"&SUBSTITUTE(T$1,"Qty ","")&":"),";")),"") -> 9.64 | U79: =IFERROR(VALUE(_xlfn.TEXTBEFORE(_xlfn.TEXTAFTER(";"&$N79,";"&SUBSTITUTE(U$1,"Qty ","")&":"),";")),"") -> 8.5 | V79: =IFERROR(VALUE(_xlfn.TEXTBEFORE(_xlfn.TEXTAFTER(";"&$N79,";"&SUBSTITUTE(V$1,"Qty ","")&":"),";")),"") -> 7.95 | W79: =IFERROR(VALUE(_xlfn.TEXTBEFORE(_xlfn.TEXTAFTER(";"&$N79,";"&SUBSTITUTE(W$1,"Qty ","")&":"),";")),"") -> 7.36 | X79: {=IF(Y79="","",_xlfn.TEXTJOIN(";",TRUE,SUBSTITUTE($Y$1:$AG$1,"Qty ","")&":"&TEXT(Y79:AG79,"0.00"))&";")} -> 1:22.91;10:21.60;25:16.69;50:14.75;100:13.43;250:13.03;500:11.77;750:11.22;1000:10.54; | Y79: ='Blocking Prices'!$C$16+O79 -> 22.91 | Z79: ='Blocking Prices'!$D$16+P79 -> 21.6 | AA79: ='Blocking Prices'!$E$16+Q79 -> 16.69 | AB79: ='Blocking Prices'!$F$16+R79 -> 14.75 | AC79: ='Blocking Prices'!$G$16+S79 -> 13.43 | AD79: ='Blocking Prices'!$H$16+T79 -> 13.03 | AE79: ='Blocking Prices'!$I$16+U79 -> 11.77 | AF79: ='Blocking Prices'!$J$16+V79 -> 11.22 | AG79: ='Blocking Prices'!$K$16+W79 -> 10.54 | AL79: Stay organized with the Dorchester Bicolor Quarto Diary - Week to View. With a sleek one or two design,?cream paper?paper, and a spacious week-to-view layout, this stylish diary is perfect for keeping track of your week in a modern, professional format._x000D_\n_x000D_\n&nbsp; | AM79: The Dorchester Bicolour Quarto Diary - White Paper ? Week to View brings together functionality and contemporary style in a compact, high-quality design. With its bold bicolour cover and premium construction, this diary is ideal for those who seek a modern solution to their planning needs. The Quarto size offers a spacious layout, making it perfect for professionals, creatives, or anyone who needs ample space for their weekly appointments and tasks._x000D_\n_x000D_\nFeaturing a week-to-view format, the diary presents your schedule across two pages, allowing for easy organization of meetings, deadlines, and personal notes. The crisp white paper enhances readability and adds a touch of sophistication. The diary is also equipped with a ribbon marker and perimeter stitching, adding both durability and style to this must-have planning tool. With its sleek design and practical features, the Dorchester Bicolour Quarto Diary is perfect for anyone who wants a reliable, stylish companion for their week-to-week organization. | AN79: =IFERROR(_xlfn.LET(_xlpm.v,INDEX('product-export-27-8-2026'!$A:$AJ,MATCH($A79,'product-export-27-8-2026'!$A:$A,0),MATCH(AN$1,'product-export-27-8-2026'!$1:$1,0)),IF(_xlpm.v="","",_xlpm.v)),"") | AO79: =IFERROR(_xlfn.LET(_xlpm.v,INDEX('product-export-27-8-2026'!$A:$AJ,MATCH($A79,'product-export-27-8-2026'!$A:$A,0),MATCH(AO$1,'product-export-27-8-2026'!$1:$1,0)),IF(_xlpm.v="","",_xlpm.v)),"") | AP79: =IFERROR(_xlfn.LET(_xlpm.v,INDEX('product-export-27-8-2026'!$A:$AJ,MATCH($A79,'product-export-27-8-2026'!$A:$A,0),MATCH(AP$1,'product-export-27-8-2026'!$1:$1,0)),IF(_xlpm.v="","",_xlpm.v)),"") | AQ79: =IFERROR(_xlfn.LET(_xlpm.v,INDEX('product-export-27-8-2026'!$A:$AJ,MATCH($A79,'product-export-27-8-2026'!$A:$A,0),MATCH(AQ$1,'product-export-27-8-2026'!$1:$1,0)),IF(_xlpm.v="","",_xlpm.v)),"") | AR79: =IFERROR(_xlfn.LET(_xlpm.v,INDEX('product-export-27-8-2026'!$A:$AJ,MATCH($A79,'product-export-27-8-2026'!$A:$A,0),MATCH(AR$1,'product-export-27-8-2026'!$1:$1,0)),IF(_xlpm.v="","",_xlpm.v)),"") -> Diaries, Dorchester Collection, Diaries > Quarto Diary, Diaries > Quarto Diary > Quarto WTV | AS79: =IFERROR(_xlfn.LET(_xlpm.v,INDEX('product-export-27-8-2026'!$A:$AJ,MATCH($A79,'product-export-27-8-2026'!$A:$A,0),MATCH(AS$1,'product-export-27-8-2026'!$1:$1,0)),IF(_xlpm.v="","",_xlpm.v)),"")
A80: 1014 | B80: Dorchester Horizon Quarto Desk Diary, Week to View, Green-Green | C80: Diary | D80: HZ-GN/GN-P-084 | E80: HZ-GN/GN-P-084 | F80: HZ84P | G80: Quarto | H80: Green-Green | I80: Week to View | J80: Cream | K80: 27mm x 27mm | L80: 0.48 | M80: 16.99 | N80: 1:16.79;10:16.09;25:11.80;50:10.67;100:9.71;250:9.64;500:8.50;750:7.95;1000:7.36; | O80: =IFERROR(VALUE(_xlfn.TEXTBEFORE(_xlfn.TEXTAFTER(";"&$N80,";"&SUBSTITUTE(O$1,"Qty ","")&":"),";")),"") -> 16.79 | P80: =IFERROR(VALUE(_xlfn.TEXTBEFORE(_xlfn.TEXTAFTER(";"&$N80,";"&SUBSTITUTE(P$1,"Qty ","")&":"),";")),"") -> 16.09 | Q80: =IFERROR(VALUE(_xlfn.TEXTBEFORE(_xlfn.TEXTAFTER(";"&$N80,";"&SUBSTITUTE(Q$1,"Qty ","")&":"),";")),"") -> 11.8 | R80: =IFERROR(VALUE(_xlfn.TEXTBEFORE(_xlfn.TEXTAFTER(";"&$N80,";"&SUBSTITUTE(R$1,"Qty ","")&":"),";")),"") -> 10.67 | S80: =IFERROR(VALUE(_xlfn.TEXTBEFORE(_xlfn.TEXTAFTER(";"&$N80,";"&SUBSTITUTE(S$1,"Qty ","")&":"),";")),"") -> 9.71 | T80: =IFERROR(VALUE(_xlfn.TEXTBEFORE(_xlfn.TEXTAFTER(";"&$N80,";"&SUBSTITUTE(T$1,"Qty ","")&":"),";")),"") -> 9.64 | U80: =IFERROR(VALUE(_xlfn.TEXTBEFORE(_xlfn.TEXTAFTER(";"&$N80,";"&SUBSTITUTE(U$1,"Qty ","")&":"),";")),"") -> 8.5 | V80: =IFERROR(VALUE(_xlfn.TEXTBEFORE(_xlfn.TEXTAFTER(";"&$N80,";"&SUBSTITUTE(V$1,"Qty ","")&":"),";")),"") -> 7.95 | W80: =IFERROR(VALUE(_xlfn.TEXTBEFORE(_xlfn.TEXTAFTER(";"&$N80,";"&SUBSTITUTE(W$1,"Qty ","")&":"),";")),"") -> 7.36 | X80: {=IF(Y80="","",_xlfn.TEXTJOIN(";",TRUE,SUBSTITUTE($Y$1:$AG$1,"Qty ","")&":"&TEXT(Y80:AG80,"0.00"))&";")} -> 1:22.91;10:21.60;25:16.69;50:14.75;100:13.43;250:13.03;500:11.77;750:11.22;1000:10.54; | Y80: ='Blocking Prices'!$C$16+O80 -> 22.91 | Z80: ='Blocking Prices'!$D$16+P80 -> 21.6 | AA80: ='Blocking Prices'!$E$16+Q80 -> 16.69 | AB80: ='Blocking Prices'!$F$16+R80 -> 14.75 | AC80: ='Blocking Prices'!$G$16+S80 -> 13.43 | AD80: ='Blocking Prices'!$H$16+T80 -> 13.03 | AE80: ='Blocking Prices'!$I$16+U80 -> 11.77 | AF80: ='Blocking Prices'!$J$16+V80 -> 11.22 | AG80: ='Blocking Prices'!$K$16+W80 -> 10.54 | AL80: Stay organized with the Dorchester Bicolor Quarto Diary - Week to View. With a sleek one or two design,?cream paper?paper, and a spacious week-to-view layout, this stylish diary is perfect for keeping track of your week in a modern, professional format._x000D_\n_x000D_\n&nbsp; | AM80: The Dorchester Bicolour Quarto Diary - White Paper ? Week to View brings together functionality and contemporary style in a compact, high-quality design. With its bold bicolour cover and premium construction, this diary is ideal for those who seek a modern solution to their planning needs. The Quarto size offers a spacious layout, making it perfect for professionals, creatives, or anyone who needs ample space for their weekly appointments and tasks._x000D_\n_x000D_\nFeaturing a week-to-view format, the diary presents your schedule across two pages, allowing for easy organization of meetings, deadlines, and personal notes. The crisp white paper enhances readability and adds a touch of sophistication. The diary is also equipped with a ribbon marker and perimeter stitching, adding both durability and style to this must-have planning tool. With its sleek design and practical features, the Dorchester Bicolour Quarto Diary is perfect for anyone who wants a reliable, stylish companion for their week-to-week organization. | AN80: =IFERROR(_xlfn.LET(_xlpm.v,INDEX('product-export-27-8-2026'!$A:$AJ,MATCH($A80,'product-export-27-8-2026'!$A:$A,0),MATCH(AN$1,'product-export-27-8-2026'!$1:$1,0)),IF(_xlpm.v="","",_xlpm.v)),"") | AO80: =IFERROR(_xlfn.LET(_xlpm.v,INDEX('product-export-27-8-2026'!$A:$AJ,MATCH($A80,'product-export-27-8-2026'!$A:$A,0),MATCH(AO$1,'product-export-27-8-2026'!$1:$1,0)),IF(_xlpm.v="","",_xlpm.v)),"") | AP80: =IFERROR(_xlfn.LET(_xlpm.v,INDEX('product-export-27-8-2026'!$A:$AJ,MATCH($A80,'product-export-27-8-2026'!$A:$A,0),MATCH(AP$1,'product-export-27-8-2026'!$1:$1,0)),IF(_xlpm.v="","",_xlpm.v)),"") | AQ80: =IFERROR(_xlfn.LET(_xlpm.v,INDEX('product-export-27-8-2026'!$A:$AJ,MATCH($A80,'product-export-27-8-2026'!$A:$A,0),MATCH(AQ$1,'product-export-27-8-2026'!$1:$1,0)),IF(_xlpm.v="","",_xlpm.v)),"") | AR80: =IFERROR(_xlfn.LET(_xlpm.v,INDEX('product-export-27-8-2026'!$A:$AJ,MATCH($A80,'product-export-27-8-2026'!$A:$A,0),MATCH(AR$1,'product-export-27-8-2026'!$1:$1,0)),IF(_xlpm.v="","",_xlpm.v)),"") -> Diaries, Dorchester Collection, Diaries > Quarto Diary, Diaries > Quarto Diary > Quarto WTV | AS80: =IFERROR(_xlfn.LET(_xlpm.v,INDEX('product-export-27-8-2026'!$A:$AJ,MATCH($A80,'product-export-27-8-2026'!$A:$A,0),MATCH(AS$1,'product-export-27-8-2026'!$1:$1,0)),IF(_xlpm.v="","",_xlpm.v)),"") -> Dorchester-Horizon-Quarto-Desk-Diary-Week-to-View
A81: 1016 | B81: Dorchester Horizon Quarto Desk Dairy, Week to View, Black-Yellow | C81: Diary | D81: HZ-BK/YE-P-084 | E81: HZ-BK/YE-P-084 | F81: HZ84P | G81: Quarto | H81: Black-Yellow | I81: Week to View | J81: Cream | K81: 27mm x 27mm | L81: 0.48 | M81: 16.99 | N81: 1:16.79;10:16.09;25:11.80;50:10.67;100:9.71;250:9.64;500:8.50;750:7.95;1000:7.36; | O81: =IFERROR(VALUE(_xlfn.TEXTBEFORE(_xlfn.TEXTAFTER(";"&$N81,";"&SUBSTITUTE(O$1,"Qty ","")&":"),";")),"") -> 16.79 | P81: =IFERROR(VALUE(_xlfn.TEXTBEFORE(_xlfn.TEXTAFTER(";"&$N81,";"&SUBSTITUTE(P$1,"Qty ","")&":"),";")),"") -> 16.09 | Q81: =IFERROR(VALUE(_xlfn.TEXTBEFORE(_xlfn.TEXTAFTER(";"&$N81,";"&SUBSTITUTE(Q$1,"Qty ","")&":"),";")),"") -> 11.8 | R81: =IFERROR(VALUE(_xlfn.TEXTBEFORE(_xlfn.TEXTAFTER(";"&$N81,";"&SUBSTITUTE(R$1,"Qty ","")&":"),";")),"") -> 10.67 | S81: =IFERROR(VALUE(_xlfn.TEXTBEFORE(_xlfn.TEXTAFTER(";"&$N81,";"&SUBSTITUTE(S$1,"Qty ","")&":"),";")),"") -> 9.71 | T81: =IFERROR(VALUE(_xlfn.TEXTBEFORE(_xlfn.TEXTAFTER(";"&$N81,";"&SUBSTITUTE(T$1,"Qty ","")&":"),";")),"") -> 9.64 | U81: =IFERROR(VALUE(_xlfn.TEXTBEFORE(_xlfn.TEXTAFTER(";"&$N81,";"&SUBSTITUTE(U$1,"Qty ","")&":"),";")),"") -> 8.5 | V81: =IFERROR(VALUE(_xlfn.TEXTBEFORE(_xlfn.TEXTAFTER(";"&$N81,";"&SUBSTITUTE(V$1,"Qty ","")&":"),";")),"") -> 7.95 | W81: =IFERROR(VALUE(_xlfn.TEXTBEFORE(_xlfn.TEXTAFTER(";"&$N81,";"&SUBSTITUTE(W$1,"Qty ","")&":"),";")),"") -> 7.36 | X81: {=IF(Y81="","",_xlfn.TEXTJOIN(";",TRUE,SUBSTITUTE($Y$1:$AG$1,"Qty ","")&":"&TEXT(Y81:AG81,"0.00"))&";")} -> 1:22.91;10:21.60;25:16.69;50:14.75;100:13.43;250:13.03;500:11.77;750:11.22;1000:10.54; | Y81: ='Blocking Prices'!$C$16+O81 -> 22.91 | Z81: ='Blocking Prices'!$D$16+P81 -> 21.6 | AA81: ='Blocking Prices'!$E$16+Q81 -> 16.69 | AB81: ='Blocking Prices'!$F$16+R81 -> 14.75 | AC81: ='Blocking Prices'!$G$16+S81 -> 13.43 | AD81: ='Blocking Prices'!$H$16+T81 -> 13.03 | AE81: ='Blocking Prices'!$I$16+U81 -> 11.77 | AF81: ='Blocking Prices'!$J$16+V81 -> 11.22 | AG81: ='Blocking Prices'!$K$16+W81 -> 10.54 | AL81: Stay organized with the Dorchester Bicolor Quarto Diary - Week to View. With a sleek one or two design,?cream paper?paper, and a spacious week-to-view layout, this stylish diary is perfect for keeping track of your week in a modern, professional format. | AM81: The Dorchester Bicolour Quarto Diary - White Paper ? Week to View brings together functionality and contemporary style in a compact, high-quality design. With its bold bicolour cover and premium construction, this diary is ideal for those who seek a modern solution to their planning needs. The Quarto size offers a spacious layout, making it perfect for professionals, creatives, or anyone who needs ample space for their weekly appointments and tasks._x000D_\n_x000D_\nFeaturing a week-to-view format, the diary presents your schedule across two pages, allowing for easy organization of meetings, deadlines, and personal notes. The crisp white paper enhances readability and adds a touch of sophistication. The diary is also equipped with a ribbon marker and perimeter stitching, adding both durability and style to this must-have planning tool. With its sleek design and practical features, the Dorchester Bicolour Quarto Diary is perfect for anyone who wants a reliable, stylish companion for their week-to-week organization. | AN81: =IFERROR(_xlfn.LET(_xlpm.v,INDEX('product-export-27-8-2026'!$A:$AJ,MATCH($A81,'product-export-27-8-2026'!$A:$A,0),MATCH(AN$1,'product-export-27-8-2026'!$1:$1,0)),IF(_xlpm.v="","",_xlpm.v)),"") | AO81: =IFERROR(_xlfn.LET(_xlpm.v,INDEX('product-export-27-8-2026'!$A:$AJ,MATCH($A81,'product-export-27-8-2026'!$A:$A,0),MATCH(AO$1,'product-export-27-8-2026'!$1:$1,0)),IF(_xlpm.v="","",_xlpm.v)),"") | AP81: =IFERROR(_xlfn.LET(_xlpm.v,INDEX('product-export-27-8-2026'!$A:$AJ,MATCH($A81,'product-export-27-8-2026'!$A:$A,0),MATCH(AP$1,'product-export-27-8-2026'!$1:$1,0)),IF(_xlpm.v="","",_xlpm.v)),"") | AQ81: =IFERROR(_xlfn.LET(_xlpm.v,INDEX('product-export-27-8-2026'!$A:$AJ,MATCH($A81,'product-export-27-8-2026'!$A:$A,0),MATCH(AQ$1,'product-export-27-8-2026'!$1:$1,0)),IF(_xlpm.v="","",_xlpm.v)),"") | AR81: =IFERROR(_xlfn.LET(_xlpm.v,INDEX('product-export-27-8-2026'!$A:$AJ,MATCH($A81,'product-export-27-8-2026'!$A:$A,0),MATCH(AR$1,'product-export-27-8-2026'!$1:$1,0)),IF(_xlpm.v="","",_xlpm.v)),"") -> Diaries, Dorchester Collection, Diaries > Quarto Diary, Diaries > Quarto Diary > Quarto WTV | AS81: =IFERROR(_xlfn.LET(_xlpm.v,INDEX('product-export-27-8-2026'!$A:$AJ,MATCH($A81,'product-export-27-8-2026'!$A:$A,0),MATCH(AS$1,'product-export-27-8-2026'!$1:$1,0)),IF(_xlpm.v="","",_xlpm.v)),"") -> Dorchester-Horizon-Quarto-Desk-Diary-Week-to-View
A82: 1018 | B82: Dorchester Horizon Quarto Desk Diary, Week to View, Black-Grey | C82: Diary | D82: HZ-BK/GY-P-083 | E82: HZ-BK/GY-P-083 | F82: HZ84P | G82: Quarto | H82: Black-Grey | I82: Week to View | J82: Cream | K82: 27mm x 27mm | L82: 0.48 | M82: 16.99 | N82: 1:16.79;10:16.09;25:11.80;50:10.67;100:9.71;250:9.64;500:8.50;750:7.95;1000:7.36; | O82: =IFERROR(VALUE(_xlfn.TEXTBEFORE(_xlfn.TEXTAFTER(";"&$N82,";"&SUBSTITUTE(O$1,"Qty ","")&":"),";")),"") -> 16.79 | P82: =IFERROR(VALUE(_xlfn.TEXTBEFORE(_xlfn.TEXTAFTER(";"&$N82,";"&SUBSTITUTE(P$1,"Qty ","")&":"),";")),"") -> 16.09 | Q82: =IFERROR(VALUE(_xlfn.TEXTBEFORE(_xlfn.TEXTAFTER(";"&$N82,";"&SUBSTITUTE(Q$1,"Qty ","")&":"),";")),"") -> 11.8 | R82: =IFERROR(VALUE(_xlfn.TEXTBEFORE(_xlfn.TEXTAFTER(";"&$N82,";"&SUBSTITUTE(R$1,"Qty ","")&":"),";")),"") -> 10.67 | S82: =IFERROR(VALUE(_xlfn.TEXTBEFORE(_xlfn.TEXTAFTER(";"&$N82,";"&SUBSTITUTE(S$1,"Qty ","")&":"),";")),"") -> 9.71 | T82: =IFERROR(VALUE(_xlfn.TEXTBEFORE(_xlfn.TEXTAFTER(";"&$N82,";"&SUBSTITUTE(T$1,"Qty ","")&":"),";")),"") -> 9.64 | U82: =IFERROR(VALUE(_xlfn.TEXTBEFORE(_xlfn.TEXTAFTER(";"&$N82,";"&SUBSTITUTE(U$1,"Qty ","")&":"),";")),"") -> 8.5 | V82: =IFERROR(VALUE(_xlfn.TEXTBEFORE(_xlfn.TEXTAFTER(";"&$N82,";"&SUBSTITUTE(V$1,"Qty ","")&":"),";")),"") -> 7.95 | W82: =IFERROR(VALUE(_xlfn.TEXTBEFORE(_xlfn.TEXTAFTER(";"&$N82,";"&SUBSTITUTE(W$1,"Qty ","")&":"),";")),"") -> 7.36 | X82: {=IF(Y82="","",_xlfn.TEXTJOIN(";",TRUE,SUBSTITUTE($Y$1:$AG$1,"Qty ","")&":"&TEXT(Y82:AG82,"0.00"))&";")} -> 1:22.91;10:21.60;25:16.69;50:14.75;100:13.43;250:13.03;500:11.77;750:11.22;1000:10.54; | Y82: ='Blocking Prices'!$C$16+O82 -> 22.91 | Z82: ='Blocking Prices'!$D$16+P82 -> 21.6 | AA82: ='Blocking Prices'!$E$16+Q82 -> 16.69 | AB82: ='Blocking Prices'!$F$16+R82 -> 14.75 | AC82: ='Blocking Prices'!$G$16+S82 -> 13.43 | AD82: ='Blocking Prices'!$H$16+T82 -> 13.03 | AE82: ='Blocking Prices'!$I$16+U82 -> 11.77 | AF82: ='Blocking Prices'!$J$16+V82 -> 11.22 | AG82: ='Blocking Prices'!$K$16+W82 -> 10.54 | AL82: Stay organized with the Dorchester Bicolor Quarto Diary - Week to View. With a sleek one or two design,?cream paper?paper, and a spacious week-to-view layout, this stylish diary is perfect for keeping track of your week in a modern, professional format._x000D_\n_x000D_\n&nbsp; | AM82: The Dorchester Bicolour Quarto Diary - White Paper ? Week to View brings together functionality and contemporary style in a compact, high-quality design. With its bold bicolour cover and premium construction, this diary is ideal for those who seek a modern solution to their planning needs. The Quarto size offers a spacious layout, making it perfect for professionals, creatives, or anyone who needs ample space for their weekly appointments and tasks._x000D_\n_x000D_\nFeaturing a week-to-view format, the diary presents your schedule across two pages, allowing for easy organization of meetings, deadlines, and personal notes. The crisp white paper enhances readability and adds a touch of sophistication. The diary is also equipped with a ribbon marker and perimeter stitching, adding both durability and style to this must-have planning tool. With its sleek design and practical features, the Dorchester Bicolour Quarto Diary is perfect for anyone who wants a reliable, stylish companion for their week-to-week organization. | AN82: =IFERROR(_xlfn.LET(_xlpm.v,INDEX('product-export-27-8-2026'!$A:$AJ,MATCH($A82,'product-export-27-8-2026'!$A:$A,0),MATCH(AN$1,'product-export-27-8-2026'!$1:$1,0)),IF(_xlpm.v="","",_xlpm.v)),"") | AO82: =IFERROR(_xlfn.LET(_xlpm.v,INDEX('product-export-27-8-2026'!$A:$AJ,MATCH($A82,'product-export-27-8-2026'!$A:$A,0),MATCH(AO$1,'product-export-27-8-2026'!$1:$1,0)),IF(_xlpm.v="","",_xlpm.v)),"") | AP82: =IFERROR(_xlfn.LET(_xlpm.v,INDEX('product-export-27-8-2026'!$A:$AJ,MATCH($A82,'product-export-27-8-2026'!$A:$A,0),MATCH(AP$1,'product-export-27-8-2026'!$1:$1,0)),IF(_xlpm.v="","",_xlpm.v)),"") | AQ82: =IFERROR(_xlfn.LET(_xlpm.v,INDEX('product-export-27-8-2026'!$A:$AJ,MATCH($A82,'product-export-27-8-2026'!$A:$A,0),MATCH(AQ$1,'product-export-27-8-2026'!$1:$1,0)),IF(_xlpm.v="","",_xlpm.v)),"") | AR82: =IFERROR(_xlfn.LET(_xlpm.v,INDEX('product-export-27-8-2026'!$A:$AJ,MATCH($A82,'product-export-27-8-2026'!$A:$A,0),MATCH(AR$1,'product-export-27-8-2026'!$1:$1,0)),IF(_xlpm.v="","",_xlpm.v)),"") -> Diaries, Dorchester Collection, Diaries > Quarto Diary, Diaries > Quarto Diary > Quarto WTV | AS82: =IFERROR(_xlfn.LET(_xlpm.v,INDEX('product-export-27-8-2026'!$A:$AJ,MATCH($A82,'product-export-27-8-2026'!$A:$A,0),MATCH(AS$1,'product-export-27-8-2026'!$1:$1,0)),IF(_xlpm.v="","",_xlpm.v)),"") -> Dorchester-Horizon-Quarto-Desk-Diary-Week-to-View
A83: 1020 | B83: Dorchester Horizon Quarto Desk Diary, Week to View, Black-Red | C83: Diary | D83: HZ-BK/RD-P-083 | E83: HZ-BK/RD-P-083 | F83: HZ84P | G83: Quarto | H83: Black-Red | I83: Week to View | J83: Cream | K83: 27mm x 27mm | L83: 0.48 | M83: 16.99 | N83: 1:16.79;10:16.09;25:11.80;50:10.67;100:9.71;250:9.64;500:8.50;750:7.95;1000:7.36; | O83: =IFERROR(VALUE(_xlfn.TEXTBEFORE(_xlfn.TEXTAFTER(";"&$N83,";"&SUBSTITUTE(O$1,"Qty ","")&":"),";")),"") -> 16.79 | P83: =IFERROR(VALUE(_xlfn.TEXTBEFORE(_xlfn.TEXTAFTER(";"&$N83,";"&SUBSTITUTE(P$1,"Qty ","")&":"),";")),"") -> 16.09 | Q83: =IFERROR(VALUE(_xlfn.TEXTBEFORE(_xlfn.TEXTAFTER(";"&$N83,";"&SUBSTITUTE(Q$1,"Qty ","")&":"),";")),"") -> 11.8 | R83: =IFERROR(VALUE(_xlfn.TEXTBEFORE(_xlfn.TEXTAFTER(";"&$N83,";"&SUBSTITUTE(R$1,"Qty ","")&":"),";")),"") -> 10.67 | S83: =IFERROR(VALUE(_xlfn.TEXTBEFORE(_xlfn.TEXTAFTER(";"&$N83,";"&SUBSTITUTE(S$1,"Qty ","")&":"),";")),"") -> 9.71 | T83: =IFERROR(VALUE(_xlfn.TEXTBEFORE(_xlfn.TEXTAFTER(";"&$N83,";"&SUBSTITUTE(T$1,"Qty ","")&":"),";")),"") -> 9.64 | U83: =IFERROR(VALUE(_xlfn.TEXTBEFORE(_xlfn.TEXTAFTER(";"&$N83,";"&SUBSTITUTE(U$1,"Qty ","")&":"),";")),"") -> 8.5 | V83: =IFERROR(VALUE(_xlfn.TEXTBEFORE(_xlfn.TEXTAFTER(";"&$N83,";"&SUBSTITUTE(V$1,"Qty ","")&":"),";")),"") -> 7.95 | W83: =IFERROR(VALUE(_xlfn.TEXTBEFORE(_xlfn.TEXTAFTER(";"&$N83,";"&SUBSTITUTE(W$1,"Qty ","")&":"),";")),"") -> 7.36 | X83: {=IF(Y83="","",_xlfn.TEXTJOIN(";",TRUE,SUBSTITUTE($Y$1:$AG$1,"Qty ","")&":"&TEXT(Y83:AG83,"0.00"))&";")} -> 1:22.91;10:21.60;25:16.69;50:14.75;100:13.43;250:13.03;500:11.77;750:11.22;1000:10.54; | Y83: ='Blocking Prices'!$C$16+O83 -> 22.91 | Z83: ='Blocking Prices'!$D$16+P83 -> 21.6 | AA83: ='Blocking Prices'!$E$16+Q83 -> 16.69 | AB83: ='Blocking Prices'!$F$16+R83 -> 14.75 | AC83: ='Blocking Prices'!$G$16+S83 -> 13.43 | AD83: ='Blocking Prices'!$H$16+T83 -> 13.03 | AE83: ='Blocking Prices'!$I$16+U83 -> 11.77 | AF83: ='Blocking Prices'!$J$16+V83 -> 11.22 | AG83: ='Blocking Prices'!$K$16+W83 -> 10.54 | AL83: Stay organized with the Dorchester Bicolor Quarto Diary - Week to View. With a sleek one or two design,?cream paper?paper, and a spacious week-to-view layout, this stylish diary is perfect for keeping track of your week in a modern, professional format. | AM83: The Dorchester Bicolour Quarto Diary - White Paper ? Week to View brings together functionality and contemporary style in a compact, high-quality design. With its bold bicolour cover and premium construction, this diary is ideal for those who seek a modern solution to their planning needs. The Quarto size offers a spacious layout, making it perfect for professionals, creatives, or anyone who needs ample space for their weekly appointments and tasks._x000D_\n_x000D_\nFeaturing a week-to-view format, the diary presents your schedule across two pages, allowing for easy organization of meetings, deadlines, and personal notes. The crisp white paper enhances readability and adds a touch of sophistication. The diary is also equipped with a ribbon marker and perimeter stitching, adding both durability and style to this must-have planning tool. With its sleek design and practical features, the Dorchester Bicolour Quarto Diary is perfect for anyone who wants a reliable, stylish companion for their week-to-week organization. | AN83: =IFERROR(_xlfn.LET(_xlpm.v,INDEX('product-export-27-8-2026'!$A:$AJ,MATCH($A83,'product-export-27-8-2026'!$A:$A,0),MATCH(AN$1,'product-export-27-8-2026'!$1:$1,0)),IF(_xlpm.v="","",_xlpm.v)),"") | AO83: =IFERROR(_xlfn.LET(_xlpm.v,INDEX('product-export-27-8-2026'!$A:$AJ,MATCH($A83,'product-export-27-8-2026'!$A:$A,0),MATCH(AO$1,'product-export-27-8-2026'!$1:$1,0)),IF(_xlpm.v="","",_xlpm.v)),"") | AP83: =IFERROR(_xlfn.LET(_xlpm.v,INDEX('product-export-27-8-2026'!$A:$AJ,MATCH($A83,'product-export-27-8-2026'!$A:$A,0),MATCH(AP$1,'product-export-27-8-2026'!$1:$1,0)),IF(_xlpm.v="","",_xlpm.v)),"") | AQ83: =IFERROR(_xlfn.LET(_xlpm.v,INDEX('product-export-27-8-2026'!$A:$AJ,MATCH($A83,'product-export-27-8-2026'!$A:$A,0),MATCH(AQ$1,'product-export-27-8-2026'!$1:$1,0)),IF(_xlpm.v="","",_xlpm.v)),"") | AR83: =IFERROR(_xlfn.LET(_xlpm.v,INDEX('product-export-27-8-2026'!$A:$AJ,MATCH($A83,'product-export-27-8-2026'!$A:$A,0),MATCH(AR$1,'product-export-27-8-2026'!$1:$1,0)),IF(_xlpm.v="","",_xlpm.v)),"") -> Diaries, Dorchester Collection, Diaries > Quarto Diary, Diaries > Quarto Diary > Quarto WTV | AS83: =IFERROR(_xlfn.LET(_xlpm.v,INDEX('product-export-27-8-2026'!$A:$AJ,MATCH($A83,'product-export-27-8-2026'!$A:$A,0),MATCH(AS$1,'product-export-27-8-2026'!$1:$1,0)),IF(_xlpm.v="","",_xlpm.v)),"") -> Dorchester-Horizon-Quarto-Desk-Diary-Week-to-View
A84: 1022 | B84: Graphic Prints Quarto Diary, Day Per Page, Full Colour | C84: Diary | D84: CX-44-P-082 | E84: CX-44-P-082 | F84: CXP82 | G84: Quarto | H84: Full Colour | I84: Day Per Page | J84: Cream | K84: 27mm x 27mm | L84: 0.48 | M84: 23.99 | N84: 1:22.08;10:21.08;25:13.90;50:10.69;100:9.32;250:6.49;500:6.24;750:6.04;1000:5.81; | O84: =IFERROR(VALUE(_xlfn.TEXTBEFORE(_xlfn.TEXTAFTER(";"&$N84,";"&SUBSTITUTE(O$1,"Qty ","")&":"),";")),"") -> 22.08 | P84: =IFERROR(VALUE(_xlfn.TEXTBEFORE(_xlfn.TEXTAFTER(";"&$N84,";"&SUBSTITUTE(P$1,"Qty ","")&":"),";")),"") -> 21.08 | Q84: =IFERROR(VALUE(_xlfn.TEXTBEFORE(_xlfn.TEXTAFTER(";"&$N84,";"&SUBSTITUTE(Q$1,"Qty ","")&":"),";")),"") -> 13.9 | R84: =IFERROR(VALUE(_xlfn.TEXTBEFORE(_xlfn.TEXTAFTER(";"&$N84,";"&SUBSTITUTE(R$1,"Qty ","")&":"),";")),"") -> 10.69 | S84: =IFERROR(VALUE(_xlfn.TEXTBEFORE(_xlfn.TEXTAFTER(";"&$N84,";"&SUBSTITUTE(S$1,"Qty ","")&":"),";")),"") -> 9.32 | T84: =IFERROR(VALUE(_xlfn.TEXTBEFORE(_xlfn.TEXTAFTER(";"&$N84,";"&SUBSTITUTE(T$1,"Qty ","")&":"),";")),"") -> 6.49 | U84: =IFERROR(VALUE(_xlfn.TEXTBEFORE(_xlfn.TEXTAFTER(";"&$N84,";"&SUBSTITUTE(U$1,"Qty ","")&":"),";")),"") -> 6.24 | V84: =IFERROR(VALUE(_xlfn.TEXTBEFORE(_xlfn.TEXTAFTER(";"&$N84,";"&SUBSTITUTE(V$1,"Qty ","")&":"),";")),"") -> 6.04 | W84: =IFERROR(VALUE(_xlfn.TEXTBEFORE(_xlfn.TEXTAFTER(";"&$N84,";"&SUBSTITUTE(W$1,"Qty ","")&":"),";")),"") -> 5.81 | X84: {=IF(Y84="","",_xlfn.TEXTJOIN(";",TRUE,SUBSTITUTE($Y$1:$AG$1,"Qty ","")&":"&TEXT(Y84:AG84,"0.00"))&";")} | AL84: Plan each day in style with the Graphic Prints Full Colour Quarto Diary - Day per Page. Featuring a customizable full-colour cover and premium cream paper, this diary provides ample space for detailed daily planning in an elegant, durable format._x000D_\n_x000D_\n&nbsp; | AM84: The Graphic PrintsFull Colour Quarto Diary - Cream Paper ? Day Per Page combines premium craftsmanship with customizable flair to provide an exceptional daily planner. Bound in high-quality Graphic Prints material, this diary features a smooth and durable full-colour cover, ideal for those looking for a personalized design. Whether for corporate branding, gifts, or personal use, the vibrant cover can be fully customized to reflect your unique style, making it both functional and eye-catching._x000D_\n_x000D_\nWith a day-per-page layout, this diary offers an organized and spacious format for your daily appointments, meetings, tasks, and notes. The cream paper provides a soft, professional touch, reducing glare and enhancing the readability of your writing. The Quarto size offers generous space to plan your day in detail, while the ribbon marker and sturdy perimeter stitching ensure easy navigation and durability throughout the year. Whether you?re managing a busy schedule or jotting down personal thoughts, the Graphic Prints Full Colour Quarto Diary is the perfect choice for staying organized with style. | AN84: =IFERROR(_xlfn.LET(_xlpm.v,INDEX('product-export-27-8-2026'!$A:$AJ,MATCH($A84,'product-export-27-8-2026'!$A:$A,0),MATCH(AN$1,'product-export-27-8-2026'!$1:$1,0)),IF(_xlpm.v="","",_xlpm.v)),"") | AO84: =IFERROR(_xlfn.LET(_xlpm.v,INDEX('product-export-27-8-2026'!$A:$AJ,MATCH($A84,'product-export-27-8-2026'!$A:$A,0),MATCH(AO$1,'product-export-27-8-2026'!$1:$1,0)),IF(_xlpm.v="","",_xlpm.v)),"") | AP84: =IFERROR(_xlfn.LET(_xlpm.v,INDEX('product-export-27-8-2026'!$A:$AJ,MATCH($A84,'product-export-27-8-2026'!$A:$A,0),MATCH(AP$1,'product-export-27-8-2026'!$1:$1,0)),IF(_xlpm.v="","",_xlpm.v)),"") | AQ84: =IFERROR(_xlfn.LET(_xlpm.v,INDEX('product-export-27-8-2026'!$A:$AJ,MATCH($A84,'product-export-27-8-2026'!$A:$A,0),MATCH(AQ$1,'product-export-27-8-2026'!$1:$1,0)),IF(_xlpm.v="","",_xlpm.v)),"") | AR84: =IFERROR(_xlfn.LET(_xlpm.v,INDEX('product-export-27-8-2026'!$A:$AJ,MATCH($A84,'product-export-27-8-2026'!$A:$A,0),MATCH(AR$1,'product-export-27-8-2026'!$1:$1,0)),IF(_xlpm.v="","",_xlpm.v)),"") -> Diaries, Graphic Print Collection, Diaries > Quarto Diary, Diaries > Quarto Diary > Quarto DPP | AS84: =IFERROR(_xlfn.LET(_xlpm.v,INDEX('product-export-27-8-2026'!$A:$AJ,MATCH($A84,'product-export-27-8-2026'!$A:$A,0),MATCH(AS$1,'product-export-27-8-2026'!$1:$1,0)),IF(_xlpm.v="","",_xlpm.v)),"") -> Graphic-Prints-Quarto-Diary-Week-to-View
